Workbook

Sheet Leaderboard
B1: Account Executive Name | C1: Mega Region | D1: Channel | E1: H2'21 NB Quota | F1: H2'21 CO Quota | G1: H2 Total Quota | H1: Tenure based ramp status | I1: Status as of 12/31
B2: Rep1 | C2: APACx | D2: MM | E2: 52500 | F2: 0 | G2: 52500 | H2: Fully ramped | I2: active
B3: Rep2 | C3: MEA | D3: MM | E3: 37994 | F3: 0 | G3: 37994 | H3: Fully ramped | I3: active
B4: Rep3 | C4: MEA | D4: MM | E4: 152587 | F4: 210000 | G4: 362587 | H4: Fully ramped | I4: active
B5: Rep4 | C5: LatAm | D5: SMB | E5: 60000 | F5: 0 | G5: 60000 | H5: Partially ramped | I5: active
B6: Rep5 | C6: APACx | D6: MM | E6: 285319 | F6: 0 | G6: 285319 | H6: Fully ramped | I6: active
B7: Rep6 | C7: APACx | D7: ENT | E7: 189668 | F7: 0 | G7: 189668 | H7: Partially ramped | I7: active
B8: Rep7 | C8: US&Can | D8: SMB | E8: 103950 | F8: 0 | G8: 103950 | H8: Partially ramped | I8: active
B9: Rep8 | C9: LatAm | D9: ENT | E9: 140250 | F9: 0 | G9: 140250 | H9: Partially ramped | I9: active
B10: Rep9 | C10: LatAm | D10: ENT | E10: 115500 | F10: 0 | G10: 115500 | H10: Partially ramped | I10: active
B11: Rep10 | C11: APACx | D11: ENT | E11: 25462 | F11: 0 | G11: 25462 | H11: Partially ramped | I11: active
B12: Rep11 | C12: LatAm | D12: MM | E12: 109725 | F12: 0 | G12: 109725 | H12: Partially ramped | I12: active
B13: Rep12 | C13: APACx | D13: ENT | E13: 189668 | F13: 0 | G13: 189668 | H13: Partially ramped | I13: active
... B186: Rep195 | C186: APACx | D186: ENT | E186: 0 | F186: 0 | G186: 0 | H186: No quota | I186: active

Sheet Attainment Query Data
A1: Unique Dashboard ID | B1: Salesforce Opportunity ID | C1: Salesforce Account ID | D1: Opportunity owner (Account Executive) | E1: Mega region | F1: Channel | G1: Close Date | H1: Product | I1: NB GB (USD) | J1: CO GB (USD) | K1: Total $GB (USD) | L1: Customer Use Case
A2: 0001356c-8549-5751-a23b-0ce25238c4da | B2: 0064z000026LAomAAG | C2: 0014z00001giwevAAA | D2: Rep84 | E2: US&Can | F2: MM | G2: 44536 | H2: eats vouchers | I2: 801.72 | J2: 0 | K2: 801.72 | L2: Eats Vouchers - Recruiting
A3: 000a4a29-6642-4f59-88a5-6b302c1311fd | B3: 0064z000025lMeGAAU | C3: 0014z00001fzJkJAAU | D3: Rep94 | E3: US&Can | F3: ENT | G3: 44474 | H3: eats vouchers | I3: 1632 | J3: 0 | K3: 1632 | L3: Vouchers - Courtesy Meals
A4: 00124a2c-834d-4909-8198-9e6755a2b542 | B4: 0063k00000zHY5pAAG | C4: 0013k00002qQTLzAAO | D4: Rep31 | E4: Europe | F4: MM | G4: 44223 | H4: eats | I4: 0 | J4: 34.84 | K4: 34.84 | L4: eats - Work From Home Meals
A5: 001e2ee0-5b47-403f-a8d6-0740c70c0ebd | B5: 0063k000010YVvAAAW | C5: 0013k00002w922LAAQ | D5: Rep163 | E5: India | F5: ENT | G5: 44291 | H5: central | I5: 0 | J5: 20.71 | K5: 20.71 | L5: Central - Delivery
A6: 001ef1a0-f6d7-568e-b31d-4e56e75a456e | B6: 0064z000026LLkmAAG | C6: 0014z00001hJZEoAAO | D6: Rep186 | E6: US&Can | F6: SMB | G6: 44543 | H6: vouchers | I6: 239.59 | J6: 0 | K6: 239.59 | L6: Rides Vouchers - One-time event transportation
A7: 00372079-d375-5cdb-a137-d2111ea1e2b4 | B7: 0064z000025lFsMAAU | C7: 0014z00001fz1F5AAI | D7: Rep100 | E7: US&Can | F7: ENT | G7: 44517 | H7: eats vouchers | I7: 479.76 | J7: 0 | K7: 479.76 | L7: Eats Vouchers - Employee benefit / reward
A8: 00413e02-ac02-4141-af13-bb65a25d73c2 | B8: 0064z000025ho6mAAA | C8: 0014z00001fHCH9AAO | D8: Rep162 | E8: India | F8: MM | G8: 44473 | H8: travel | I8: 136.23 | J8: 0 | K8: 136.23 | L8: Travel - Business Travel
A9: 00431f67-6716-46da-ba41-daf05ee6894b | B9: 0064z000024lWgSAAU | C9: 0014z00001cWHRKAA4 | D9: Rep162 | E9: India | F9: MM | G9: 44367 | H9: central | I9: 0 | J9: 27.91 | K9: 27.91 | L9: Travel - Business Travel
A10: 00431f67-6716-46da-ba41-daf05ee6894b | B10: 0064z000024lWgSAAU | C10: 0014z00001cWHRKAA4 | D10: Rep162 | E10: India | F10: MM | G10: 44367 | H10: travel | I10: 0 | J10: 353.32 | K10: 353.32 | L10: Travel - Business Travel
A11: 004c3925-a7e2-5558-8b4b-3bec3ee91367 | B11: 0064z000025jYazAAE | C11: 0013k00002jMlxyAAC | D11: Rep23 | E11: US&Can | F11: SMB | G11: 44425 | H11: vouchers | I11: 1252.73 | J11: 0 | K11: 1252.73 | L11: Vouchers - Courtesy Rides
A12: 004c62a8-ab69-405d-8ed9-aad8446e5832 | B12: 0063k00000zHWpEAAW | C12: 0013k00002jMdkKAAS | D12: Rep27 | E12: US&Can | F12: MM | G12: 44440 | H12: eats | I12: 27.65 | J12: 0 | K12: 27.65 | L12: eats - Work From Home Meals
A13: 004cca28-bb39-4118-bab6-f21c18af24b2 | B13: 0063k000010SZEmAAO | C13: 0013k00002t7rxPAAQ | D13: Rep115 | E13: Europe | F13: MM | G13: 44211 | H13: travel | I13: 0 | J13: 42.34 | K13: 42.34 | L13: Travel - Business Travel
... A38: 00d3c6ef-05bd-593e-9273-95f832d6c420 | B38: 0064z000026L1gpAAC | C38: 0014z00001hItWLAA0 | D38: Rep38 | E38: US&Can | F38: SMB | G38: 44538 | H38: travel | I38: 646.32 | J38: 0 | K38: 646.32 | L38: Travel - Business Travel
A39: 00d47f12-ddd3-422a-9149-be3de840ae8c | B39: 0064z000025lANVAA2 | C39: 0013k00002jQ0qNAAS | D39: Rep68 | E39: #N/A | F39: #N/A | G39: 44468 | H39: eats vouchers | I39: 396.43 | J39: 0 | K39: 396.43 | L39: Vouchers - Employee Morale
A40: 00d92a0d-13e5-5cd8-aa6a-4698262eef35 | B40: 0064z000025kCOLAA2 | C40: 0013k00002iUXT0AAO | D40: Rep14 | E40: US&Can | F40: SMB | G40: 44441 | H40: central | I40: 8733.56 | J40: 0 | K40: 8733.56 | L40: Central - Delivery
A41: 00d92a0d-13e5-5cd8-aa6a-4698262eef35 | B41: 0064z000025kCOLAA2 | C41: 0013k00002iUXT0AAO | D41: Rep14 | E41: US&Can | F41: SMB | G41: 44441 | H41: eats vouchers | I41: 691.43 | J41: 0 | K41: 691.43 | L41: Central - Delivery
A42: 00e63c99-78c7-4943-9698-0849978712a0 | B42: 0064z000025hUV1AAM | C42: 0013k00002jQ0hYAAS | D42: Rep47 | E42: US&Can | F42: ENT | G42: 44399 | H42: eats vouchers | I42: 140.19 | J42: 0 | K42: 140.19 | L42: Vouchers - Courtesy Meals
A43: 00fe5137-2936-482e-abab-1eb044d448ff | B43: 0063k000011LSLRAA4 | C43: 0013k00002jNjeSAAS | D43: Rep50 | E43: US&Can | F43: MM | G43: 44330 | H43: central | I43: 0 | J43: 1011.8 | K43: 1011.8 | L43: Travel - Business Travel
A44: 00fe5137-2936-482e-abab-1eb044d448ff | B44: 0063k000011LSLRAA4 | C44: 0013k00002jNjeSAAS | D44: Rep50 | E44: US&Can | F44: MM | G44: 44330 | H44: travel | I44: 0 | J44: 4785.96 | K44: 4785.96 | L44: Travel - Business Travel
A45: 01021b7d-6132-4ed6-a39e-2883cc1bf94a | B45: 0064z000024mmt1AAA | C45: 0013k00002jM19EAAS | D45: Rep36 | E45: US&Can | F45: MM | G45: 44334 | H45: travel | I45: 0 | J45: 3840.16 | K45: 3840.16 | L45: Travel - Commute
A46: 010235fc-2a57-45fc-a45c-e4a8b05c096e | B46: 0064z000025hoX5AAI | C46: 0013k00002jQAsnAAG | D46: Rep36 | E46: US&Can | F46: MM | G46: 44495 | H46: eats vouchers | I46: 4474.98 | J46: 0 | K46: 4474.98 | L46: Vouchers - Incentive / Promotional Tool
A47: 010235fc-2a57-45fc-a45c-e4a8b05c096e | B47: 0064z000025hoX5AAI | C47: 0013k00002jQAsnAAG | D47: Rep36 | E47: US&Can | F47: MM | G47: 44495 | H47: vouchers | I47: 10125.34 | J47: 0 | K47: 10125.34 | L47: Vouchers - Incentive / Promotional Tool
A48: 010bdc58-495a-5170-8dea-ab0058e18dc0 | B48: 0064z000025kbqgAAA | C48: 0014z00001fxIlnAAE | D48: Rep4 | E48: LatAm | F48: SMB | G48: 44452 | H48: travel | I48: 242.85 | J48: 0 | K48: 242.85 | L48: Travel - Business Travel; Travel - Commute
A49: 010bdc58-495a-5170-8dea-ab0058e18dc0 | B49: 0064z000025kbqgAAA | C49: 0014z00001fxIlnAAE | D49: Rep4 | E49: LatAm | F49: SMB | G49: 44452 | H49: vouchers | I49: 182.29 | J49: 0 | K49: 182.29 | L49: Travel - Business Travel; Travel - Commute
A50: 01164f98-bc59-4fdb-b2ad-d702504e8c99 | B50: 0064z000026JD4rAAG | C50: 0013k00002jQ0qKAAS | D50: Rep96 | E50: US&Can | F50: MM | G50: 44489 | H50: eats vouchers | I50: 225.47 | J50: 0 | K50: 225.47 | L50: Vouchers - Courtesy Meals
A51: 011bb750-1461-4460-b0d0-247546ded438 | B51: 0063k000011LxUnAAK | C51: 0013k00002jKxtWAAS | D51: Rep65 | E51: US&Can | F51: MM | G51: 44363 | H51: eats vouchers | I51: 0 | J51: 159.23 | K51: 159.23 | L51: eats - Work From Home Meals
... A56: 01364f92-aca4-4010-94ef-ed83581a7368 | B56: 0064z000025hZi5AAE | C56: 0013k00002lcNgkAAE | D56: Rep117 | E56: MEA | F56: MM | G56: 44378 | H56: travel | I56: 249.99 | J56: 0 | K56: 249.99 | L56: Travel - Business Travel
A57: 013afb3b-cae7-40df-8e2c-e4d497b89a1e | B57: 0063k000010TAxqAAG | C57: 0013k00002jLNWGAA4 | D57: Rep68 | E57: #N/A | F57: #N/A | G57: 44298 | H57: eats vouchers | I57: 0 | J57: 8205.17 | K57: 8205.17 | L57: Vouchers - Courtesy Meals
A58: 013b08d0-d382-4cb7-a45a-818764d44fa8 | B58: 0063k000010YC8ZAAW | C58: 0013k00002iW2baAAC | D58: Rep66 | E58: US&Can | F58: ENT | G58: 44243 | H58: eats vouchers | I58: 0 | J58: 1104.83 | K58: 1104.83 | L58: Vouchers - Courtesy Meals
A59: 013bda93-b809-4ea7-892f-7c43255bc386 | B59: 0064z000025kG3vAAE | C59: 0014z00001fPrQaAAK | D59: Rep23 | E59: US&Can | F59: SMB | G59: 44459 | H59: travel | I59: 134.88 | J59: 0 | K59: 134.88 | L59: Travel - Business Travel
A60: 013cd016-b06a-46d9-9a70-8915ef890879 | B60: 0064z000026K55LAAS | C60: 0013k00002jNSn2AAG | D60: Rep89 | E60: US&Can | F60: MM | G60: 44508 | H60: eats | I60: 67.57 | J60: 0 | K60: 67.57 | L60: Travel - Business Travel; Travel - Commute
A61: 013cd016-b06a-46d9-9a70-8915ef890879 | B61: 0064z000026K55LAAS | C61: 0013k00002jNSn2AAG | D61: Rep89 | E61: US&Can | F61: MM | G61: 44508 | H61: travel | I61: 1742.73 | J61: 0 | K61: 1742.73 | L61: Travel - Business Travel; Travel - Commute
A62: 0145aa52-f0a8-4438-b267-919d6d7372ef | B62: 0064z000024mhStAAI | C62: 0013k00002iWNawAAG | D62: Rep61 | E62: LatAm | F62: MM | G62: 44484 | H62: central | I62: 3907.36 | J62: 0 | K62: 3907.36 | L62: Central - Commute
A63: 0145aa52-f0a8-4438-b267-919d6d7372ef | B63: 0064z000024mhStAAI | C63: 0013k00002iWNawAAG | D63: Rep61 | E63: LatAm | F63: MM | G63: 44484 | H63: travel | I63: 96.37 | J63: 0 | K63: 96.37 | L63: Central - Commute
A64: 014b36b9-0d7f-4eea-aafe-f66e87baeatsa | B64: 0064z000024m2LdAAI | C64: 0014z00001cXRxiAAG | D64: Rep71 | E64: LatAm | F64: MM | G64: 44326 | H64: travel | I64: 0 | J64: 880.87 | K64: 880.87 | L64: Travel - Business Travel
A65: 01579b76-50fb-5309-bf22-9edd68453759 | B65: 0064z000025kfY3AAI | C65: 0013k00002jKoQIAA0 | D65: Rep76 | E65: US&Can | F65: SMB | G65: 44459 | H65: vouchers | I65: 8123.29 | J65: 0 | K65: 8123.29 | L65: Vouchers - Courtesy Rides
A66: 0163be36-7305-4563-8bdc-7404ab0a2dfe | B66: 0064z000025i6lgAAA | C66: 0013k00002jP65CAAS | D66: Rep23 | E66: US&Can | F66: SMB | G66: 44403 | H66: travel | I66: 6299.94 | J66: 0 | K66: 6299.94 | L66: GC - Employee Morale
A67: 0166b862-edc8-4c01-8a0e-0f1102712ada | B67: 0064z000025hm54AAA | C67: 0014z00001eyJJjAAM | D67: Rep1 | E67: APACx | F67: MM | G67: 44389 | H67: eats vouchers | I67: 599.76 | J67: 0 | K67: 599.76 | L67: Vouchers - Employee Morale
A68: 01691228-00ae-45f0-a5d6-c0f5e6a6c9fc | B68: 0064z000024nOSYAA2 | C68: 0013k00002iUXx3AAG | D68: Rep91 | E68: US&Can | F68: MM | G68: 44362 | H68: eats vouchers | I68: 0 | J68: 649.15 | K68: 649.15 | L68: Vouchers - Courtesy Meals
A69: 016eb583-f812-4c4e-83bb-47c44739ea6b | B69: 0064z000026LiHlAAK | C69: 0013k00002iW2baAAC | D69: Rep66 | E69: US&Can | F69: ENT | G69: 44544 | H69: eats vouchers | I69: 262.13 | J69: 0 | K69: 262.13 | L69: Eats Vouchers - Employee benefit / reward
... A112: 02a74480-c233-4e7c-b592-d0e2d8ba91ae | B112: 0063k000010YCiPAAW | C112: 0013k00002w84ESAAY | D112: Rep95 | E112: Europe | F112: MM | G112: 44379 | H112: travel | I112: 45.28 | J112: 0 | K112: 45.28 | L112: eats - In-office Meals
A113: 02b1ab71-f7c5-4b03-934b-832bdb0b9607 | B113: 0063k000010SkLEAA0 | C113: 0013k00002jLNWGAA4 | D113: Rep68 | E113: #N/A | F113: #N/A | G113: 44258 | H113: eats vouchers | I113: 0 | J113: 641.96 | K113: 641.96 | L113: Vouchers - Courtesy Meals
A114: 02b3719a-02f2-5a2c-b393-86b8aae46421 | B114: 0064z000026KOaSAAW | C114: 0014z00001gjMOvAAM | D114: Rep18 | E114: US&Can | F114: SMB | G114: 44522 | H114: vouchers | I114: 667.4 | J114: 0 | K114: 667.4 | L114: Rides Vouchers - Employee benefit / reward
A115: 02b9f067-3fe3-418f-bce3-7ecd5a318664 | B115: 0064z000025jsnXAAQ | C115: 0013k00002jLVM6AAO | D115: Rep47 | E115: US&Can | F115: ENT | G115: 44433 | H115: central | I115: 653.97 | J115: 0 | K115: 653.97 | L115: Central - Delivery
A116: 02b9f067-3fe3-418f-bce3-7ecd5a318664 | B116: 0064z000025jsnXAAQ | C116: 0013k00002jLVM6AAO | D116: Rep47 | E116: US&Can | F116: ENT | G116: 44433 | H116: travel | I116: 34.05 | J116: 0 | K116: 34.05 | L116: Central - Delivery
A117: 02c884e9-10c8-4c07-afbd-3c09641e809a | B117: 0064z000025lMGxAAM | C117: 0014z00001fzJ1dAAE | D117: Rep117 | E117: MEA | F117: MM | G117: 44510 | H117: travel | I117: 582.29 | J117: 0 | K117: 582.29 | L117: Travel - Business Travel
A118: 02d0247a-dfad-4290-a2ee-de5df8456547 | B118: 0064z000024mcbHAAQ | C118: 0013k00002jMtX2AAK | D118: Rep102 | E118: LatAm | F118: ENT | G118: 44392 | H118: travel | I118: 9640.93 | J118: 0 | K118: 9640.93 | L118: Travel - Commute
A119: 02d89e05-524e-4c48-a855-4820aa263147 | B119: 0064z000026KYSvAAO | C119: 0014z00001gjgTKAAY | D119: Rep101 | E119: US&Can | F119: SMB | G119: 44529 | H119: vouchers | I119: 431.01 | J119: 0 | K119: 431.01 | L119: Rides Vouchers - One-time event transportation
A120: 02da9676-7fb4-46a4-99ce-a59722449207 | B120: 0064z000026L1oSAAS | C120: 0013k00002iUU1eAAG | D120: Rep65 | E120: US&Can | F120: MM | G120: 44532 | H120: eats vouchers | I120: 414.45 | J120: 0 | K120: 414.45 | L120: Eats Vouchers - One-time event meals
A121: 02e447c7-ce9c-4b29-8581-2f1534f0a50a | B121: 0063k000010T9ikAAC | C121: 0013k00002iWPRDAA4 | D121: Rep46 | E121: LatAm | F121: MM | G121: 44249 | H121: eats vouchers | I121: 0 | J121: 351.97 | K121: 351.97 | L121: Vouchers - Employee Morale
A122: 02e497f1-43a3-40d8-ae14-d99b90b2517d | B122: 0063k000011LoqGAAS | C122: 0013k00002nLSAOAA4 | D122: Rep5 | E122: APACx | F122: MM | G122: 44449 | H122: travel | I122: 46.44 | J122: 0 | K122: 46.44 | L122: Travel - Business Travel
A123: 02ea9d95-e028-4e9d-b6d6-37c4324d577c | B123: 0064z000025jV0bAAE | C123: 0013k00002jLOo5AAG | D123: Rep144 | E123: India | F123: MM | G123: 44435 | H123: central | I123: 2.28 | J123: 0 | K123: 2.28 | L123: Central - Courtesy Rides
A124: 02ea9d95-e028-4e9d-b6d6-37c4324d577c | B124: 0064z000025jV0bAAE | C124: 0013k00002jLOo5AAG | D124: Rep144 | E124: India | F124: MM | G124: 44435 | H124: travel | I124: 763.9 | J124: 0 | K124: 763.9 | L124: Central - Courtesy Rides
A125: 02ee6eef-89e2-45f9-a849-141b5d285cdc | B125: 0064z000026JqAjAAK | C125: 0013k00002jLwszAAC | D125: Rep35 | E125: US&Can | F125: MM | G125: 44503 | H125: vouchers | I125: 136.15 | J125: 0 | K125: 136.15 | L125: Rides Vouchers - Recurring event transportation
... A215: 0510d14f-0ad3-4f15-a90b-66a38aa9c877 | B215: 0064z000025kFruAAE | C215: 0014z00001fwYU3AAM | D215: Rep22 | E215: US&Can | F215: SMB | G215: 44441 | H215: vouchers | I215: 1116.66 | J215: 0 | K215: 1116.66 | L215: Vouchers - Courtesy Rides
A216: 051416bd-c543-495e-b9ba-d4a445dcd22e | B216: 0064z000025j30GAAQ | C216: 0013k00002iUU1fAAG | D216: Rep68 | E216: #N/A | F216: #N/A | G216: 44410 | H216: eats vouchers | I216: 191.15 | J216: 0 | K216: 191.15 | L216: Vouchers - Employee Morale
A217: 0515ec8b-7f30-5685-9ae8-6d1507837f6a | B217: 0064z000025l2k5AAA | C217: 0014z00001fygQTAAY | D217: Rep86 | E217: Europe | F217: MM | G217: 44473 | H217: central | I217: 307.38 | J217: 0 | K217: 307.38 | L217: Central - Courtesy Rides
A218: 0515ec8b-7f30-5685-9ae8-6d1507837f6a | B218: 0064z000025l2k5AAA | C218: 0014z00001fygQTAAY | D218: Rep86 | E218: Europe | F218: MM | G218: 44473 | H218: travel | I218: 1064.66 | J218: 0 | K218: 1064.66 | L218: Central - Courtesy Rides
A219: 05197510-a685-48d5-938b-0757788b7abb | B219: 0064z000025hyJvAAI | C219: 0013k00002qNhxBAAS | D219: Rep46 | E219: LatAm | F219: MM | G219: 44407 | H219: vouchers | I219: 279.61 | J219: 0 | K219: 279.61 | L219: Vouchers - Courtesy Rides
A220: 051b310a-06f9-4163-9fbb-a189a254e9fa | B220: 0064z000026LERGAA4 | C220: 0013k00002iUxlEAAS | D220: Rep21 | E220: LatAm | F220: SMB | G220: 44545 | H220: vouchers | I220: 15.01 | J220: 0 | K220: 15.01 | L220: Rides Vouchers - One-time event transportation
A221: 05217e3f-765b-43ce-84db-f8d5af303e04 | B221: 0064z000026Ke3SAAS | C221: 0013k00002jRUTeAAO | D221: Rep51 | E221: LatAm | F221: MM | G221: 44529 | H221: eats | I221: 22.97 | J221: 0 | K221: 22.97 | L221: eats - In-office Meals
A222: 05217e3f-765b-43ce-84db-f8d5af303e04 | B222: 0064z000025kUeAAAU | C222: 0013k00002jRUTeAAO | D222: Rep51 | E222: LatAm | F222: MM | G222: 44522 | H222: travel | I222: 506.11 | J222: 0 | K222: 506.11 | L222: Travel - Business Travel
A223: 0528947a-1948-4806-874c-8c1701939267 | B223: 0063k00000yahDPAAY | C223: 0013k00002iWFaGAAW | D223: Rep115 | E223: Europe | F223: MM | G223: 44395 | H223: travel | I223: 1254.74 | J223: 0 | K223: 1254.74 | L223: Travel - Business Travel; Travel - Commute
A224: 052c5937-8a1b-4b21-b9a2-db13052bee31 | B224: 0064z000025kXmdAAE | C224: 0014z00001fxH5nAAE | D224: Rep22 | E224: US&Can | F224: SMB | G224: 44467 | H224: travel | I224: 79.92 | J224: 0 | K224: 79.92 | L224: Travel - Business Travel
A225: 05329744-61f7-4628-852f-25b01aee2764 | B225: 0064z000026JQihAAG | C225: 0013k00002iUbKHAA0 | D225: Rep13 | E225: US&Can | F225: MM | G225: 44495 | H225: central | I225: 32815.37 | J225: 0 | K225: 32815.37 | L225: Central - Late Night Rides
A226: 05329744-61f7-4628-852f-25b01aee2764 | B226: 0064z000026JQihAAG | C226: 0013k00002iUbKHAA0 | D226: Rep13 | E226: US&Can | F226: MM | G226: 44495 | H226: travel | I226: 3074.82 | J226: 0 | K226: 3074.82 | L226: Central - Late Night Rides
A227: 05339c44-dcd1-41b7-af1e-a9caee8ea12e | B227: 0063k00000zHwHuAAK | C227: 0013k00002jMlsYAAS | D227: Rep74 | E227: US&Can | F227: ENT | G227: 44262 | H227: eats vouchers | I227: 0 | J227: 213.46 | K227: 213.46 | L227: Vouchers - Courtesy Meals
A228: 05350ceb-ab4a-56ae-80e3-ec448cff61ef | B228: 0064z000025lKhhAAE | C228: 0014z00001fzGE4AAM | D228: Rep37 | E228: US&Can | F228: SMB | G228: 44479 | H228: eats vouchers | I228: 221.36 | J228: 0 | K228: 221.36 | L228: Vouchers - Courtesy Meals
... A256: 05a210a9-0cd6-575a-84f4-48aeeb7e835c | B256: 0064z000026JLf0AAG | C256: 0014z00001ggCJFAA2 | D256: Rep67 | E256: LatAm | F256: SMB | G256: 44491 | H256: travel | I256: 345.69 | J256: 0 | K256: 345.69 | L256: Travel - Business Travel; Travel - Commute
A257: 05b017ac-63a6-4eba-b780-2416cbecfee9 | B257: 0064z000026JMleAAG | C257: 0013k00002jQ0qNAAS | D257: Rep68 | E257: #N/A | F257: #N/A | G257: 44487 | H257: eats vouchers | I257: 1028.86 | J257: 0 | K257: 1028.86 | L257: Vouchers - Courtesy Meals
A258: 05b1f8df-70dc-5e18-b216-f9dd6d84638b | B258: 0064z000026Ku8oAAC | C258: 0014z00001hIkFPAA0 | D258: Rep45 | E258: US&Can | F258: SMB | G258: 44540 | H258: vouchers | I258: 182.53 | J258: 0 | K258: 182.53 | L258: Rides Vouchers - One-time event transportation
A259: 05c5815e-8675-4ce2-ac96-126f4a867ecc | B259: 0064z000026LoXJAA0 | C259: 0013k00002jQ0qNAAS | D259: Rep68 | E259: #N/A | F259: #N/A | G259: 44547 | H259: eats vouchers | I259: 203.84 | J259: 0 | K259: 203.84 | L259: Rides/Eats Vouchers - One-time event
A260: 05c67efd-75e2-5ebe-9c9b-bed2c9ec9361 | B260: 0064z000026KiMIAA0 | C260: 0014z00001gkANfAAM | D260: Rep188 | E260: US&Can | F260: SMB | G260: 44529 | H260: vouchers | I260: 407.78 | J260: 0 | K260: 407.78 | L260: Rides/Eats Vouchers - One-time event
A261: 05ce1572-0187-44ad-af8a-f4f7e76df993 | B261: 0064z000026KZgAAAW | C261: 0014z00001gjjhwAAA | D261: Rep25 | E261: US&Can | F261: SMB | G261: 44519 | H261: vouchers | I261: 662.66 | J261: 0 | K261: 662.66 | L261: Rides Vouchers - One-time event transportation
A262: 05cf0b19-6893-441b-9ef0-79ac4484a199 | B262: 0064z000026KS3xAAG | C262: 0013k00002jPOItAAO | D262: Rep77 | E262: US&Can | F262: MM | G262: 44517 | H262: travel | I262: 187.96 | J262: 0 | K262: 187.96 | L262: Rides Vouchers - One-time event transportation
A263: 05cfbaec-0bdf-48e0-8d83-a0affdca0298 | B263: 0064z000026KjD2AAK | C263: 0013k00002jLGRfAAO | D263: Rep67 | E263: LatAm | F263: SMB | G263: 44537 | H263: vouchers | I263: 1258.24 | J263: 0 | K263: 1258.24 | L263: Rides Vouchers - Employee benefit / reward
A264: 05d7c23b-f3be-5b53-9b1e-892ff13dc932 | B264: 0064z000026JiaXAAS | C264: 0014z00001ghNi2AAE | D264: Rep186 | E264: US&Can | F264: SMB | G264: 44515 | H264: central | I264: 112.52 | J264: 0 | K264: 112.52 | L264: Rides Vouchers - One-time event transportation
A265: 05d7c23b-f3be-5b53-9b1e-892ff13dc932 | B265: 0064z000026JiaXAAS | C265: 0014z00001ghNi2AAE | D265: Rep186 | E265: US&Can | F265: SMB | G265: 44515 | H265: vouchers | I265: 185.24 | J265: 0 | K265: 185.24 | L265: Rides Vouchers - One-time event transportation
A266: 05dac7d0-ee06-4928-ac54-4b0865411ece | B266: 0064z000026KdwqAAC | C266: 0013k00002jPUMYAA4 | D266: Rep158 | E266: US&Can | F266: SMB | G266: 44530 | H266: eats vouchers | I266: 8395.41 | J266: 0 | K266: 8395.41 | L266: Eats Vouchers - Recruiting
A267: 05dbf8d9-cf75-4572-afaa-81f8546dc1d5 | B267: 0064z000025kva1AAA | C267: 0014z00001fyI7yAAE | D267: Rep23 | E267: US&Can | F267: SMB | G267: 44481 | H267: central | I267: 932.47 | J267: 0 | K267: 932.47 | L267: Central - Delivery
A268: 05dbf8d9-cf75-4572-afaa-81f8546dc1d5 | B268: 0064z000025kva1AAA | C268: 0014z00001fyI7yAAE | D268: Rep23 | E268: US&Can | F268: SMB | G268: 44481 | H268: travel | I268: 221.25 | J268: 0 | K268: 221.25 | L268: Central - Delivery
A269: 05e34260-b7a2-5c5c-a0c8-5c5566ee744d | B269: 0064z000026Lb2CAAS | C269: 0014z00001hKA1EAAW | D269: Rep103 | E269: LatAm | F269: SMB | G269: 44551 | H269: travel | I269: 1.78 | J269: 0 | K269: 1.78 | L269: Travel - Business Travel
A270: 05efc51c-b35d-4c86-ba44-f54b1fa066f7 | B270: 0064z000024nWDfAAM | C270: 0013k00002jQ0o8AAC | D270: Rep43 | E270: US&Can | F270: ENT | G270: 44348 | H270: eats vouchers | I270: 0 | J270: 28292.84 | K270: 28292.84 | L270: Vouchers - Courtesy Meals
A271: 05f80a6c-6ef4-48e9-804e-e8c0a274d2a8 | B271: 0063k000010RbMHAA0 | C271: 0013k00002iVxQ2AAK | D271: Rep115 | E271: Europe | F271: MM | G271: 44209 | H271: eats | I271: 0 | J271: 6425.95 | K271: 6425.95 | L271: eats - Work From Home Meals
... A294: 067912cc-51a9-489b-a6ec-b79c29491519 | B294: 0064z000026Jsp0AAC | C294: 0013k00002jQ0toAAC | D294: Rep66 | E294: US&Can | F294: ENT | G294: 44502 | H294: eats vouchers | I294: 108.75 | J294: 0 | K294: 108.75 | L294: Vouchers - Employee Morale
A295: 067ade31-3887-402d-8ac2-de495ab98242 | B295: 0063k00000yauZfAAI | C295: 0013k00002iWEFiAAO | D295: Rep88 | E295: Europe | F295: MM | G295: 44211 | H295: travel | I295: 0 | J295: 215.14 | K295: 215.14 | L295: 0
A296: 067b6db3-dd87-4134-96b7-b9de8e950c39 | B296: 0064z000025iKuyAAE | C296: 0013k00002jLjwlAAC | D296: Rep163 | E296: India | F296: ENT | G296: 44421 | H296: travel | I296: 2405.94 | J296: 0 | K296: 2405.94 | L296: Travel - Business Travel; Travel - Rental
A297: 06963448-f61e-44b8-ab38-4db93a8fdca0 | B297: 0064z000026JBzxAAG | C297: 0013k00002jQf9bAAC | D297: Rep165 | E297: India | F297: ENT | G297: 44498 | H297: travel | I297: 4682.71 | J297: 0 | K297: 4682.71 | L297: Travel - Business Travel; Travel - Commute
A298: 069b6ff6-9491-4e71-b220-54b9bb4016f7 | B298: 0063k000010YGQJAA4 | C298: 0013k00002w8Mm1AAE | D298: Rep127 | E298: Europe | F298: ENT | G298: 44270 | H298: travel | I298: 0 | J298: 17.71 | K298: 17.71 | L298: Vouchers - Incentive / Promotional Tool
A299: 069c122b-a44d-47a2-8493-ffdaf6df65a6 | B299: 0063k00000zHrdeAAC | C299: 0013k00002iWIDPAA4 | D299: Rep115 | E299: Europe | F299: MM | G299: 44246 | H299: eats | I299: 0 | J299: 1020.4 | K299: 1020.4 | L299: eats - Work From Home Meals
A300: 069c122b-a44d-47a2-8493-ffdaf6df65a6 | B300: 0063k00000zHrdeAAC | C300: 0013k00002iWIDPAA4 | D300: Rep115 | E300: Europe | F300: MM | G300: 44246 | H300: travel | I300: 0 | J300: 219.31 | K300: 219.31 | L300: eats - Work From Home Meals
A301: 06a05c73-95c9-4794-9e75-472d5e06abd0 | B301: 0064z000025kzoNAAQ | C301: 0014z00001fyQk5AAE | D301: Rep90 | E301: Europe | F301: MM | G301: 44468 | H301: travel | I301: 8095.68 | J301: 0 | K301: 8095.68 | L301: Travel - Business Travel
A302: 06aad5d6-353e-465e-97bd-0ef0cba051f0 | B302: 0064z000025ivXvAAI | C302: 0014z00001evBHDAA2 | D302: Rep61 | E302: LatAm | F302: MM | G302: 44419 | H302: travel | I302: 5143.43 | J302: 0 | K302: 5143.43 | L302: Travel - Business Travel
A303: 06c60482-d1bb-542e-987d-162e94262027 | B303: 0064z000025idvjAAA | C303: 0013k00002jQLlLAAW | D303: Rep87 | E303: US&Can | F303: SMB | G303: 44414 | H303: vouchers | I303: 7799.75 | J303: 0 | K303: 7799.75 | L303: Vouchers - Employee Morale
A304: 06cbf684-20bd-4dfa-8dad-7664e8354e52 | B304: 0064z000025ktXoAAI | C304: 0013k00002iW2baAAC | D304: Rep66 | E304: US&Can | F304: ENT | G304: 44462 | H304: eats vouchers | I304: 3671.97 | J304: 0 | K304: 3671.97 | L304: Vouchers - Courtesy Meals
A305: 06cdf647-7a69-45b8-a635-cd1d799dfdf9 | B305: 0064z000025iJUFAA2 | C305: 0013k00002iUagGAAS | D305: Rep66 | E305: US&Can | F305: ENT | G305: 44398 | H305: eats vouchers | I305: 132.68 | J305: 0 | K305: 132.68 | L305: Vouchers - Employee Morale
A306: 06d13bdb-1664-4cf3-b9f9-c225a483e56e | B306: 0064z000024mJyXAAU | C306: 0013k00002iUxdlAAC | D306: Rep65 | E306: US&Can | F306: MM | G306: 44378 | H306: central | I306: 1589.21 | J306: 0 | K306: 1589.21 | L306: Vouchers - Courtesy Rides
A307: 06d13bdb-1664-4cf3-b9f9-c225a483e56e | B307: 0064z000024mJyXAAU | C307: 0013k00002iUxdlAAC | D307: Rep65 | E307: US&Can | F307: MM | G307: 44378 | H307: vouchers | I307: 170.25 | J307: 0 | K307: 170.25 | L307: Vouchers - Courtesy Rides
... A410: 090d5ed7-ff53-51b4-926c-0a17728f2bfd | B410: 0064z000026K5KZAA0 | C410: 0014z00001giXl7AAE | D410: Rep22 | E410: US&Can | F410: SMB | G410: 44538 | H410: vouchers | I410: 46.3 | J410: 0 | K410: 46.3 | L410: Rides Vouchers - One-time event transportation
...

Sheet Lookup
B1: Week of 2/18 | C1: Week of 2/25 | D1: Week of 3/3 | E1: Week of 3/10 | F1: Week of 3/17 | G1: Week of 3/24
B2: 43879 | C2: =B2+7 -> 43886 | D2: =C2+7 -> 43893 | E2: =D2+7 -> 43900 | F2: =E2+7 -> 43907 | G2: =F2+7 -> 43914

Sheet Q3 Open Tickets
A1: Timestamp | B1: Email Address | C1: What can we help with? | D1: Which Salesforce Opportunity does this relate to? (please provide link) | E1: Any additional comments? | F1: Notes | G1: Status
A2: 44393.288 | B2: mara.goeckner@uber.com | C2: My New Business Attainment is incorrect | D2: https://u4b.lightning.force.com/lightning/r/Opportunity/0064z000024mn60AAA/view | E2: Gift card opp was not closed. Please change closed won date to July 9 as this is when the gift cards were sent. Thanks! | F2: reflected in attainment | G2: completed
A3: 44393.318 | B3: hooley@uber.com | C3: My Carryover Attainment is incorrect | D3: https://u4b.my.salesforce.com/0064z000024l5wt | E3: Taboola is being pulled into the attainment report for CO meal program, but I've only closed a gift card opp on the account. Is it possible to adjust this? Thank you! | F3: reflected in attainment | G3: completed
A4: 44396.115 | B4: mendes@uber.com | C4: My Carryover Attainment is incorrect | D4: https://u4b.my.salesforce.com/0063k000010YQrD | E4: This account doesn't feature in my carryover attainment. | F4: There are no trips in H2 21 yet. | G4: completed
A5: 44410.681 | B5: francescar@uber.com | C5: My Carryover Attainment is incorrect | D5: https://u4b.lightning.force.com/lightning/r/Opportunity/0064z000024lYvjAAE/view. https://u4b.lightning.force.com/lightning/r/Opportunity/0064z000024lPl4AAE/view. https://u4b.lightning.force.com/lightning/r/Opportunity/0064z000024lPl9AAE/view. https://u4b.lightning.force.com/lightning/r/Opportunity/0064z000024lPlAAAU/view. | E5: Just noticed that 4 of the dashboards I closed in H1 under Virtual Kitchen Co. have different numbers pulling into the attainment report from the actuals. 57bd3703-f9e4-4d51-b766-4404416acedc - $597.77 0507c1b3-4f7d-4fe7-9e33-7859ece1fdb7 - $44,613.72 cd047bc4-7fed-4b59-99b9-3490548335c3 - $17,100.95 3e8dd309-9e06-4e11-956d-27a8973f99b6 - $21,969.97 CO$GB from attainment report: $31,896 Total (granted 7/27 leaves a few days for revenue in July): $84,879.41 | F5: The correct GB is reflected in attainment | G5: completed
A6: 44413.53 | B6: ch.james@uber.com | C6: My New Business Attainment is incorrect | D6: https://u4b.lightning.force.com/lightning/r/Opportunity/0064z000025hp20AAA/view | E6: vouchers NB attainment not populating. CW opp 7.9.2021 | F6: reflected in attainment | G6: completed
A7: 44421.424 | B7: francescar@uber.com | C7: My Carryover Attainment is incorrect | D7: cd047bc4-7fed-4b59-99b9-3490548335c3,3e8dd309-9e06-4e11-956d-27a8973f99b6, 57bd3703-f9e4-4d51-b766-4404416acedc, 0507c1b3-4f7d-4fe7-9e33-7859ece1fdb7, | E7: 7/1 - 8/10 Carryover GB: All Day Kitchen - Rides 0507c1b3-4f7d-4fe7-9e33-7859ece1fdb7 - $49,170.72 All Day Kitchens - cd047bc4-7fed-4b59-99b9-3490548335c3 - $22,143.95 Vrias Foods - Eats - 3e8dd309-9e06-4e11-956d-27a8973f99b6 - $25,013.11 Vrias foods - Rides 57bd3703-f9e4-4d51-b766-4404416acedc - $764.44 Attainment Report: 52,071 Missing = 45,021.22 | F7: reflected in attainment | G7: completed
A8: 44421.502 | B8: danielb@uber.com | C8: My Total Attainment is incorrect | D8: https://u4b.my.salesforce.com/0063k00000ybuo6 | E8: I've not received any attainment for this opportunity this half. Please update. | F8: reflected in attainment | G8: completed
A9: 44432.397 | B9: kiran.rao@uber.com | C9: My Carryover Attainment is incorrect | D9: https://u4b.my.salesforce.com/0064z000024mlAPAAY | E9: The CO GB should have been USD 1691. GB Reflecting in attainment USD 1409 GB Missing USD 282 | F9: reflected in attainment | G9: completed
A10: 44434.774 | B10: gwallworth@uber.com | C10: My New Business Attainment is incorrect | D10: https://u4b.my.salesforce.com/0064z000024nSc3 | E10: Open case #10534392 - sitting with Jassem Shukr regarding the transfer of this opp into my name for attainment. Previously CW vouchers by a rep who is no longer with Uber, approval from Juan to create a new opp as there was low spend on the account and grown to 60K plus GB. SF doesn't allow me to create a new opp for vouchers so the request is for the opp to be transferred to me with attainment from the 20th of Aug onwards. Thankyou | F10: reflected in attainment | G10: completed
A11: 44435.265 | B11: mara.goeckner@uber.com | C11: My New Business Attainment is incorrect | D11: https://u4b.lightning.force.com/lightning/r/Opportunity/0064z000024lb6XAAQ/view?0.source=alohaHeader | E11: There is no GB from this account pulling into the attainment report | F11: reflected in attainment | G11: completed
A12: 44446.791 | B12: kayvanc@uber.com | C12: My New Business Attainment is incorrect | D12: https://u4b.my.salesforce.com/0064z000024lSC9?srPos=0&srKp=006 | E12: UUID: b9048c5f-56a6-450d-8292-7b65ef0e444a Per attainment, H2 spend = $72,521.10 (incorrect) Per the UUID / Dashboard, July 2021 spend = $84,041.93 Please update H2 attainment for this UUID to $84,041.93. It would be great if it could accurately reflect on this upcoming attainment report. Thank you! | G12: completed
A13: 44448.82 | B13: josh.miller@uber.com | C13: My Total Attainment is incorrect | D13: 1) https://u4b.lightning.force.com/lightning/r/Opportunity/0064z000025kCOLAA2/view 2) https://u4b.lightning.force.com/lightning/r/Opportunity/0064z000025jthUAAQ/view 3) https://u4b.lightning.force.com/lightning/r/Opportunity/0064z000025jaQvAAI/view | E13: These opps are closed/won opps using existing UUID’s. These clients indicated they would used Central for delivery. From what I can tell these orgs have unfortunately not started using Connect on Central. I believe this would show the vehicle category as “connect” if so. I want to call these out as I am worried I am being given attainment for courtesy rides I did not initiate. My questions: -Do we need to create a new UUID for delivery to be tracked separately from courtesy rides? -Will these opps be tracked correctly if we create a new program for delivery under the same UUID? -Will these opps track correctly if we submit the product as Central/Delivery on the same program as courtesy rides? My apologies for any mixup here, please advise on how to proceed. Thanks, Josh | G13: completed
A14: 44451.824 | B14: ruby.rios@uber.com | C14: My Total Attainment is incorrect | D14: General Question | E14: Can you clearly define what is included in GB? The reports for the UUIDs in office space do not add up to the attainment report for multiple accounts. It was brought to my attention that tips and taxes are not counted towards our total GB number. Are the tips/taxes not being counted in attainment a new policy? Is there anything else that is not counted in our attainment number? What report can we pull to check and balance the attainment report if not office space? | G14: completed
A15: 44454.604 | B15: mdecastro@uber.com | C15: My Total Attainment is incorrect | D15: Radiant Health Centers | E15: There are several accounts across all health AEs that appear to be showing until travel and health GB. Radiant Health Centers is an example. | F15: reflected in attainment | G15: completed
A16: 44459.306 | B16: gkauffmann@uber.com | C16: My Carryover Attainment is incorrect | D16: https://u4b.lightning.force.com/lightning/r/Opportunity/0063k000010RrGfAAK/view | E16: API Direct Deal closed-won in April/2021 and GB is not being considered (I believe) in my att. Team, could you please, verify? Thanks, | F16: reflected in attainment | G16: completed
A17: 44461.416 | B17: guilherme.gabriel@uber.com | C17: My New Business Attainment is incorrect | D17: Acount 0013k00002jQPveAAG | E17: Could you pls confirm the acct 0013k00002jQPveAAG is spending on connect/flash? We checked on office-space and with the client it does not seems they are spending in this solution? | F17: central/connect was not sold, and it was requested to be removed | G17: completed
A18: 44461.416 | B18: guilherme.gabriel@uber.com | C18: My New Business Attainment is incorrect | D18: Account 0013k00002jLdlsAAC | E18: ccount 0013k00002jLdlsAAC - spend seems much lower than amount observed in office space ($3,246 in attn report vs. ~8k checking office-space) | F18: correctly reflected in attainment | G18: completed
A19: 44461.416 | B19: guilherme.gabriel@uber.com | C19: My New Business Attainment is incorrect | D19: UUID 05520de5-be56-587d-9341-023aa68ddee9 | E19: ASSINO CREDITO IMOBILIARIO: AE did not sell travel UUID 05520de5-be56-587d-9341-023aa68ddee9 Value to be disconsidered $1245 | F19: reflected in attainment | G19: completed
A20: 44461.417 | B20: guilherme.gabriel@uber.com | C20: My New Business Attainment is incorrect | D20: UUID 3eeaa4ee-d16f-4bb7-910c-b48513d56ad3 | E20: COMUNICARE COMERCIO DE APARELHOS AUDITIVOS LTDA AE did not sell travel UUID 3eeaa4ee-d16f-4bb7-910c-b48513d56ad3 Value to be disconsidered $3113 | F20: reflected in attainment | G20: completed
A21: 44461.417 | B21: guilherme.gabriel@uber.com | C21: My New Business Attainment is incorrect | D21: UUID 68232936-8af5-539f-bc95-2d5d09364a4c | E21: Nexcorp ServiÁos e TelecomunicaÁıes S.A. AE did not sell travel UUID 68232936-8af5-539f-bc95-2d5d09364a4c Value to be disconsidered $8043 | F21: reflected in attainment | G21: completed
A22: 44461.417 | B22: guilherme.gabriel@uber.com | C22: My New Business Attainment is incorrect | D22: UUID 850c227f-b953-48fb-866d-4e7477328392 | E22: ALFILM AMAZONIA IND E COM LTDA AE did not sell travel UUID 850c227f-b953-48fb-866d-4e7477328392 Value to be disconsidered $2400 | F22: reflected in attainment | G22: completed
A23: 44461.417 | B23: guilherme.gabriel@uber.com | C23: My New Business Attainment is incorrect | D23: UUID f2748eaa-15c9-458d-9b77-9d0cdccd1e2b | E23: YAMADA-LOM FABRICA????O DE ARTEFATOS DE MATERIAL PL?STICO LTDA. AE did not sell travel UUID f2748eaa-15c9-458d-9b77-9d0cdccd1e2b Value to be disconsidered $456 | F23: reflected in attainment | G23: completed
A24: 44461.417 | B24: guilherme.gabriel@uber.com | C24: My New Business Attainment is incorrect | D24: UUID 96850bad-a924-4fe9-85e5-aec7c890b230 | E24: IKM Servicios Central Central not sold by AE UUID 96850bad-a924-4fe9-85e5-aec7c890b230 Value to be disconsidered $49.37 | F24: reflected in attainment | G24: completed
A25: 44461.418 | B25: guilherme.gabriel@uber.com | C25: My New Business Attainment is incorrect | D25: UUID 96850bad-a924-4fe9-85e5-aec7c890b230 | E25: IKM Servicios Central Travel not sold by AE UUID 96850bad-a924-4fe9-85e5-aec7c890b230 Vaue to be disconsidered $2391.18 | F25: reflected in attainment | G25: completed
A26: 44461.418 | B26: guilherme.gabriel@uber.com | C26: My New Business Attainment is incorrect | D26: UUID cf76249e-74b2-44c3-aff1-c4c451764102 | E26: BCYSA Servicios Industriales SA de CV travel Travel not sold by AE UUID cf76249e-74b2-44c3-aff1-c4c451764102 Vaue to be disconsidered $2010.99 | F26: reflected in attainment | G26: completed
... A62: 44477.526 | B62: guilherme.gabriel@uber.com | C62: My Total Attainment is incorrect | D62: https://u4b.lightning.force.com/lightning/r/Opportunity/0063k00000yYYJFAA4/view | E62: Grupo Loyga SA de CV-2020-01-27 868e347b-f0da-489a-9310-a013dc1d3ac2 Travel was not sold by the AE and should not be considered | F62: reflected in attainment | G62: completed
A63: 44477.547 | B63: stephen.chapman@uber.com | C63: My New Business Attainment is incorrect | D63: https://u4b.my.salesforce.com/0064z000025jcZv?srPos=0&srKp=006 | E63: The UUID on that Opp is incorrect. Can you populate it with the correct UUID included below? 8c870501-d6a1-4658-a944-1e493de7e982
A64: 44477.548 | B64: stephen.chapman@uber.com | C64: My New Business Attainment is incorrect | D64: https://u4b.my.salesforce.com/0064z000025jtsD?srPos=0&srKp=006 | E64: The closed won - Optiver Eats, is not pulling the GB into the attainment. Not sure why, they are spending. UUID: 17044f8a-20af-4333-b9d8-a7ea31382338
A65: 44479.951 | B65: mendes@uber.com | C65: My New Business Attainment is incorrect | D65: https://u4b.lightning.force.com/lightning/r/Opportunity/0064z000025izaQAAQ/view | E65: There is a discrepancy in the GB attributed vs Trips taken.
A66: 44481.323 | B66: michelle.caldas@uber.com | C66: My Carryover Attainment is incorrect | D66: https://u4b.lightning.force.com/lightning/r/Opportunity/0063k000011LKT3AAO/view | E66: The total carryover from July 1 - Sept 30 should be $83,993.77
A67: 44481.338 | B67: michelle.caldas@uber.com | C67: My New Business Attainment is incorrect | D67: https://u4b.lightning.force.com/lightning/r/Opportunity/0064z000025iGasAAE/view | E67: Total new business in vouchers for Q3 should be $2,497.50
A68: 44481.34 | B68: michelle.caldas@uber.com | C68: My New Business Attainment is incorrect | D68: https://u4b.lightning.force.com/lightning/r/Opportunity/0064z000025iVpGAAU/view | E68: New Business GB should be $1,364
A69: 44481.348 | B69: michelle.caldas@uber.com | C69: My New Business Attainment is incorrect | D69: https://u4b.lightning.force.com/lightning/r/Opportunity/0064z000025iW8cAAE/view | E69: New Business total from Sept 1 - 30 should be $153,965
A70: 44481.381 | B70: michelle.caldas@uber.com | C70: My New Business Attainment is incorrect | D70: https://u4b.lightning.force.com/lightning/r/Opportunity/0064z000025hHEtAAM/view | E70: Attainment should be $25,678.53 for Q3
A71: 44481.481 | B71: hooley@uber.com | C71: My New Business Attainment is incorrect | D71: 22fad395-8a5f-4cbc-b62a-02a720eea36f | E71: Travel GB is pulling into NB attainment, but it should only be Eats. Thanks!
A72: 44481.482 | B72: hooley@uber.com | C72: My New Business Attainment is incorrect | D72: 2b2bfd08-bddd-5177-b6fd-b61a1fb4045e | E72: Travel GB is pulling into NB attainment, but only Eats and Vouchers GB should be pulling in. Thanks!
A73: 44481.483 | B73: hooley@uber.com | C73: My New Business Attainment is incorrect | D73: 673aec42-4933-4212-a600-e7eb018c7286 | E73: Travel GB is pulling into NB attainment, but only Eats should be. Thanks!
A74: 44481.483 | B74: hooley@uber.com | C74: My New Business Attainment is incorrect | D74: d00c3236-041d-49dd-96f1-a494ad1729fe | E74: Travel and Vouchers GB is pulling into NB attainment, but only Eats should be. Thanks!
... A76: 44481.488 | B76: bains@uber.com | C76: My New Business Attainment is incorrect | D76: https://u4b.lightning.force.com/lightning/r/Opportunity/0064z000025kbxNAAQ/view | E76: Voucher opportunity not showing at all in NB, closed 9/26
A77: 44481.591 | B77: bryan.watts@uber.com | C77: The Country Manager attainment on the scorecard is incorrect | D77: https://docs.google.com/spreadsheets/d/18B-EYsvOGYIPySuH0MKpELs_eg921fTGyZj9pe28amo/edit#gid=0 | E77: Shows AM cross-sell at 0% for Canada, when it should be 138% which represents Riza Capulong's cross-sell attainment as of 9/30. Please correct as this will affect manager quarterly payout. Thanks | F77: corrected in CM scorecard | G77: completed
A78: 44481.619 | B78: sebastian.reszka@uber.com | C78: My New Business Attainment is incorrect | D78: https://u4b.lightning.force.com/lightning/r/Account/0013k00002qQfBBAA0/view | E78: USMMA launched in August. | F78: no opps created | G78: completed
A79: 44481.62 | B79: sebastian.reszka@uber.com | C79: My New Business Attainment is incorrect | D79: https://u4b.lightning.force.com/lightning/r/Account/0013k00002jKyR5AAK/view | E79: SDSU launched vouchers in Sept. | F79: reflected | G79: completed
A80: 44481.62 | B80: sebastian.reszka@uber.com | C80: My New Business Attainment is incorrect | D80: https://u4b.lightning.force.com/lightning/r/Account/0014z00001fxBnQAAU/view | E80: Drexel launched vouchers in Sept | F80: reflected | G80: completed
A81: 44481.62 | B81: sebastian.reszka@uber.com | C81: My New Business Attainment is incorrect | D81: https://u4b.lightning.force.com/lightning/r/Account/0014z00001fQZWuAAO/view | E81: FL Health launched in Sept for vouchers | F81: reflected | G81: completed
A82: 44481.62 | B82: sebastian.reszka@uber.com | C82: My New Business Attainment is incorrect | D82: https://u4b.lightning.force.com/lightning/r/Account/0014z00001eJx2rAAC/view | E82: The GC's were purchased in Sept | F82: reflected | G82: completed
A83: 44481.642 | B83: sebastian.reszka@uber.com | C83: My New Business Attainment is incorrect | D83: https://u4b.lightning.force.com/lightning/r/Opportunity/0063k000010YHSzAAO/view | E83: NSF has invited employees | F83: reflected | G83: completed
A84: 44481.662 | B84: sebastian.reszka@uber.com | C84: My New Business Attainment is incorrect | D84: https://u4b.lightning.force.com/lightning/r/Opportunity/0063k000010T1p2AAC/view | E84: USMMA started their trips officially on 9/1 | F84: reflected | G84: completed
A85: 44482.479 | B85: tsorice@uber.com | C85: My New Business Attainment is incorrect | D85: https://u4b.lightning.force.com/lightning/r/Opportunity/0064z000025jRApAAM/view | E85: I was looking at the attainment report and checking on my Cooper Vision (events) dashboard. I downloaded the CSV report from their dashboard just for the months of Aug and Sept and it doesn't match my attainment unless I'm reading it wrong. My total was $4,170.38. But attainment says $3,899.38. Just want to clarify. Thank you!
A86: 44484.316 | B86: mara.goeckner@uber.com | C86: My New Business Attainment is incorrect | D86: https://u4b.lightning.force.com/lightning/r/Opportunity/0064z000025ju3aAAA/view | E86: attainment from this opp should be $3,798.11
A87: 44484.316 | B87: mara.goeckner@uber.com | C87: My Carryover Attainment is incorrect | D87: https://u4b.lightning.force.com/lightning/r/Opportunity/0064z000024mnGeAAI/view | E87: attainment on this opp should be $22,410
A88: 44484.337 | B88: renan.alves@uber.com | C88: My Total Attainment is incorrect | D88: https://u4b.lightning.force.com/lightning/r/Opportunity/0063k000010RrGfAAK/view | E88: Review direct attn - seems lower than client spent
A89: 44484.338 | B89: renan.alves@uber.com | C89: My Total Attainment is incorrect | D89: https://u4b.lightning.force.com/lightning/r/Opportunity/0064z000024lmBdAAI/view | E89: Direct GB seems lower than client is spending, could you pls review it.

Sheet Copy of Total Launches by Produ
D2: 43879 | E2: =D3 -> 43886 | F2: =E3 -> 43893 | G2: =F3 -> 43900 | H2: =G3 -> 43907 | I2: =H3 -> 43914 | J2: =I3 -> 43921 | K2: =J3 -> 43928 | L2: =K3 -> 43935 | ... V2: =U3 -> 44005 | W2: 44013
D3: =D2+7 -> 43886 | E3: =E2+7 -> 43893 | F3: =F2+7 -> 43900 | G3: =G2+7 -> 43907 | H3: =H2+7 -> 43914 | I3: =I2+7 -> 43921 | J3: =J2+7 -> 43928 | K3: =K2+7 -> 43935 | ... W3: =W2+7 -> 44020
B4: Mega Region | C4: Product | D4: 2/18 to 2/25 | E4: 2/25 to 3/3 | F4: 3/3 to 3/10 | G4: 3/10 to 3/17 | H4: 3/17 to 3/24 | I4: 3/24 to 3/31 | J4: 3/31 to 4/7 | K4: 4/7 to 4/14 | L4: 4/14 to 4/21 | M4: 4/21 to 4/28 | N4: 4/28 to 5/5 | O4: 5/5 to 5/12 | P4: 5/12 to 5/19 | Q4: 5/19 to 5/26 | R4: 5/26 to 6/2 | S4: 6/2 to 6/9 | T4: 6/9 to 6/16 | U4: 6/16 to 6/23 | V4: 6/23 to 6/30 | W4: 7/1 to 7/7
B5: APACx | C5: Travel | D5: =countifs(#REF!,$B5,'Attainment Query Data'!$H:$H,$C5,'Attainment Query Data'!$G:$G,">"&D$2,'Attainment Query Data'!$G:$G,"<="&D$3) -> #VALUE! | E5: =countifs(#REF!,$B5,'Attainment Query Data'!$H:$H,$C5,'Attainment Query Data'!$G:$G,">"&E$2,'Attainment Query Data'!$G:$G,"<="&E$3) -> #VALUE! | F5: =countifs(#REF!,$B5,'Attainment Query Data'!$H:$H,$C5,'Attainment Query Data'!$G:$G,">"&F$2,'Attainment Query Data'!$G:$G,"<="&F$3) -> #VALUE! | G5: =countifs(#REF!,$B5,'Attainment Query Data'!$H:$H,$C5,'Attainment Query Data'!$G:$G,">"&G$2,'Attainment Query Data'!$G:$G,"<="&G$3) -> #VALUE! | H5: =countifs(#REF!,$B5,'Attainment Query Data'!$H:$H,$C5,'Attainment Query Data'!$G:$G,">"&H$2,'Attainment Query Data'!$G:$G,"<="&H$3) -> #VALUE! | I5: =countifs(#REF!,$B5,'Attainment Query Data'!$H:$H,$C5,'Attainment Query Data'!$G:$G,">"&I$2,'Attainment Query Data'!$G:$G,"<="&I$3) -> #VALUE! | J5: =countifs(#REF!,$B5,'Attainment Query Data'!$H:$H,$C5,'Attainment Query Data'!$G:$G,">"&J$2,'Attainment Query Data'!$G:$G,"<="&J$3) -> #VALUE! | K5: =countifs(#REF!,$B5,'Attainment Query Data'!$H:$H,$C5,'Attainment Query Data'!$G:$G,">"&K$2,'Attainment Query Data'!$G:$G,"<="&K$3) -> #VALUE! | ... W5: =countifs(#REF!,$B5,'Attainment Query Data'!$H:$H,$C5,'Attainment Query Data'!$G:$G,">"&W$2,'Attainment Query Data'!$G:$G,"<="&W$3) -> #VALUE!
B6: APACx | C6: Vouchers | D6: =countifs(#REF!,$B6,'Attainment Query Data'!$H:$H,$C6,'Attainment Query Data'!$G:$G,">"&D$2,'Attainment Query Data'!$G:$G,"<="&D$3) -> #VALUE! | E6: =countifs(#REF!,$B6,'Attainment Query Data'!$H:$H,$C6,'Attainment Query Data'!$G:$G,">"&E$2,'Attainment Query Data'!$G:$G,"<="&E$3) -> #VALUE! | F6: =countifs(#REF!,$B6,'Attainment Query Data'!$H:$H,$C6,'Attainment Query Data'!$G:$G,">"&F$2,'Attainment Query Data'!$G:$G,"<="&F$3) -> #VALUE! | G6: =countifs(#REF!,$B6,'Attainment Query Data'!$H:$H,$C6,'Attainment Query Data'!$G:$G,">"&G$2,'Attainment Query Data'!$G:$G,"<="&G$3) -> #VALUE! | H6: =countifs(#REF!,$B6,'Attainment Query Data'!$H:$H,$C6,'Attainment Query Data'!$G:$G,">"&H$2,'Attainment Query Data'!$G:$G,"<="&H$3) -> #VALUE! | I6: =countifs(#REF!,$B6,'Attainment Query Data'!$H:$H,$C6,'Attainment Query Data'!$G:$G,">"&I$2,'Attainment Query Data'!$G:$G,"<="&I$3) -> #VALUE! | J6: =countifs(#REF!,$B6,'Attainment Query Data'!$H:$H,$C6,'Attainment Query Data'!$G:$G,">"&J$2,'Attainment Query Data'!$G:$G,"<="&J$3) -> #VALUE! | K6: =countifs(#REF!,$B6,'Attainment Query Data'!$H:$H,$C6,'Attainment Query Data'!$G:$G,">"&K$2,'Attainment Query Data'!$G:$G,"<="&K$3) -> #VALUE! | ... W6: =countifs(#REF!,$B6,'Attainment Query Data'!$H:$H,$C6,'Attainment Query Data'!$G:$G,">"&W$2,'Attainment Query Data'!$G:$G,"<="&W$3) -> #VALUE!
B7: APACx | C7: E4B Vouchers | D7: =countifs(#REF!,$B7,'Attainment Query Data'!$H:$H,$C7,'Attainment Query Data'!$G:$G,">"&D$2,'Attainment Query Data'!$G:$G,"<="&D$3) -> #VALUE! | E7: =countifs(#REF!,$B7,'Attainment Query Data'!$H:$H,$C7,'Attainment Query Data'!$G:$G,">"&E$2,'Attainment Query Data'!$G:$G,"<="&E$3) -> #VALUE! | F7: =countifs(#REF!,$B7,'Attainment Query Data'!$H:$H,$C7,'Attainment Query Data'!$G:$G,">"&F$2,'Attainment Query Data'!$G:$G,"<="&F$3) -> #VALUE! | G7: =countifs(#REF!,$B7,'Attainment Query Data'!$H:$H,$C7,'Attainment Query Data'!$G:$G,">"&G$2,'Attainment Query Data'!$G:$G,"<="&G$3) -> #VALUE! | H7: =countifs(#REF!,$B7,'Attainment Query Data'!$H:$H,$C7,'Attainment Query Data'!$G:$G,">"&H$2,'Attainment Query Data'!$G:$G,"<="&H$3) -> #VALUE! | I7: =countifs(#REF!,$B7,'Attainment Query Data'!$H:$H,$C7,'Attainment Query Data'!$G:$G,">"&I$2,'Attainment Query Data'!$G:$G,"<="&I$3) -> #VALUE! | J7: =countifs(#REF!,$B7,'Attainment Query Data'!$H:$H,$C7,'Attainment Query Data'!$G:$G,">"&J$2,'Attainment Query Data'!$G:$G,"<="&J$3) -> #VALUE! | K7: =countifs(#REF!,$B7,'Attainment Query Data'!$H:$H,$C7,'Attainment Query Data'!$G:$G,">"&K$2,'Attainment Query Data'!$G:$G,"<="&K$3) -> #VALUE! | ... W7: =countifs(#REF!,$B7,'Attainment Query Data'!$H:$H,$C7,'Attainment Query Data'!$G:$G,">"&W$2,'Attainment Query Data'!$G:$G,"<="&W$3) -> #VALUE!
B8: APACx | C8: Central | D8: =countifs(#REF!,$B8,'Attainment Query Data'!$H:$H,$C8,'Attainment Query Data'!$G:$G,">"&D$2,'Attainment Query Data'!$G:$G,"<="&D$3) -> #VALUE! | E8: =countifs(#REF!,$B8,'Attainment Query Data'!$H:$H,$C8,'Attainment Query Data'!$G:$G,">"&E$2,'Attainment Query Data'!$G:$G,"<="&E$3) -> #VALUE! | F8: =countifs(#REF!,$B8,'Attainment Query Data'!$H:$H,$C8,'Attainment Query Data'!$G:$G,">"&F$2,'Attainment Query Data'!$G:$G,"<="&F$3) -> #VALUE! | G8: =countifs(#REF!,$B8,'Attainment Query Data'!$H:$H,$C8,'Attainment Query Data'!$G:$G,">"&G$2,'Attainment Query Data'!$G:$G,"<="&G$3) -> #VALUE! | H8: =countifs(#REF!,$B8,'Attainment Query Data'!$H:$H,$C8,'Attainment Query Data'!$G:$G,">"&H$2,'Attainment Query Data'!$G:$G,"<="&H$3) -> #VALUE! | I8: =countifs(#REF!,$B8,'Attainment Query Data'!$H:$H,$C8,'Attainment Query Data'!$G:$G,">"&I$2,'Attainment Query Data'!$G:$G,"<="&I$3) -> #VALUE! | J8: =countifs(#REF!,$B8,'Attainment Query Data'!$H:$H,$C8,'Attainment Query Data'!$G:$G,">"&J$2,'Attainment Query Data'!$G:$G,"<="&J$3) -> #VALUE! | K8: =countifs(#REF!,$B8,'Attainment Query Data'!$H:$H,$C8,'Attainment Query Data'!$G:$G,">"&K$2,'Attainment Query Data'!$G:$G,"<="&K$3) -> #VALUE! | ... W8: =countifs(#REF!,$B8,'Attainment Query Data'!$H:$H,$C8,'Attainment Query Data'!$G:$G,">"&W$2,'Attainment Query Data'!$G:$G,"<="&W$3) -> #VALUE!
B9: APACx | C9: Eats | D9: =countifs(#REF!,$B9,'Attainment Query Data'!$H:$H,$C9,'Attainment Query Data'!$G:$G,">"&D$2,'Attainment Query Data'!$G:$G,"<="&D$3) -> #VALUE! | E9: =countifs(#REF!,$B9,'Attainment Query Data'!$H:$H,$C9,'Attainment Query Data'!$G:$G,">"&E$2,'Attainment Query Data'!$G:$G,"<="&E$3) -> #VALUE! | F9: =countifs(#REF!,$B9,'Attainment Query Data'!$H:$H,$C9,'Attainment Query Data'!$G:$G,">"&F$2,'Attainment Query Data'!$G:$G,"<="&F$3) -> #VALUE! | G9: =countifs(#REF!,$B9,'Attainment Query Data'!$H:$H,$C9,'Attainment Query Data'!$G:$G,">"&G$2,'Attainment Query Data'!$G:$G,"<="&G$3) -> #VALUE! | H9: =countifs(#REF!,$B9,'Attainment Query Data'!$H:$H,$C9,'Attainment Query Data'!$G:$G,">"&H$2,'Attainment Query Data'!$G:$G,"<="&H$3) -> #VALUE! | I9: =countifs(#REF!,$B9,'Attainment Query Data'!$H:$H,$C9,'Attainment Query Data'!$G:$G,">"&I$2,'Attainment Query Data'!$G:$G,"<="&I$3) -> #VALUE! | J9: =countifs(#REF!,$B9,'Attainment Query Data'!$H:$H,$C9,'Attainment Query Data'!$G:$G,">"&J$2,'Attainment Query Data'!$G:$G,"<="&J$3) -> #VALUE! | K9: =countifs(#REF!,$B9,'Attainment Query Data'!$H:$H,$C9,'Attainment Query Data'!$G:$G,">"&K$2,'Attainment Query Data'!$G:$G,"<="&K$3) -> #VALUE! | ... W9: =countifs(#REF!,$B9,'Attainment Query Data'!$H:$H,$C9,'Attainment Query Data'!$G:$G,">"&W$2,'Attainment Query Data'!$G:$G,"<="&W$3) -> #VALUE!
B10: APACx | C10: Gift Card | D10: =countifs(#REF!,$B10,'Attainment Query Data'!$H:$H,$C10,'Attainment Query Data'!$G:$G,">"&D$2,'Attainment Query Data'!$G:$G,"<="&D$3) -> #VALUE! | E10: =countifs(#REF!,$B10,'Attainment Query Data'!$H:$H,$C10,'Attainment Query Data'!$G:$G,">"&E$2,'Attainment Query Data'!$G:$G,"<="&E$3) -> #VALUE! | F10: =countifs(#REF!,$B10,'Attainment Query Data'!$H:$H,$C10,'Attainment Query Data'!$G:$G,">"&F$2,'Attainment Query Data'!$G:$G,"<="&F$3) -> #VALUE! | G10: =countifs(#REF!,$B10,'Attainment Query Data'!$H:$H,$C10,'Attainment Query Data'!$G:$G,">"&G$2,'Attainment Query Data'!$G:$G,"<="&G$3) -> #VALUE! | H10: =countifs(#REF!,$B10,'Attainment Query Data'!$H:$H,$C10,'Attainment Query Data'!$G:$G,">"&H$2,'Attainment Query Data'!$G:$G,"<="&H$3) -> #VALUE! | I10: =countifs(#REF!,$B10,'Attainment Query Data'!$H:$H,$C10,'Attainment Query Data'!$G:$G,">"&I$2,'Attainment Query Data'!$G:$G,"<="&I$3) -> #VALUE! | J10: =countifs(#REF!,$B10,'Attainment Query Data'!$H:$H,$C10,'Attainment Query Data'!$G:$G,">"&J$2,'Attainment Query Data'!$G:$G,"<="&J$3) -> #VALUE! | K10: =countifs(#REF!,$B10,'Attainment Query Data'!$H:$H,$C10,'Attainment Query Data'!$G:$G,">"&K$2,'Attainment Query Data'!$G:$G,"<="&K$3) -> #VALUE! | ... W10: =countifs(#REF!,$B10,'Attainment Query Data'!$H:$H,$C10,'Attainment Query Data'!$G:$G,">"&W$2,'Attainment Query Data'!$G:$G,"<="&W$3) -> #VALUE!
C11: Total | D11: =SUM(D5:D10) -> #VALUE! | E11: =SUM(E5:E10) -> #VALUE! | F11: =SUM(F5:F10) -> #VALUE! | G11: =SUM(G5:G10) -> #VALUE! | H11: =SUM(H5:H10) -> #VALUE! | I11: =SUM(I5:I10) -> #VALUE! | J11: =SUM(J5:J10) -> #VALUE! | K11: =SUM(K5:K10) -> #VALUE! | ... W11: =SUM(W5:W10) -> #VALUE!
B13: Mega Region | C13: Product | D13: 2/18 to 2/25 | E13: 2/25 to 3/3 | F13: 3/3 to 3/10 | G13: 3/10 to 3/17 | H13: 3/17 to 3/24 | I13: 3/24 to 3/31 | J13: 3/31 to 4/7 | K13: 4/7 to 4/14 | L13: 4/14 to 4/21 | M13: 4/21 to 4/28 | N13: 4/28 to 5/5 | O13: 5/5 to 5/12 | P13: 5/12 to 5/19 | Q13: 5/19 to 5/26 | R13: 5/26 to 6/2 | S13: 6/2 to 6/9 | T13: 6/9 to 6/16 | U13: 6/16 to 6/23 | V13: 6/23 to 6/30 | W13: 7/1 to 7/7
B14: Europe | C14: Travel | D14: =countifs(#REF!,$B14,'Attainment Query Data'!$H:$H,$C14,'Attainment Query Data'!$G:$G,">"&D$2,'Attainment Query Data'!$G:$G,"<="&D$3) -> #VALUE! | E14: =countifs(#REF!,$B14,'Attainment Query Data'!$H:$H,$C14,'Attainment Query Data'!$G:$G,">"&E$2,'Attainment Query Data'!$G:$G,"<="&E$3) -> #VALUE! | F14: =countifs(#REF!,$B14,'Attainment Query Data'!$H:$H,$C14,'Attainment Query Data'!$G:$G,">"&F$2,'Attainment Query Data'!$G:$G,"<="&F$3) -> #VALUE! | G14: =countifs(#REF!,$B14,'Attainment Query Data'!$H:$H,$C14,'Attainment Query Data'!$G:$G,">"&G$2,'Attainment Query Data'!$G:$G,"<="&G$3) -> #VALUE! | H14: =countifs(#REF!,$B14,'Attainment Query Data'!$H:$H,$C14,'Attainment Query Data'!$G:$G,">"&H$2,'Attainment Query Data'!$G:$G,"<="&H$3) -> #VALUE! | I14: =countifs(#REF!,$B14,'Attainment Query Data'!$H:$H,$C14,'Attainment Query Data'!$G:$G,">"&I$2,'Attainment Query Data'!$G:$G,"<="&I$3) -> #VALUE! | J14: =countifs(#REF!,$B14,'Attainment Query Data'!$H:$H,$C14,'Attainment Query Data'!$G:$G,">"&J$2,'Attainment Query Data'!$G:$G,"<="&J$3) -> #VALUE! | K14: =countifs(#REF!,$B14,'Attainment Query Data'!$H:$H,$C14,'Attainment Query Data'!$G:$G,">"&K$2,'Attainment Query Data'!$G:$G,"<="&K$3) -> #VALUE! | ... W14: =countifs(#REF!,$B14,'Attainment Query Data'!$H:$H,$C14,'Attainment Query Data'!$G:$G,">"&W$2,'Attainment Query Data'!$G:$G,"<="&W$3) -> #VALUE!
B15: Europe | C15: Vouchers | D15: =countifs(#REF!,$B15,'Attainment Query Data'!$H:$H,$C15,'Attainment Query Data'!$G:$G,">"&D$2,'Attainment Query Data'!$G:$G,"<="&D$3) -> #VALUE! | E15: =countifs(#REF!,$B15,'Attainment Query Data'!$H:$H,$C15,'Attainment Query Data'!$G:$G,">"&E$2,'Attainment Query Data'!$G:$G,"<="&E$3) -> #VALUE! | F15: =countifs(#REF!,$B15,'Attainment Query Data'!$H:$H,$C15,'Attainment Query Data'!$G:$G,">"&F$2,'Attainment Query Data'!$G:$G,"<="&F$3) -> #VALUE! | G15: =countifs(#REF!,$B15,'Attainment Query Data'!$H:$H,$C15,'Attainment Query Data'!$G:$G,">"&G$2,'Attainment Query Data'!$G:$G,"<="&G$3) -> #VALUE! | H15: =countifs(#REF!,$B15,'Attainment Query Data'!$H:$H,$C15,'Attainment Query Data'!$G:$G,">"&H$2,'Attainment Query Data'!$G:$G,"<="&H$3) -> #VALUE! | I15: =countifs(#REF!,$B15,'Attainment Query Data'!$H:$H,$C15,'Attainment Query Data'!$G:$G,">"&I$2,'Attainment Query Data'!$G:$G,"<="&I$3) -> #VALUE! | J15: =countifs(#REF!,$B15,'Attainment Query Data'!$H:$H,$C15,'Attainment Query Data'!$G:$G,">"&J$2,'Attainment Query Data'!$G:$G,"<="&J$3) -> #VALUE! | K15: =countifs(#REF!,$B15,'Attainment Query Data'!$H:$H,$C15,'Attainment Query Data'!$G:$G,">"&K$2,'Attainment Query Data'!$G:$G,"<="&K$3) -> #VALUE! | ... W15: =countifs(#REF!,$B15,'Attainment Query Data'!$H:$H,$C15,'Attainment Query Data'!$G:$G,">"&W$2,'Attainment Query Data'!$G:$G,"<="&W$3) -> #VALUE!
B16: Europe | C16: E4B Vouchers | D16: =countifs(#REF!,$B16,'Attainment Query Data'!$H:$H,$C16,'Attainment Query Data'!$G:$G,">"&D$2,'Attainment Query Data'!$G:$G,"<="&D$3) -> #VALUE! | E16: =countifs(#REF!,$B16,'Attainment Query Data'!$H:$H,$C16,'Attainment Query Data'!$G:$G,">"&E$2,'Attainment Query Data'!$G:$G,"<="&E$3) -> #VALUE! | F16: =countifs(#REF!,$B16,'Attainment Query Data'!$H:$H,$C16,'Attainment Query Data'!$G:$G,">"&F$2,'Attainment Query Data'!$G:$G,"<="&F$3) -> #VALUE! | G16: =countifs(#REF!,$B16,'Attainment Query Data'!$H:$H,$C16,'Attainment Query Data'!$G:$G,">"&G$2,'Attainment Query Data'!$G:$G,"<="&G$3) -> #VALUE! | H16: =countifs(#REF!,$B16,'Attainment Query Data'!$H:$H,$C16,'Attainment Query Data'!$G:$G,">"&H$2,'Attainment Query Data'!$G:$G,"<="&H$3) -> #VALUE! | I16: =countifs(#REF!,$B16,'Attainment Query Data'!$H:$H,$C16,'Attainment Query Data'!$G:$G,">"&I$2,'Attainment Query Data'!$G:$G,"<="&I$3) -> #VALUE! | J16: =countifs(#REF!,$B16,'Attainment Query Data'!$H:$H,$C16,'Attainment Query Data'!$G:$G,">"&J$2,'Attainment Query Data'!$G:$G,"<="&J$3) -> #VALUE! | K16: =countifs(#REF!,$B16,'Attainment Query Data'!$H:$H,$C16,'Attainment Query Data'!$G:$G,">"&K$2,'Attainment Query Data'!$G:$G,"<="&K$3) -> #VALUE! | ... W16: =countifs(#REF!,$B16,'Attainment Query Data'!$H:$H,$C16,'Attainment Query Data'!$G:$G,">"&W$2,'Attainment Query Data'!$G:$G,"<="&W$3) -> #VALUE!
B17: Europe | C17: Central | D17: =countifs(#REF!,$B17,'Attainment Query Data'!$H:$H,$C17,'Attainment Query Data'!$G:$G,">"&D$2,'Attainment Query Data'!$G:$G,"<="&D$3) -> #VALUE! | E17: =countifs(#REF!,$B17,'Attainment Query Data'!$H:$H,$C17,'Attainment Query Data'!$G:$G,">"&E$2,'Attainment Query Data'!$G:$G,"<="&E$3) -> #VALUE! | F17: =countifs(#REF!,$B17,'Attainment Query Data'!$H:$H,$C17,'Attainment Query Data'!$G:$G,">"&F$2,'Attainment Query Data'!$G:$G,"<="&F$3) -> #VALUE! | G17: =countifs(#REF!,$B17,'Attainment Query Data'!$H:$H,$C17,'Attainment Query Data'!$G:$G,">"&G$2,'Attainment Query Data'!$G:$G,"<="&G$3) -> #VALUE! | H17: =countifs(#REF!,$B17,'Attainment Query Data'!$H:$H,$C17,'Attainment Query Data'!$G:$G,">"&H$2,'Attainment Query Data'!$G:$G,"<="&H$3) -> #VALUE! | I17: =countifs(#REF!,$B17,'Attainment Query Data'!$H:$H,$C17,'Attainment Query Data'!$G:$G,">"&I$2,'Attainment Query Data'!$G:$G,"<="&I$3) -> #VALUE! | J17: =countifs(#REF!,$B17,'Attainment Query Data'!$H:$H,$C17,'Attainment Query Data'!$G:$G,">"&J$2,'Attainment Query Data'!$G:$G,"<="&J$3) -> #VALUE! | K17: =countifs(#REF!,$B17,'Attainment Query Data'!$H:$H,$C17,'Attainment Query Data'!$G:$G,">"&K$2,'Attainment Query Data'!$G:$G,"<="&K$3) -> #VALUE! | ... W17: =countifs(#REF!,$B17,'Attainment Query Data'!$H:$H,$C17,'Attainment Query Data'!$G:$G,">"&W$2,'Attainment Query Data'!$G:$G,"<="&W$3) -> #VALUE!
B18: Europe | C18: Eats | D18: =countifs(#REF!,$B18,'Attainment Query Data'!$H:$H,$C18,'Attainment Query Data'!$G:$G,">"&D$2,'Attainment Query Data'!$G:$G,"<="&D$3) -> #VALUE! | E18: =countifs(#REF!,$B18,'Attainment Query Data'!$H:$H,$C18,'Attainment Query Data'!$G:$G,">"&E$2,'Attainment Query Data'!$G:$G,"<="&E$3) -> #VALUE! | F18: =countifs(#REF!,$B18,'Attainment Query Data'!$H:$H,$C18,'Attainment Query Data'!$G:$G,">"&F$2,'Attainment Query Data'!$G:$G,"<="&F$3) -> #VALUE! | G18: =countifs(#REF!,$B18,'Attainment Query Data'!$H:$H,$C18,'Attainment Query Data'!$G:$G,">"&G$2,'Attainment Query Data'!$G:$G,"<="&G$3) -> #VALUE! | H18: =countifs(#REF!,$B18,'Attainment Query Data'!$H:$H,$C18,'Attainment Query Data'!$G:$G,">"&H$2,'Attainment Query Data'!$G:$G,"<="&H$3) -> #VALUE! | I18: =countifs(#REF!,$B18,'Attainment Query Data'!$H:$H,$C18,'Attainment Query Data'!$G:$G,">"&I$2,'Attainment Query Data'!$G:$G,"<="&I$3) -> #VALUE! | J18: =countifs(#REF!,$B18,'Attainment Query Data'!$H:$H,$C18,'Attainment Query Data'!$G:$G,">"&J$2,'Attainment Query Data'!$G:$G,"<="&J$3) -> #VALUE! | K18: =countifs(#REF!,$B18,'Attainment Query Data'!$H:$H,$C18,'Attainment Query Data'!$G:$G,">"&K$2,'Attainment Query Data'!$G:$G,"<="&K$3) -> #VALUE! | ... W18: =countifs(#REF!,$B18,'Attainment Query Data'!$H:$H,$C18,'Attainment Query Data'!$G:$G,">"&W$2,'Attainment Query Data'!$G:$G,"<="&W$3) -> #VALUE!
B19: Europe | C19: Gift Card | D19: =countifs(#REF!,$B19,'Attainment Query Data'!$H:$H,$C19,'Attainment Query Data'!$G:$G,">"&D$2,'Attainment Query Data'!$G:$G,"<="&D$3) -> #VALUE! | E19: =countifs(#REF!,$B19,'Attainment Query Data'!$H:$H,$C19,'Attainment Query Data'!$G:$G,">"&E$2,'Attainment Query Data'!$G:$G,"<="&E$3) -> #VALUE! | F19: =countifs(#REF!,$B19,'Attainment Query Data'!$H:$H,$C19,'Attainment Query Data'!$G:$G,">"&F$2,'Attainment Query Data'!$G:$G,"<="&F$3) -> #VALUE! | G19: =countifs(#REF!,$B19,'Attainment Query Data'!$H:$H,$C19,'Attainment Query Data'!$G:$G,">"&G$2,'Attainment Query Data'!$G:$G,"<="&G$3) -> #VALUE! | H19: =countifs(#REF!,$B19,'Attainment Query Data'!$H:$H,$C19,'Attainment Query Data'!$G:$G,">"&H$2,'Attainment Query Data'!$G:$G,"<="&H$3) -> #VALUE! | I19: =countifs(#REF!,$B19,'Attainment Query Data'!$H:$H,$C19,'Attainment Query Data'!$G:$G,">"&I$2,'Attainment Query Data'!$G:$G,"<="&I$3) -> #VALUE! | J19: =countifs(#REF!,$B19,'Attainment Query Data'!$H:$H,$C19,'Attainment Query Data'!$G:$G,">"&J$2,'Attainment Query Data'!$G:$G,"<="&J$3) -> #VALUE! | K19: =countifs(#REF!,$B19,'Attainment Query Data'!$H:$H,$C19,'Attainment Query Data'!$G:$G,">"&K$2,'Attainment Query Data'!$G:$G,"<="&K$3) -> #VALUE! | ... W19: =countifs(#REF!,$B19,'Attainment Query Data'!$H:$H,$C19,'Attainment Query Data'!$G:$G,">"&W$2,'Attainment Query Data'!$G:$G,"<="&W$3) -> #VALUE!
C20: Total | D20: =SUM(D14:D19) -> #VALUE! | E20: =SUM(E14:E19) -> #VALUE! | F20: =SUM(F14:F19) -> #VALUE! | G20: =SUM(G14:G19) -> #VALUE! | H20: =SUM(H14:H19) -> #VALUE! | I20: =SUM(I14:I19) -> #VALUE! | J20: =SUM(J14:J19) -> #VALUE! | K20: =SUM(K14:K19) -> #VALUE! | ... W20: =SUM(W14:W19) -> #VALUE!
B22: Mega Region | C22: Product | D22: 2/18 to 2/25 | E22: 2/25 to 3/3 | F22: 3/3 to 3/10 | G22: 3/10 to 3/17 | H22: 3/17 to 3/24 | I22: 3/24 to 3/31 | J22: 3/31 to 4/7 | K22: 4/7 to 4/14 | L22: 4/14 to 4/21 | M22: 4/21 to 4/28 | N22: 4/28 to 5/5 | O22: 5/5 to 5/12 | P22: 5/12 to 5/19 | Q22: 5/19 to 5/26 | R22: 5/26 to 6/2 | S22: 6/2 to 6/9 | T22: 6/9 to 6/16 | U22: 6/16 to 6/23 | V22: 6/23 to 6/30 | W22: 7/1 to 7/7
B23: MEA | C23: Travel | D23: =countifs(#REF!,$B23,'Attainment Query Data'!$H:$H,$C23,'Attainment Query Data'!$G:$G,">"&D$2,'Attainment Query Data'!$G:$G,"<="&D$3) -> #VALUE! | E23: =countifs(#REF!,$B23,'Attainment Query Data'!$H:$H,$C23,'Attainment Query Data'!$G:$G,">"&E$2,'Attainment Query Data'!$G:$G,"<="&E$3) -> #VALUE! | F23: =countifs(#REF!,$B23,'Attainment Query Data'!$H:$H,$C23,'Attainment Query Data'!$G:$G,">"&F$2,'Attainment Query Data'!$G:$G,"<="&F$3) -> #VALUE! | G23: =countifs(#REF!,$B23,'Attainment Query Data'!$H:$H,$C23,'Attainment Query Data'!$G:$G,">"&G$2,'Attainment Query Data'!$G:$G,"<="&G$3) -> #VALUE! | H23: =countifs(#REF!,$B23,'Attainment Query Data'!$H:$H,$C23,'Attainment Query Data'!$G:$G,">"&H$2,'Attainment Query Data'!$G:$G,"<="&H$3) -> #VALUE! | I23: =countifs(#REF!,$B23,'Attainment Query Data'!$H:$H,$C23,'Attainment Query Data'!$G:$G,">"&I$2,'Attainment Query Data'!$G:$G,"<="&I$3) -> #VALUE! | J23: =countifs(#REF!,$B23,'Attainment Query Data'!$H:$H,$C23,'Attainment Query Data'!$G:$G,">"&J$2,'Attainment Query Data'!$G:$G,"<="&J$3) -> #VALUE! | K23: =countifs(#REF!,$B23,'Attainment Query Data'!$H:$H,$C23,'Attainment Query Data'!$G:$G,">"&K$2,'Attainment Query Data'!$G:$G,"<="&K$3) -> #VALUE! | ... W23: =countifs(#REF!,$B23,'Attainment Query Data'!$H:$H,$C23,'Attainment Query Data'!$G:$G,">"&W$2,'Attainment Query Data'!$G:$G,"<="&W$3) -> #VALUE!
B24: MEA | C24: Vouchers | D24: =countifs(#REF!,$B24,'Attainment Query Data'!$H:$H,$C24,'Attainment Query Data'!$G:$G,">"&D$2,'Attainment Query Data'!$G:$G,"<="&D$3) -> #VALUE! | E24: =countifs(#REF!,$B24,'Attainment Query Data'!$H:$H,$C24,'Attainment Query Data'!$G:$G,">"&E$2,'Attainment Query Data'!$G:$G,"<="&E$3) -> #VALUE! | F24: =countifs(#REF!,$B24,'Attainment Query Data'!$H:$H,$C24,'Attainment Query Data'!$G:$G,">"&F$2,'Attainment Query Data'!$G:$G,"<="&F$3) -> #VALUE! | G24: =countifs(#REF!,$B24,'Attainment Query Data'!$H:$H,$C24,'Attainment Query Data'!$G:$G,">"&G$2,'Attainment Query Data'!$G:$G,"<="&G$3) -> #VALUE! | H24: =countifs(#REF!,$B24,'Attainment Query Data'!$H:$H,$C24,'Attainment Query Data'!$G:$G,">"&H$2,'Attainment Query Data'!$G:$G,"<="&H$3) -> #VALUE! | I24: =countifs(#REF!,$B24,'Attainment Query Data'!$H:$H,$C24,'Attainment Query Data'!$G:$G,">"&I$2,'Attainment Query Data'!$G:$G,"<="&I$3) -> #VALUE! | J24: =countifs(#REF!,$B24,'Attainment Query Data'!$H:$H,$C24,'Attainment Query Data'!$G:$G,">"&J$2,'Attainment Query Data'!$G:$G,"<="&J$3) -> #VALUE! | K24: =countifs(#REF!,$B24,'Attainment Query Data'!$H:$H,$C24,'Attainment Query Data'!$G:$G,">"&K$2,'Attainment Query Data'!$G:$G,"<="&K$3) -> #VALUE! | ... W24: =countifs(#REF!,$B24,'Attainment Query Data'!$H:$H,$C24,'Attainment Query Data'!$G:$G,">"&W$2,'Attainment Query Data'!$G:$G,"<="&W$3) -> #VALUE!
B25: MEA | C25: E4B Vouchers | D25: =countifs(#REF!,$B25,'Attainment Query Data'!$H:$H,$C25,'Attainment Query Data'!$G:$G,">"&D$2,'Attainment Query Data'!$G:$G,"<="&D$3) -> #VALUE! | E25: =countifs(#REF!,$B25,'Attainment Query Data'!$H:$H,$C25,'Attainment Query Data'!$G:$G,">"&E$2,'Attainment Query Data'!$G:$G,"<="&E$3) -> #VALUE! | F25: =countifs(#REF!,$B25,'Attainment Query Data'!$H:$H,$C25,'Attainment Query Data'!$G:$G,">"&F$2,'Attainment Query Data'!$G:$G,"<="&F$3) -> #VALUE! | G25: =countifs(#REF!,$B25,'Attainment Query Data'!$H:$H,$C25,'Attainment Query Data'!$G:$G,">"&G$2,'Attainment Query Data'!$G:$G,"<="&G$3) -> #VALUE! | H25: =countifs(#REF!,$B25,'Attainment Query Data'!$H:$H,$C25,'Attainment Query Data'!$G:$G,">"&H$2,'Attainment Query Data'!$G:$G,"<="&H$3) -> #VALUE! | I25: =countifs(#REF!,$B25,'Attainment Query Data'!$H:$H,$C25,'Attainment Query Data'!$G:$G,">"&I$2,'Attainment Query Data'!$G:$G,"<="&I$3) -> #VALUE! | J25: =countifs(#REF!,$B25,'Attainment Query Data'!$H:$H,$C25,'Attainment Query Data'!$G:$G,">"&J$2,'Attainment Query Data'!$G:$G,"<="&J$3) -> #VALUE! | K25: =countifs(#REF!,$B25,'Attainment Query Data'!$H:$H,$C25,'Attainment Query Data'!$G:$G,">"&K$2,'Attainment Query Data'!$G:$G,"<="&K$3) -> #VALUE! | ... W25: =countifs(#REF!,$B25,'Attainment Query Data'!$H:$H,$C25,'Attainment Query Data'!$G:$G,">"&W$2,'Attainment Query Data'!$G:$G,"<="&W$3) -> #VALUE!
B26: MEA | C26: Central | D26: =countifs(#REF!,$B26,'Attainment Query Data'!$H:$H,$C26,'Attainment Query Data'!$G:$G,">"&D$2,'Attainment Query Data'!$G:$G,"<="&D$3) -> #VALUE! | E26: =countifs(#REF!,$B26,'Attainment Query Data'!$H:$H,$C26,'Attainment Query Data'!$G:$G,">"&E$2,'Attainment Query Data'!$G:$G,"<="&E$3) -> #VALUE! | F26: =countifs(#REF!,$B26,'Attainment Query Data'!$H:$H,$C26,'Attainment Query Data'!$G:$G,">"&F$2,'Attainment Query Data'!$G:$G,"<="&F$3) -> #VALUE! | G26: =countifs(#REF!,$B26,'Attainment Query Data'!$H:$H,$C26,'Attainment Query Data'!$G:$G,">"&G$2,'Attainment Query Data'!$G:$G,"<="&G$3) -> #VALUE! | H26: =countifs(#REF!,$B26,'Attainment Query Data'!$H:$H,$C26,'Attainment Query Data'!$G:$G,">"&H$2,'Attainment Query Data'!$G:$G,"<="&H$3) -> #VALUE! | I26: =countifs(#REF!,$B26,'Attainment Query Data'!$H:$H,$C26,'Attainment Query Data'!$G:$G,">"&I$2,'Attainment Query Data'!$G:$G,"<="&I$3) -> #VALUE! | J26: =countifs(#REF!,$B26,'Attainment Query Data'!$H:$H,$C26,'Attainment Query Data'!$G:$G,">"&J$2,'Attainment Query Data'!$G:$G,"<="&J$3) -> #VALUE! | K26: =countifs(#REF!,$B26,'Attainment Query Data'!$H:$H,$C26,'Attainment Query Data'!$G:$G,">"&K$2,'Attainment Query Data'!$G:$G,"<="&K$3) -> #VALUE! | ... W26: =countifs(#REF!,$B26,'Attainment Query Data'!$H:$H,$C26,'Attainment Query Data'!$G:$G,">"&W$2,'Attainment Query Data'!$G:$G,"<="&W$3) -> #VALUE!
B27: MEA | C27: Eats | D27: =countifs(#REF!,$B27,'Attainment Query Data'!$H:$H,$C27,'Attainment Query Data'!$G:$G,">"&D$2,'Attainment Query Data'!$G:$G,"<="&D$3) -> #VALUE! | E27: =countifs(#REF!,$B27,'Attainment Query Data'!$H:$H,$C27,'Attainment Query Data'!$G:$G,">"&E$2,'Attainment Query Data'!$G:$G,"<="&E$3) -> #VALUE! | F27: =countifs(#REF!,$B27,'Attainment Query Data'!$H:$H,$C27,'Attainment Query Data'!$G:$G,">"&F$2,'Attainment Query Data'!$G:$G,"<="&F$3) -> #VALUE! | G27: =countifs(#REF!,$B27,'Attainment Query Data'!$H:$H,$C27,'Attainment Query Data'!$G:$G,">"&G$2,'Attainment Query Data'!$G:$G,"<="&G$3) -> #VALUE! | H27: =countifs(#REF!,$B27,'Attainment Query Data'!$H:$H,$C27,'Attainment Query Data'!$G:$G,">"&H$2,'Attainment Query Data'!$G:$G,"<="&H$3) -> #VALUE! | I27: =countifs(#REF!,$B27,'Attainment Query Data'!$H:$H,$C27,'Attainment Query Data'!$G:$G,">"&I$2,'Attainment Query Data'!$G:$G,"<="&I$3) -> #VALUE! | J27: =countifs(#REF!,$B27,'Attainment Query Data'!$H:$H,$C27,'Attainment Query Data'!$G:$G,">"&J$2,'Attainment Query Data'!$G:$G,"<="&J$3) -> #VALUE! | K27: =countifs(#REF!,$B27,'Attainment Query Data'!$H:$H,$C27,'Attainment Query Data'!$G:$G,">"&K$2,'Attainment Query Data'!$G:$G,"<="&K$3) -> #VALUE! | ... W27: =countifs(#REF!,$B27,'Attainment Query Data'!$H:$H,$C27,'Attainment Query Data'!$G:$G,">"&W$2,'Attainment Query Data'!$G:$G,"<="&W$3) -> #VALUE!
B28: MEA | C28: Gift Card | D28: =countifs(#REF!,$B28,'Attainment Query Data'!$H:$H,$C28,'Attainment Query Data'!$G:$G,">"&D$2,'Attainment Query Data'!$G:$G,"<="&D$3) -> #VALUE! | E28: =countifs(#REF!,$B28,'Attainment Query Data'!$H:$H,$C28,'Attainment Query Data'!$G:$G,">"&E$2,'Attainment Query Data'!$G:$G,"<="&E$3) -> #VALUE! | F28: =countifs(#REF!,$B28,'Attainment Query Data'!$H:$H,$C28,'Attainment Query Data'!$G:$G,">"&F$2,'Attainment Query Data'!$G:$G,"<="&F$3) -> #VALUE! | G28: =countifs(#REF!,$B28,'Attainment Query Data'!$H:$H,$C28,'Attainment Query Data'!$G:$G,">"&G$2,'Attainment Query Data'!$G:$G,"<="&G$3) -> #VALUE! | H28: =countifs(#REF!,$B28,'Attainment Query Data'!$H:$H,$C28,'Attainment Query Data'!$G:$G,">"&H$2,'Attainment Query Data'!$G:$G,"<="&H$3) -> #VALUE! | I28: =countifs(#REF!,$B28,'Attainment Query Data'!$H:$H,$C28,'Attainment Query Data'!$G:$G,">"&I$2,'Attainment Query Data'!$G:$G,"<="&I$3) -> #VALUE! | J28: =countifs(#REF!,$B28,'Attainment Query Data'!$H:$H,$C28,'Attainment Query Data'!$G:$G,">"&J$2,'Attainment Query Data'!$G:$G,"<="&J$3) -> #VALUE! | K28: =countifs(#REF!,$B28,'Attainment Query Data'!$H:$H,$C28,'Attainment Query Data'!$G:$G,">"&K$2,'Attainment Query Data'!$G:$G,"<="&K$3) -> #VALUE! | ... W28: =countifs(#REF!,$B28,'Attainment Query Data'!$H:$H,$C28,'Attainment Query Data'!$G:$G,">"&W$2,'Attainment Query Data'!$G:$G,"<="&W$3) -> #VALUE!
C29: Total | D29: =SUM(D23:D28) -> #VALUE! | E29: =SUM(E23:E28) -> #VALUE! | F29: =SUM(F23:F28) -> #VALUE! | G29: =SUM(G23:G28) -> #VALUE! | H29: =SUM(H23:H28) -> #VALUE! | I29: =SUM(I23:I28) -> #VALUE! | J29: =SUM(J23:J28) -> #VALUE! | K29: =SUM(K23:K28) -> #VALUE! | ... W29: =SUM(W23:W28) -> #VALUE!
B31: , | C31: Product | D31: 2/18 to 2/25 | E31: 2/25 to 3/3 | F31: 3/3 to 3/10 | G31: 3/10 to 3/17 | H31: 3/17 to 3/24 | I31: 3/24 to 3/31 | J31: 3/31 to 4/7 | K31: 4/7 to 4/14 | L31: 4/14 to 4/21 | M31: 4/21 to 4/28 | N31: 4/28 to 5/5 | O31: 5/5 to 5/12 | P31: 5/12 to 5/19 | Q31: 5/19 to 5/26 | R31: 5/26 to 6/2 | S31: 6/2 to 6/9 | T31: 6/9 to 6/16 | U31: 6/16 to 6/23 | V31: 6/23 to 6/30 | W31: 7/1 to 7/7
B32: India | C32: Travel | D32: =countifs(#REF!,$B32,'Attainment Query Data'!$H:$H,$C32,'Attainment Query Data'!$G:$G,">"&D$2,'Attainment Query Data'!$G:$G,"<="&D$3) -> #VALUE! | E32: =countifs(#REF!,$B32,'Attainment Query Data'!$H:$H,$C32,'Attainment Query Data'!$G:$G,">"&E$2,'Attainment Query Data'!$G:$G,"<="&E$3) -> #VALUE! | F32: =countifs(#REF!,$B32,'Attainment Query Data'!$H:$H,$C32,'Attainment Query Data'!$G:$G,">"&F$2,'Attainment Query Data'!$G:$G,"<="&F$3) -> #VALUE! | G32: =countifs(#REF!,$B32,'Attainment Query Data'!$H:$H,$C32,'Attainment Query Data'!$G:$G,">"&G$2,'Attainment Query Data'!$G:$G,"<="&G$3) -> #VALUE! | H32: =countifs(#REF!,$B32,'Attainment Query Data'!$H:$H,$C32,'Attainment Query Data'!$G:$G,">"&H$2,'Attainment Query Data'!$G:$G,"<="&H$3) -> #VALUE! | I32: =countifs(#REF!,$B32,'Attainment Query Data'!$H:$H,$C32,'Attainment Query Data'!$G:$G,">"&I$2,'Attainment Query Data'!$G:$G,"<="&I$3) -> #VALUE! | J32: =countifs(#REF!,$B32,'Attainment Query Data'!$H:$H,$C32,'Attainment Query Data'!$G:$G,">"&J$2,'Attainment Query Data'!$G:$G,"<="&J$3) -> #VALUE! | K32: =countifs(#REF!,$B32,'Attainment Query Data'!$H:$H,$C32,'Attainment Query Data'!$G:$G,">"&K$2,'Attainment Query Data'!$G:$G,"<="&K$3) -> #VALUE! | ... W32: =countifs(#REF!,$B32,'Attainment Query Data'!$H:$H,$C32,'Attainment Query Data'!$G:$G,">"&W$2,'Attainment Query Data'!$G:$G,"<="&W$3) -> #VALUE!
B33: India | C33: Vouchers | D33: =countifs(#REF!,$B33,'Attainment Query Data'!$H:$H,$C33,'Attainment Query Data'!$G:$G,">"&D$2,'Attainment Query Data'!$G:$G,"<="&D$3) -> #VALUE! | E33: =countifs(#REF!,$B33,'Attainment Query Data'!$H:$H,$C33,'Attainment Query Data'!$G:$G,">"&E$2,'Attainment Query Data'!$G:$G,"<="&E$3) -> #VALUE! | F33: =countifs(#REF!,$B33,'Attainment Query Data'!$H:$H,$C33,'Attainment Query Data'!$G:$G,">"&F$2,'Attainment Query Data'!$G:$G,"<="&F$3) -> #VALUE! | G33: =countifs(#REF!,$B33,'Attainment Query Data'!$H:$H,$C33,'Attainment Query Data'!$G:$G,">"&G$2,'Attainment Query Data'!$G:$G,"<="&G$3) -> #VALUE! | H33: =countifs(#REF!,$B33,'Attainment Query Data'!$H:$H,$C33,'Attainment Query Data'!$G:$G,">"&H$2,'Attainment Query Data'!$G:$G,"<="&H$3) -> #VALUE! | I33: =countifs(#REF!,$B33,'Attainment Query Data'!$H:$H,$C33,'Attainment Query Data'!$G:$G,">"&I$2,'Attainment Query Data'!$G:$G,"<="&I$3) -> #VALUE! | J33: =countifs(#REF!,$B33,'Attainment Query Data'!$H:$H,$C33,'Attainment Query Data'!$G:$G,">"&J$2,'Attainment Query Data'!$G:$G,"<="&J$3) -> #VALUE! | K33: =countifs(#REF!,$B33,'Attainment Query Data'!$H:$H,$C33,'Attainment Query Data'!$G:$G,">"&K$2,'Attainment Query Data'!$G:$G,"<="&K$3) -> #VALUE! | ... W33: =countifs(#REF!,$B33,'Attainment Query Data'!$H:$H,$C33,'Attainment Query Data'!$G:$G,">"&W$2,'Attainment Query Data'!$G:$G,"<="&W$3) -> #VALUE!
B34: India | C34: E4B Vouchers | D34: =countifs(#REF!,$B34,'Attainment Query Data'!$H:$H,$C34,'Attainment Query Data'!$G:$G,">"&D$2,'Attainment Query Data'!$G:$G,"<="&D$3) -> #VALUE! | E34: =countifs(#REF!,$B34,'Attainment Query Data'!$H:$H,$C34,'Attainment Query Data'!$G:$G,">"&E$2,'Attainment Query Data'!$G:$G,"<="&E$3) -> #VALUE! | F34: =countifs(#REF!,$B34,'Attainment Query Data'!$H:$H,$C34,'Attainment Query Data'!$G:$G,">"&F$2,'Attainment Query Data'!$G:$G,"<="&F$3) -> #VALUE! | G34: =countifs(#REF!,$B34,'Attainment Query Data'!$H:$H,$C34,'Attainment Query Data'!$G:$G,">"&G$2,'Attainment Query Data'!$G:$G,"<="&G$3) -> #VALUE! | H34: =countifs(#REF!,$B34,'Attainment Query Data'!$H:$H,$C34,'Attainment Query Data'!$G:$G,">"&H$2,'Attainment Query Data'!$G:$G,"<="&H$3) -> #VALUE! | I34: =countifs(#REF!,$B34,'Attainment Query Data'!$H:$H,$C34,'Attainment Query Data'!$G:$G,">"&I$2,'Attainment Query Data'!$G:$G,"<="&I$3) -> #VALUE! | J34: =countifs(#REF!,$B34,'Attainment Query Data'!$H:$H,$C34,'Attainment Query Data'!$G:$G,">"&J$2,'Attainment Query Data'!$G:$G,"<="&J$3) -> #VALUE! | K34: =countifs(#REF!,$B34,'Attainment Query Data'!$H:$H,$C34,'Attainment Query Data'!$G:$G,">"&K$2,'Attainment Query Data'!$G:$G,"<="&K$3) -> #VALUE! | ... W34: =countifs(#REF!,$B34,'Attainment Query Data'!$H:$H,$C34,'Attainment Query Data'!$G:$G,">"&W$2,'Attainment Query Data'!$G:$G,"<="&W$3) -> #VALUE!
B35: India | C35: Central | D35: =countifs(#REF!,$B35,'Attainment Query Data'!$H:$H,$C35,'Attainment Query Data'!$G:$G,">"&D$2,'Attainment Query Data'!$G:$G,"<="&D$3) -> #VALUE! | E35: =countifs(#REF!,$B35,'Attainment Query Data'!$H:$H,$C35,'Attainment Query Data'!$G:$G,">"&E$2,'Attainment Query Data'!$G:$G,"<="&E$3) -> #VALUE! | F35: =countifs(#REF!,$B35,'Attainment Query Data'!$H:$H,$C35,'Attainment Query Data'!$G:$G,">"&F$2,'Attainment Query Data'!$G:$G,"<="&F$3) -> #VALUE! | G35: =countifs(#REF!,$B35,'Attainment Query Data'!$H:$H,$C35,'Attainment Query Data'!$G:$G,">"&G$2,'Attainment Query Data'!$G:$G,"<="&G$3) -> #VALUE! | H35: =countifs(#REF!,$B35,'Attainment Query Data'!$H:$H,$C35,'Attainment Query Data'!$G:$G,">"&H$2,'Attainment Query Data'!$G:$G,"<="&H$3) -> #VALUE! | I35: =countifs(#REF!,$B35,'Attainment Query Data'!$H:$H,$C35,'Attainment Query Data'!$G:$G,">"&I$2,'Attainment Query Data'!$G:$G,"<="&I$3) -> #VALUE! | J35: =countifs(#REF!,$B35,'Attainment Query Data'!$H:$H,$C35,'Attainment Query Data'!$G:$G,">"&J$2,'Attainment Query Data'!$G:$G,"<="&J$3) -> #VALUE! | K35: =countifs(#REF!,$B35,'Attainment Query Data'!$H:$H,$C35,'Attainment Query Data'!$G:$G,">"&K$2,'Attainment Query Data'!$G:$G,"<="&K$3) -> #VALUE! | ... W35: =countifs(#REF!,$B35,'Attainment Query Data'!$H:$H,$C35,'Attainment Query Data'!$G:$G,">"&W$2,'Attainment Query Data'!$G:$G,"<="&W$3) -> #VALUE!
B36: India | C36: Eats | D36: =countifs(#REF!,$B36,'Attainment Query Data'!$H:$H,$C36,'Attainment Query Data'!$G:$G,">"&D$2,'Attainment Query Data'!$G:$G,"<="&D$3) -> #VALUE! | E36: =countifs(#REF!,$B36,'Attainment Query Data'!$H:$H,$C36,'Attainment Query Data'!$G:$G,">"&E$2,'Attainment Query Data'!$G:$G,"<="&E$3) -> #VALUE! | F36: =countifs(#REF!,$B36,'Attainment Query Data'!$H:$H,$C36,'Attainment Query Data'!$G:$G,">"&F$2,'Attainment Query Data'!$G:$G,"<="&F$3) -> #VALUE! | G36: =countifs(#REF!,$B36,'Attainment Query Data'!$H:$H,$C36,'Attainment Query Data'!$G:$G,">"&G$2,'Attainment Query Data'!$G:$G,"<="&G$3) -> #VALUE! | H36: =countifs(#REF!,$B36,'Attainment Query Data'!$H:$H,$C36,'Attainment Query Data'!$G:$G,">"&H$2,'Attainment Query Data'!$G:$G,"<="&H$3) -> #VALUE! | I36: =countifs(#REF!,$B36,'Attainment Query Data'!$H:$H,$C36,'Attainment Query Data'!$G:$G,">"&I$2,'Attainment Query Data'!$G:$G,"<="&I$3) -> #VALUE! | J36: =countifs(#REF!,$B36,'Attainment Query Data'!$H:$H,$C36,'Attainment Query Data'!$G:$G,">"&J$2,'Attainment Query Data'!$G:$G,"<="&J$3) -> #VALUE! | K36: =countifs(#REF!,$B36,'Attainment Query Data'!$H:$H,$C36,'Attainment Query Data'!$G:$G,">"&K$2,'Attainment Query Data'!$G:$G,"<="&K$3) -> #VALUE! | ... W36: =countifs(#REF!,$B36,'Attainment Query Data'!$H:$H,$C36,'Attainment Query Data'!$G:$G,">"&W$2,'Attainment Query Data'!$G:$G,"<="&W$3) -> #VALUE!
B37: India | C37: Gift Card | D37: =countifs(#REF!,$B37,'Attainment Query Data'!$H:$H,$C37,'Attainment Query Data'!$G:$G,">"&D$2,'Attainment Query Data'!$G:$G,"<="&D$3) -> #VALUE! | E37: =countifs(#REF!,$B37,'Attainment Query Data'!$H:$H,$C37,'Attainment Query Data'!$G:$G,">"&E$2,'Attainment Query Data'!$G:$G,"<="&E$3) -> #VALUE! | F37: =countifs(#REF!,$B37,'Attainment Query Data'!$H:$H,$C37,'Attainment Query Data'!$G:$G,">"&F$2,'Attainment Query Data'!$G:$G,"<="&F$3) -> #VALUE! | G37: =countifs(#REF!,$B37,'Attainment Query Data'!$H:$H,$C37,'Attainment Query Data'!$G:$G,">"&G$2,'Attainment Query Data'!$G:$G,"<="&G$3) -> #VALUE! | H37: =countifs(#REF!,$B37,'Attainment Query Data'!$H:$H,$C37,'Attainment Query Data'!$G:$G,">"&H$2,'Attainment Query Data'!$G:$G,"<="&H$3) -> #VALUE! | I37: =countifs(#REF!,$B37,'Attainment Query Data'!$H:$H,$C37,'Attainment Query Data'!$G:$G,">"&I$2,'Attainment Query Data'!$G:$G,"<="&I$3) -> #VALUE! | J37: =countifs(#REF!,$B37,'Attainment Query Data'!$H:$H,$C37,'Attainment Query Data'!$G:$G,">"&J$2,'Attainment Query Data'!$G:$G,"<="&J$3) -> #VALUE! | K37: =countifs(#REF!,$B37,'Attainment Query Data'!$H:$H,$C37,'Attainment Query Data'!$G:$G,">"&K$2,'Attainment Query Data'!$G:$G,"<="&K$3) -> #VALUE! | ... W37: =countifs(#REF!,$B37,'Attainment Query Data'!$H:$H,$C37,'Attainment Query Data'!$G:$G,">"&W$2,'Attainment Query Data'!$G:$G,"<="&W$3) -> #VALUE!
C38: Total | D38: =SUM(D32:D37) -> #VALUE! | E38: =SUM(E32:E37) -> #VALUE! | F38: =SUM(F32:F37) -> #VALUE! | G38: =SUM(G32:G37) -> #VALUE! | H38: =SUM(H32:H37) -> #VALUE! | I38: =SUM(I32:I37) -> #VALUE! | J38: =SUM(J32:J37) -> #VALUE! | K38: =SUM(K32:K37) -> #VALUE! | ... W38: =SUM(W32:W37) -> #VALUE!
B40: Mega Region | C40: Product | D40: 2/18 to 2/25 | E40: 2/25 to 3/3 | F40: 3/3 to 3/10 | G40: 3/10 to 3/17 | H40: 3/17 to 3/24 | I40: 3/24 to 3/31 | J40: 3/31 to 4/7 | K40: 4/7 to 4/14 | L40: 4/14 to 4/21 | M40: 4/21 to 4/28 | N40: 4/28 to 5/5 | O40: 5/5 to 5/12 | P40: 5/12 to 5/19 | Q40: 5/19 to 5/26 | R40: 5/26 to 6/2 | S40: 6/2 to 6/9 | T40: 6/9 to 6/16 | U40: 6/16 to 6/23 | V40: 6/23 to 6/30 | W40: 7/1 to 7/7
B41: LatAm | C41: Travel | D41: =countifs(#REF!,$B41,'Attainment Query Data'!$H:$H,$C41,'Attainment Query Data'!$G:$G,">"&D$2,'Attainment Query Data'!$G:$G,"<="&D$3) -> #VALUE! | E41: =countifs(#REF!,$B41,'Attainment Query Data'!$H:$H,$C41,'Attainment Query Data'!$G:$G,">"&E$2,'Attainment Query Data'!$G:$G,"<="&E$3) -> #VALUE! | F41: =countifs(#REF!,$B41,'Attainment Query Data'!$H:$H,$C41,'Attainment Query Data'!$G:$G,">"&F$2,'Attainment Query Data'!$G:$G,"<="&F$3) -> #VALUE! | G41: =countifs(#REF!,$B41,'Attainment Query Data'!$H:$H,$C41,'Attainment Query Data'!$G:$G,">"&G$2,'Attainment Query Data'!$G:$G,"<="&G$3) -> #VALUE! | H41: =countifs(#REF!,$B41,'Attainment Query Data'!$H:$H,$C41,'Attainment Query Data'!$G:$G,">"&H$2,'Attainment Query Data'!$G:$G,"<="&H$3) -> #VALUE! | I41: =countifs(#REF!,$B41,'Attainment Query Data'!$H:$H,$C41,'Attainment Query Data'!$G:$G,">"&I$2,'Attainment Query Data'!$G:$G,"<="&I$3) -> #VALUE! | J41: =countifs(#REF!,$B41,'Attainment Query Data'!$H:$H,$C41,'Attainment Query Data'!$G:$G,">"&J$2,'Attainment Query Data'!$G:$G,"<="&J$3) -> #VALUE! | K41: =countifs(#REF!,$B41,'Attainment Query Data'!$H:$H,$C41,'Attainment Query Data'!$G:$G,">"&K$2,'Attainment Query Data'!$G:$G,"<="&K$3) -> #VALUE! | ... W41: =countifs(#REF!,$B41,'Attainment Query Data'!$H:$H,$C41,'Attainment Query Data'!$G:$G,">"&W$2,'Attainment Query Data'!$G:$G,"<="&W$3) -> #VALUE!
B42: LatAm | C42: Vouchers | D42: =countifs(#REF!,$B42,'Attainment Query Data'!$H:$H,$C42,'Attainment Query Data'!$G:$G,">"&D$2,'Attainment Query Data'!$G:$G,"<="&D$3) -> #VALUE! | E42: =countifs(#REF!,$B42,'Attainment Query Data'!$H:$H,$C42,'Attainment Query Data'!$G:$G,">"&E$2,'Attainment Query Data'!$G:$G,"<="&E$3) -> #VALUE! | F42: =countifs(#REF!,$B42,'Attainment Query Data'!$H:$H,$C42,'Attainment Query Data'!$G:$G,">"&F$2,'Attainment Query Data'!$G:$G,"<="&F$3) -> #VALUE! | G42: =countifs(#REF!,$B42,'Attainment Query Data'!$H:$H,$C42,'Attainment Query Data'!$G:$G,">"&G$2,'Attainment Query Data'!$G:$G,"<="&G$3) -> #VALUE! | H42: =countifs(#REF!,$B42,'Attainment Query Data'!$H:$H,$C42,'Attainment Query Data'!$G:$G,">"&H$2,'Attainment Query Data'!$G:$G,"<="&H$3) -> #VALUE! | I42: =countifs(#REF!,$B42,'Attainment Query Data'!$H:$H,$C42,'Attainment Query Data'!$G:$G,">"&I$2,'Attainment Query Data'!$G:$G,"<="&I$3) -> #VALUE! | J42: =countifs(#REF!,$B42,'Attainment Query Data'!$H:$H,$C42,'Attainment Query Data'!$G:$G,">"&J$2,'Attainment Query Data'!$G:$G,"<="&J$3) -> #VALUE! | K42: =countifs(#REF!,$B42,'Attainment Query Data'!$H:$H,$C42,'Attainment Query Data'!$G:$G,">"&K$2,'Attainment Query Data'!$G:$G,"<="&K$3) -> #VALUE! | ... W42: =countifs(#REF!,$B42,'Attainment Query Data'!$H:$H,$C42,'Attainment Query Data'!$G:$G,">"&W$2,'Attainment Query Data'!$G:$G,"<="&W$3) -> #VALUE!
B43: LatAm | C43: E4B Vouchers | D43: =countifs(#REF!,$B43,'Attainment Query Data'!$H:$H,$C43,'Attainment Query Data'!$G:$G,">"&D$2,'Attainment Query Data'!$G:$G,"<="&D$3) -> #VALUE! | E43: =countifs(#REF!,$B43,'Attainment Query Data'!$H:$H,$C43,'Attainment Query Data'!$G:$G,">"&E$2,'Attainment Query Data'!$G:$G,"<="&E$3) -> #VALUE! | F43: =countifs(#REF!,$B43,'Attainment Query Data'!$H:$H,$C43,'Attainment Query Data'!$G:$G,">"&F$2,'Attainment Query Data'!$G:$G,"<="&F$3) -> #VALUE! | G43: =countifs(#REF!,$B43,'Attainment Query Data'!$H:$H,$C43,'Attainment Query Data'!$G:$G,">"&G$2,'Attainment Query Data'!$G:$G,"<="&G$3) -> #VALUE! | H43: =countifs(#REF!,$B43,'Attainment Query Data'!$H:$H,$C43,'Attainment Query Data'!$G:$G,">"&H$2,'Attainment Query Data'!$G:$G,"<="&H$3) -> #VALUE! | I43: =countifs(#REF!,$B43,'Attainment Query Data'!$H:$H,$C43,'Attainment Query Data'!$G:$G,">"&I$2,'Attainment Query Data'!$G:$G,"<="&I$3) -> #VALUE! | J43: =countifs(#REF!,$B43,'Attainment Query Data'!$H:$H,$C43,'Attainment Query Data'!$G:$G,">"&J$2,'Attainment Query Data'!$G:$G,"<="&J$3) -> #VALUE! | K43: =countifs(#REF!,$B43,'Attainment Query Data'!$H:$H,$C43,'Attainment Query Data'!$G:$G,">"&K$2,'Attainment Query Data'!$G:$G,"<="&K$3) -> #VALUE! | ... W43: =countifs(#REF!,$B43,'Attainment Query Data'!$H:$H,$C43,'Attainment Query Data'!$G:$G,">"&W$2,'Attainment Query Data'!$G:$G,"<="&W$3) -> #VALUE!
B44: LatAm | C44: Central | D44: =countifs(#REF!,$B44,'Attainment Query Data'!$H:$H,$C44,'Attainment Query Data'!$G:$G,">"&D$2,'Attainment Query Data'!$G:$G,"<="&D$3) -> #VALUE! | E44: =countifs(#REF!,$B44,'Attainment Query Data'!$H:$H,$C44,'Attainment Query Data'!$G:$G,">"&E$2,'Attainment Query Data'!$G:$G,"<="&E$3) -> #VALUE! | F44: =countifs(#REF!,$B44,'Attainment Query Data'!$H:$H,$C44,'Attainment Query Data'!$G:$G,">"&F$2,'Attainment Query Data'!$G:$G,"<="&F$3) -> #VALUE! | G44: =countifs(#REF!,$B44,'Attainment Query Data'!$H:$H,$C44,'Attainment Query Data'!$G:$G,">"&G$2,'Attainment Query Data'!$G:$G,"<="&G$3) -> #VALUE! | H44: =countifs(#REF!,$B44,'Attainment Query Data'!$H:$H,$C44,'Attainment Query Data'!$G:$G,">"&H$2,'Attainment Query Data'!$G:$G,"<="&H$3) -> #VALUE! | I44: =countifs(#REF!,$B44,'Attainment Query Data'!$H:$H,$C44,'Attainment Query Data'!$G:$G,">"&I$2,'Attainment Query Data'!$G:$G,"<="&I$3) -> #VALUE! | J44: =countifs(#REF!,$B44,'Attainment Query Data'!$H:$H,$C44,'Attainment Query Data'!$G:$G,">"&J$2,'Attainment Query Data'!$G:$G,"<="&J$3) -> #VALUE! | K44: =countifs(#REF!,$B44,'Attainment Query Data'!$H:$H,$C44,'Attainment Query Data'!$G:$G,">"&K$2,'Attainment Query Data'!$G:$G,"<="&K$3) -> #VALUE! | ... W44: =countifs(#REF!,$B44,'Attainment Query Data'!$H:$H,$C44,'Attainment Query Data'!$G:$G,">"&W$2,'Attainment Query Data'!$G:$G,"<="&W$3) -> #VALUE!
B45: LatAm | C45: Eats | D45: =countifs(#REF!,$B45,'Attainment Query Data'!$H:$H,$C45,'Attainment Query Data'!$G:$G,">"&D$2,'Attainment Query Data'!$G:$G,"<="&D$3) -> #VALUE! | E45: =countifs(#REF!,$B45,'Attainment Query Data'!$H:$H,$C45,'Attainment Query Data'!$G:$G,">"&E$2,'Attainment Query Data'!$G:$G,"<="&E$3) -> #VALUE! | F45: =countifs(#REF!,$B45,'Attainment Query Data'!$H:$H,$C45,'Attainment Query Data'!$G:$G,">"&F$2,'Attainment Query Data'!$G:$G,"<="&F$3) -> #VALUE! | G45: =countifs(#REF!,$B45,'Attainment Query Data'!$H:$H,$C45,'Attainment Query Data'!$G:$G,">"&G$2,'Attainment Query Data'!$G:$G,"<="&G$3) -> #VALUE! | H45: =countifs(#REF!,$B45,'Attainment Query Data'!$H:$H,$C45,'Attainment Query Data'!$G:$G,">"&H$2,'Attainment Query Data'!$G:$G,"<="&H$3) -> #VALUE! | I45: =countifs(#REF!,$B45,'Attainment Query Data'!$H:$H,$C45,'Attainment Query Data'!$G:$G,">"&I$2,'Attainment Query Data'!$G:$G,"<="&I$3) -> #VALUE! | J45: =countifs(#REF!,$B45,'Attainment Query Data'!$H:$H,$C45,'Attainment Query Data'!$G:$G,">"&J$2,'Attainment Query Data'!$G:$G,"<="&J$3) -> #VALUE! | K45: =countifs(#REF!,$B45,'Attainment Query Data'!$H:$H,$C45,'Attainment Query Data'!$G:$G,">"&K$2,'Attainment Query Data'!$G:$G,"<="&K$3) -> #VALUE! | ... W45: =countifs(#REF!,$B45,'Attainment Query Data'!$H:$H,$C45,'Attainment Query Data'!$G:$G,">"&W$2,'Attainment Query Data'!$G:$G,"<="&W$3) -> #VALUE!
B46: LatAm | C46: Gift Card | D46: =countifs(#REF!,$B46,'Attainment Query Data'!$H:$H,$C46,'Attainment Query Data'!$G:$G,">"&D$2,'Attainment Query Data'!$G:$G,"<="&D$3) -> #VALUE! | E46: =countifs(#REF!,$B46,'Attainment Query Data'!$H:$H,$C46,'Attainment Query Data'!$G:$G,">"&E$2,'Attainment Query Data'!$G:$G,"<="&E$3) -> #VALUE! | F46: =countifs(#REF!,$B46,'Attainment Query Data'!$H:$H,$C46,'Attainment Query Data'!$G:$G,">"&F$2,'Attainment Query Data'!$G:$G,"<="&F$3) -> #VALUE! | G46: =countifs(#REF!,$B46,'Attainment Query Data'!$H:$H,$C46,'Attainment Query Data'!$G:$G,">"&G$2,'Attainment Query Data'!$G:$G,"<="&G$3) -> #VALUE! | H46: =countifs(#REF!,$B46,'Attainment Query Data'!$H:$H,$C46,'Attainment Query Data'!$G:$G,">"&H$2,'Attainment Query Data'!$G:$G,"<="&H$3) -> #VALUE! | I46: =countifs(#REF!,$B46,'Attainment Query Data'!$H:$H,$C46,'Attainment Query Data'!$G:$G,">"&I$2,'Attainment Query Data'!$G:$G,"<="&I$3) -> #VALUE! | J46: =countifs(#REF!,$B46,'Attainment Query Data'!$H:$H,$C46,'Attainment Query Data'!$G:$G,">"&J$2,'Attainment Query Data'!$G:$G,"<="&J$3) -> #VALUE! | K46: =countifs(#REF!,$B46,'Attainment Query Data'!$H:$H,$C46,'Attainment Query Data'!$G:$G,">"&K$2,'Attainment Query Data'!$G:$G,"<="&K$3) -> #VALUE! | ... W46: =countifs(#REF!,$B46,'Attainment Query Data'!$H:$H,$C46,'Attainment Query Data'!$G:$G,">"&W$2,'Attainment Query Data'!$G:$G,"<="&W$3) -> #VALUE!
C47: Total | D47: =SUM(D41:D46) -> #VALUE! | E47: =SUM(E41:E46) -> #VALUE! | F47: =SUM(F41:F46) -> #VALUE! | G47: =SUM(G41:G46) -> #VALUE! | H47: =SUM(H41:H46) -> #VALUE! | I47: =SUM(I41:I46) -> #VALUE! | J47: =SUM(J41:J46) -> #VALUE! | K47: =SUM(K41:K46) -> #VALUE! | ... W47: =SUM(W41:W46) -> #VALUE!
B49: Mega Region | C49: Product | D49: 2/18 to 2/25 | E49: 2/25 to 3/3 | F49: 3/3 to 3/10 | G49: 3/10 to 3/17 | H49: 3/17 to 3/24 | I49: 3/24 to 3/31 | J49: 3/31 to 4/7 | K49: 4/7 to 4/14 | L49: 4/14 to 4/21 | M49: 4/21 to 4/28 | N49: 4/28 to 5/5 | O49: 5/5 to 5/12 | P49: 5/12 to 5/19 | Q49: 5/19 to 5/26 | R49: 5/26 to 6/2 | S49: 6/2 to 6/9 | T49: 6/9 to 6/16 | U49: 6/16 to 6/23 | V49: 6/23 to 6/30 | W49: 7/1 to 7/7
B50: US&Can | C50: Travel | D50: =countifs(#REF!,$B50,'Attainment Query Data'!$H:$H,$C50,'Attainment Query Data'!$G:$G,">"&D$2,'Attainment Query Data'!$G:$G,"<="&D$3) -> #VALUE! | E50: =countifs(#REF!,$B50,'Attainment Query Data'!$H:$H,$C50,'Attainment Query Data'!$G:$G,">"&E$2,'Attainment Query Data'!$G:$G,"<="&E$3) -> #VALUE! | F50: =countifs(#REF!,$B50,'Attainment Query Data'!$H:$H,$C50,'Attainment Query Data'!$G:$G,">"&F$2,'Attainment Query Data'!$G:$G,"<="&F$3) -> #VALUE! | G50: =countifs(#REF!,$B50,'Attainment Query Data'!$H:$H,$C50,'Attainment Query Data'!$G:$G,">"&G$2,'Attainment Query Data'!$G:$G,"<="&G$3) -> #VALUE! | H50: =countifs(#REF!,$B50,'Attainment Query Data'!$H:$H,$C50,'Attainment Query Data'!$G:$G,">"&H$2,'Attainment Query Data'!$G:$G,"<="&H$3) -> #VALUE! | I50: =countifs(#REF!,$B50,'Attainment Query Data'!$H:$H,$C50,'Attainment Query Data'!$G:$G,">"&I$2,'Attainment Query Data'!$G:$G,"<="&I$3) -> #VALUE! | J50: =countifs(#REF!,$B50,'Attainment Query Data'!$H:$H,$C50,'Attainment Query Data'!$G:$G,">"&J$2,'Attainment Query Data'!$G:$G,"<="&J$3) -> #VALUE! | K50: =countifs(#REF!,$B50,'Attainment Query Data'!$H:$H,$C50,'Attainment Query Data'!$G:$G,">"&K$2,'Attainment Query Data'!$G:$G,"<="&K$3) -> #VALUE! | ... W50: =countifs(#REF!,$B50,'Attainment Query Data'!$H:$H,$C50,'Attainment Query Data'!$G:$G,">"&W$2,'Attainment Query Data'!$G:$G,"<="&W$3) -> #VALUE!
B51: US&Can | C51: Vouchers | D51: =countifs(#REF!,$B51,'Attainment Query Data'!$H:$H,$C51,'Attainment Query Data'!$G:$G,">"&D$2,'Attainment Query Data'!$G:$G,"<="&D$3) -> #VALUE! | E51: =countifs(#REF!,$B51,'Attainment Query Data'!$H:$H,$C51,'Attainment Query Data'!$G:$G,">"&E$2,'Attainment Query Data'!$G:$G,"<="&E$3) -> #VALUE! | F51: =countifs(#REF!,$B51,'Attainment Query Data'!$H:$H,$C51,'Attainment Query Data'!$G:$G,">"&F$2,'Attainment Query Data'!$G:$G,"<="&F$3) -> #VALUE! | G51: =countifs(#REF!,$B51,'Attainment Query Data'!$H:$H,$C51,'Attainment Query Data'!$G:$G,">"&G$2,'Attainment Query Data'!$G:$G,"<="&G$3) -> #VALUE! | H51: =countifs(#REF!,$B51,'Attainment Query Data'!$H:$H,$C51,'Attainment Query Data'!$G:$G,">"&H$2,'Attainment Query Data'!$G:$G,"<="&H$3) -> #VALUE! | I51: =countifs(#REF!,$B51,'Attainment Query Data'!$H:$H,$C51,'Attainment Query Data'!$G:$G,">"&I$2,'Attainment Query Data'!$G:$G,"<="&I$3) -> #VALUE! | J51: =countifs(#REF!,$B51,'Attainment Query Data'!$H:$H,$C51,'Attainment Query Data'!$G:$G,">"&J$2,'Attainment Query Data'!$G:$G,"<="&J$3) -> #VALUE! | K51: =countifs(#REF!,$B51,'Attainment Query Data'!$H:$H,$C51,'Attainment Query Data'!$G:$G,">"&K$2,'Attainment Query Data'!$G:$G,"<="&K$3) -> #VALUE! | ... W51: =countifs(#REF!,$B51,'Attainment Query Data'!$H:$H,$C51,'Attainment Query Data'!$G:$G,">"&W$2,'Attainment Query Data'!$G:$G,"<="&W$3) -> #VALUE!
B52: US&Can | C52: E4B Vouchers | D52: =countifs(#REF!,$B52,'Attainment Query Data'!$H:$H,$C52,'Attainment Query Data'!$G:$G,">"&D$2,'Attainment Query Data'!$G:$G,"<="&D$3) -> #VALUE! | E52: =countifs(#REF!,$B52,'Attainment Query Data'!$H:$H,$C52,'Attainment Query Data'!$G:$G,">"&E$2,'Attainment Query Data'!$G:$G,"<="&E$3) -> #VALUE! | F52: =countifs(#REF!,$B52,'Attainment Query Data'!$H:$H,$C52,'Attainment Query Data'!$G:$G,">"&F$2,'Attainment Query Data'!$G:$G,"<="&F$3) -> #VALUE! | G52: =countifs(#REF!,$B52,'Attainment Query Data'!$H:$H,$C52,'Attainment Query Data'!$G:$G,">"&G$2,'Attainment Query Data'!$G:$G,"<="&G$3) -> #VALUE! | H52: =countifs(#REF!,$B52,'Attainment Query Data'!$H:$H,$C52,'Attainment Query Data'!$G:$G,">"&H$2,'Attainment Query Data'!$G:$G,"<="&H$3) -> #VALUE! | I52: =countifs(#REF!,$B52,'Attainment Query Data'!$H:$H,$C52,'Attainment Query Data'!$G:$G,">"&I$2,'Attainment Query Data'!$G:$G,"<="&I$3) -> #VALUE! | J52: =countifs(#REF!,$B52,'Attainment Query Data'!$H:$H,$C52,'Attainment Query Data'!$G:$G,">"&J$2,'Attainment Query Data'!$G:$G,"<="&J$3) -> #VALUE! | K52: =countifs(#REF!,$B52,'Attainment Query Data'!$H:$H,$C52,'Attainment Query Data'!$G:$G,">"&K$2,'Attainment Query Data'!$G:$G,"<="&K$3) -> #VALUE! | ... W52: =countifs(#REF!,$B52,'Attainment Query Data'!$H:$H,$C52,'Attainment Query Data'!$G:$G,">"&W$2,'Attainment Query Data'!$G:$G,"<="&W$3) -> #VALUE!
B53: US&Can | C53: Central | D53: =countifs(#REF!,$B53,'Attainment Query Data'!$H:$H,$C53,'Attainment Query Data'!$G:$G,">"&D$2,'Attainment Query Data'!$G:$G,"<="&D$3) -> #VALUE! | E53: =countifs(#REF!,$B53,'Attainment Query Data'!$H:$H,$C53,'Attainment Query Data'!$G:$G,">"&E$2,'Attainment Query Data'!$G:$G,"<="&E$3) -> #VALUE! | F53: =countifs(#REF!,$B53,'Attainment Query Data'!$H:$H,$C53,'Attainment Query Data'!$G:$G,">"&F$2,'Attainment Query Data'!$G:$G,"<="&F$3) -> #VALUE! | G53: =countifs(#REF!,$B53,'Attainment Query Data'!$H:$H,$C53,'Attainment Query Data'!$G:$G,">"&G$2,'Attainment Query Data'!$G:$G,"<="&G$3) -> #VALUE! | H53: =countifs(#REF!,$B53,'Attainment Query Data'!$H:$H,$C53,'Attainment Query Data'!$G:$G,">"&H$2,'Attainment Query Data'!$G:$G,"<="&H$3) -> #VALUE! | I53: =countifs(#REF!,$B53,'Attainment Query Data'!$H:$H,$C53,'Attainment Query Data'!$G:$G,">"&I$2,'Attainment Query Data'!$G:$G,"<="&I$3) -> #VALUE! | J53: =countifs(#REF!,$B53,'Attainment Query Data'!$H:$H,$C53,'Attainment Query Data'!$G:$G,">"&J$2,'Attainment Query Data'!$G:$G,"<="&J$3) -> #VALUE! | K53: =countifs(#REF!,$B53,'Attainment Query Data'!$H:$H,$C53,'Attainment Query Data'!$G:$G,">"&K$2,'Attainment Query Data'!$G:$G,"<="&K$3) -> #VALUE! | ... W53: =countifs(#REF!,$B53,'Attainment Query Data'!$H:$H,$C53,'Attainment Query Data'!$G:$G,">"&W$2,'Attainment Query Data'!$G:$G,"<="&W$3) -> #VALUE!
B54: US&Can | C54: Eats | D54: =countifs(#REF!,$B54,'Attainment Query Data'!$H:$H,$C54,'Attainment Query Data'!$G:$G,">"&D$2,'Attainment Query Data'!$G:$G,"<="&D$3) -> #VALUE! | E54: =countifs(#REF!,$B54,'Attainment Query Data'!$H:$H,$C54,'Attainment Query Data'!$G:$G,">"&E$2,'Attainment Query Data'!$G:$G,"<="&E$3) -> #VALUE! | F54: =countifs(#REF!,$B54,'Attainment Query Data'!$H:$H,$C54,'Attainment Query Data'!$G:$G,">"&F$2,'Attainment Query Data'!$G:$G,"<="&F$3) -> #VALUE! | G54: =countifs(#REF!,$B54,'Attainment Query Data'!$H:$H,$C54,'Attainment Query Data'!$G:$G,">"&G$2,'Attainment Query Data'!$G:$G,"<="&G$3) -> #VALUE! | H54: =countifs(#REF!,$B54,'Attainment Query Data'!$H:$H,$C54,'Attainment Query Data'!$G:$G,">"&H$2,'Attainment Query Data'!$G:$G,"<="&H$3) -> #VALUE! | I54: =countifs(#REF!,$B54,'Attainment Query Data'!$H:$H,$C54,'Attainment Query Data'!$G:$G,">"&I$2,'Attainment Query Data'!$G:$G,"<="&I$3) -> #VALUE! | J54: =countifs(#REF!,$B54,'Attainment Query Data'!$H:$H,$C54,'Attainment Query Data'!$G:$G,">"&J$2,'Attainment Query Data'!$G:$G,"<="&J$3) -> #VALUE! | K54: =countifs(#REF!,$B54,'Attainment Query Data'!$H:$H,$C54,'Attainment Query Data'!$G:$G,">"&K$2,'Attainment Query Data'!$G:$G,"<="&K$3) -> #VALUE! | ... W54: =countifs(#REF!,$B54,'Attainment Query Data'!$H:$H,$C54,'Attainment Query Data'!$G:$G,">"&W$2,'Attainment Query Data'!$G:$G,"<="&W$3) -> #VALUE!
B55: US&Can | C55: Gift Card | D55: =countifs(#REF!,$B55,'Attainment Query Data'!$H:$H,$C55,'Attainment Query Data'!$G:$G,">"&D$2,'Attainment Query Data'!$G:$G,"<="&D$3) -> #VALUE! | E55: =countifs(#REF!,$B55,'Attainment Query Data'!$H:$H,$C55,'Attainment Query Data'!$G:$G,">"&E$2,'Attainment Query Data'!$G:$G,"<="&E$3) -> #VALUE! | F55: =countifs(#REF!,$B55,'Attainment Query Data'!$H:$H,$C55,'Attainment Query Data'!$G:$G,">"&F$2,'Attainment Query Data'!$G:$G,"<="&F$3) -> #VALUE! | G55: =countifs(#REF!,$B55,'Attainment Query Data'!$H:$H,$C55,'Attainment Query Data'!$G:$G,">"&G$2,'Attainment Query Data'!$G:$G,"<="&G$3) -> #VALUE! | H55: =countifs(#REF!,$B55,'Attainment Query Data'!$H:$H,$C55,'Attainment Query Data'!$G:$G,">"&H$2,'Attainment Query Data'!$G:$G,"<="&H$3) -> #VALUE! | I55: =countifs(#REF!,$B55,'Attainment Query Data'!$H:$H,$C55,'Attainment Query Data'!$G:$G,">"&I$2,'Attainment Query Data'!$G:$G,"<="&I$3) -> #VALUE! | J55: =countifs(#REF!,$B55,'Attainment Query Data'!$H:$H,$C55,'Attainment Query Data'!$G:$G,">"&J$2,'Attainment Query Data'!$G:$G,"<="&J$3) -> #VALUE! | K55: =countifs(#REF!,$B55,'Attainment Query Data'!$H:$H,$C55,'Attainment Query Data'!$G:$G,">"&K$2,'Attainment Query Data'!$G:$G,"<="&K$3) -> #VALUE! | ... W55: =countifs(#REF!,$B55,'Attainment Query Data'!$H:$H,$C55,'Attainment Query Data'!$G:$G,">"&W$2,'Attainment Query Data'!$G:$G,"<="&W$3) -> #VALUE!
C56: Total | D56: =SUM(D50:D55) -> #VALUE! | E56: =SUM(E50:E55) -> #VALUE! | F56: =SUM(F50:F55) -> #VALUE! | G56: =SUM(G50:G55) -> #VALUE! | H56: =SUM(H50:H55) -> #VALUE! | I56: =SUM(I50:I55) -> #VALUE! | J56: =SUM(J50:J55) -> #VALUE! | K56: =SUM(K50:K55) -> #VALUE! | ... W56: =SUM(W50:W55) -> #VALUE!
B59: Mega Region | C59: Product | D59: 2/18 to 2/25 | E59: 2/25 to 3/3 | F59: 3/3 to 3/10 | G59: 3/10 to 3/17 | H59: 3/17 to 3/24 | I59: 3/24 to 3/31 | J59: 3/31 to 4/7 | K59: 4/7 to 4/14 | L59: 4/14 to 4/21 | M59: 4/21 to 4/28 | N59: 4/28 to 5/5 | O59: 5/5 to 5/12 | P59: 5/12 to 5/19 | Q59: 5/19 to 5/26 | R59: 5/26 to 6/2 | S59: 6/2 to 6/9 | T59: 6/9 to 6/16 | U59: 6/16 to 6/23 | V59: 6/23 to 6/30 | W59: 7/1 to 7/7
B60: E4B - US&Can | C60: Travel | D60: =countifs(#REF!,$B60,'Attainment Query Data'!$H:$H,$C60,'Attainment Query Data'!$G:$G,">"&D$2,'Attainment Query Data'!$G:$G,"<="&D$3) -> #VALUE! | E60: =countifs(#REF!,$B60,'Attainment Query Data'!$H:$H,$C60,'Attainment Query Data'!$G:$G,">"&E$2,'Attainment Query Data'!$G:$G,"<="&E$3) -> #VALUE! | F60: =countifs(#REF!,$B60,'Attainment Query Data'!$H:$H,$C60,'Attainment Query Data'!$G:$G,">"&F$2,'Attainment Query Data'!$G:$G,"<="&F$3) -> #VALUE! | G60: =countifs(#REF!,$B60,'Attainment Query Data'!$H:$H,$C60,'Attainment Query Data'!$G:$G,">"&G$2,'Attainment Query Data'!$G:$G,"<="&G$3) -> #VALUE! | H60: =countifs(#REF!,$B60,'Attainment Query Data'!$H:$H,$C60,'Attainment Query Data'!$G:$G,">"&H$2,'Attainment Query Data'!$G:$G,"<="&H$3) -> #VALUE! | I60: =countifs(#REF!,$B60,'Attainment Query Data'!$H:$H,$C60,'Attainment Query Data'!$G:$G,">"&I$2,'Attainment Query Data'!$G:$G,"<="&I$3) -> #VALUE! | J60: =countifs(#REF!,$B60,'Attainment Query Data'!$H:$H,$C60,'Attainment Query Data'!$G:$G,">"&J$2,'Attainment Query Data'!$G:$G,"<="&J$3) -> #VALUE! | K60: =countifs(#REF!,$B60,'Attainment Query Data'!$H:$H,$C60,'Attainment Query Data'!$G:$G,">"&K$2,'Attainment Query Data'!$G:$G,"<="&K$3) -> #VALUE! | ... W60: =countifs(#REF!,$B60,'Attainment Query Data'!$H:$H,$C60,'Attainment Query Data'!$G:$G,">"&W$2,'Attainment Query Data'!$G:$G,"<="&W$3) -> #VALUE!
B61: E4B - US&Can | C61: Vouchers | D61: =countifs(#REF!,$B61,'Attainment Query Data'!$H:$H,$C61,'Attainment Query Data'!$G:$G,">"&D$2,'Attainment Query Data'!$G:$G,"<="&D$3) -> #VALUE! | E61: =countifs(#REF!,$B61,'Attainment Query Data'!$H:$H,$C61,'Attainment Query Data'!$G:$G,">"&E$2,'Attainment Query Data'!$G:$G,"<="&E$3) -> #VALUE! | F61: =countifs(#REF!,$B61,'Attainment Query Data'!$H:$H,$C61,'Attainment Query Data'!$G:$G,">"&F$2,'Attainment Query Data'!$G:$G,"<="&F$3) -> #VALUE! | G61: =countifs(#REF!,$B61,'Attainment Query Data'!$H:$H,$C61,'Attainment Query Data'!$G:$G,">"&G$2,'Attainment Query Data'!$G:$G,"<="&G$3) -> #VALUE! | H61: =countifs(#REF!,$B61,'Attainment Query Data'!$H:$H,$C61,'Attainment Query Data'!$G:$G,">"&H$2,'Attainment Query Data'!$G:$G,"<="&H$3) -> #VALUE! | I61: =countifs(#REF!,$B61,'Attainment Query Data'!$H:$H,$C61,'Attainment Query Data'!$G:$G,">"&I$2,'Attainment Query Data'!$G:$G,"<="&I$3) -> #VALUE! | J61: =countifs(#REF!,$B61,'Attainment Query Data'!$H:$H,$C61,'Attainment Query Data'!$G:$G,">"&J$2,'Attainment Query Data'!$G:$G,"<="&J$3) -> #VALUE! | K61: =countifs(#REF!,$B61,'Attainment Query Data'!$H:$H,$C61,'Attainment Query Data'!$G:$G,">"&K$2,'Attainment Query Data'!$G:$G,"<="&K$3) -> #VALUE! | ... W61: =countifs(#REF!,$B61,'Attainment Query Data'!$H:$H,$C61,'Attainment Query Data'!$G:$G,">"&W$2,'Attainment Query Data'!$G:$G,"<="&W$3) -> #VALUE!
B62: E4B - US&Can | C62: E4B Vouchers | D62: =countifs(#REF!,$B62,'Attainment Query Data'!$H:$H,$C62,'Attainment Query Data'!$G:$G,">"&D$2,'Attainment Query Data'!$G:$G,"<="&D$3) -> #VALUE! | E62: =countifs(#REF!,$B62,'Attainment Query Data'!$H:$H,$C62,'Attainment Query Data'!$G:$G,">"&E$2,'Attainment Query Data'!$G:$G,"<="&E$3) -> #VALUE! | F62: =countifs(#REF!,$B62,'Attainment Query Data'!$H:$H,$C62,'Attainment Query Data'!$G:$G,">"&F$2,'Attainment Query Data'!$G:$G,"<="&F$3) -> #VALUE! | G62: =countifs(#REF!,$B62,'Attainment Query Data'!$H:$H,$C62,'Attainment Query Data'!$G:$G,">"&G$2,'Attainment Query Data'!$G:$G,"<="&G$3) -> #VALUE! | H62: =countifs(#REF!,$B62,'Attainment Query Data'!$H:$H,$C62,'Attainment Query Data'!$G:$G,">"&H$2,'Attainment Query Data'!$G:$G,"<="&H$3) -> #VALUE! | I62: =countifs(#REF!,$B62,'Attainment Query Data'!$H:$H,$C62,'Attainment Query Data'!$G:$G,">"&I$2,'Attainment Query Data'!$G:$G,"<="&I$3) -> #VALUE! | J62: =countifs(#REF!,$B62,'Attainment Query Data'!$H:$H,$C62,'Attainment Query Data'!$G:$G,">"&J$2,'Attainment Query Data'!$G:$G,"<="&J$3) -> #VALUE! | K62: =countifs(#REF!,$B62,'Attainment Query Data'!$H:$H,$C62,'Attainment Query Data'!$G:$G,">"&K$2,'Attainment Query Data'!$G:$G,"<="&K$3) -> #VALUE! | ... W62: =countifs(#REF!,$B62,'Attainment Query Data'!$H:$H,$C62,'Attainment Query Data'!$G:$G,">"&W$2,'Attainment Query Data'!$G:$G,"<="&W$3) -> #VALUE!
B63: E4B - US&Can | C63: Central | D63: =countifs(#REF!,$B63,'Attainment Query Data'!$H:$H,$C63,'Attainment Query Data'!$G:$G,">"&D$2,'Attainment Query Data'!$G:$G,"<="&D$3) -> #VALUE! | E63: =countifs(#REF!,$B63,'Attainment Query Data'!$H:$H,$C63,'Attainment Query Data'!$G:$G,">"&E$2,'Attainment Query Data'!$G:$G,"<="&E$3) -> #VALUE! | F63: =countifs(#REF!,$B63,'Attainment Query Data'!$H:$H,$C63,'Attainment Query Data'!$G:$G,">"&F$2,'Attainment Query Data'!$G:$G,"<="&F$3) -> #VALUE! | G63: =countifs(#REF!,$B63,'Attainment Query Data'!$H:$H,$C63,'Attainment Query Data'!$G:$G,">"&G$2,'Attainment Query Data'!$G:$G,"<="&G$3) -> #VALUE! | H63: =countifs(#REF!,$B63,'Attainment Query Data'!$H:$H,$C63,'Attainment Query Data'!$G:$G,">"&H$2,'Attainment Query Data'!$G:$G,"<="&H$3) -> #VALUE! | I63: =countifs(#REF!,$B63,'Attainment Query Data'!$H:$H,$C63,'Attainment Query Data'!$G:$G,">"&I$2,'Attainment Query Data'!$G:$G,"<="&I$3) -> #VALUE! | J63: =countifs(#REF!,$B63,'Attainment Query Data'!$H:$H,$C63,'Attainment Query Data'!$G:$G,">"&J$2,'Attainment Query Data'!$G:$G,"<="&J$3) -> #VALUE! | K63: =countifs(#REF!,$B63,'Attainment Query Data'!$H:$H,$C63,'Attainment Query Data'!$G:$G,">"&K$2,'Attainment Query Data'!$G:$G,"<="&K$3) -> #VALUE! | ... W63: =countifs(#REF!,$B63,'Attainment Query Data'!$H:$H,$C63,'Attainment Query Data'!$G:$G,">"&W$2,'Attainment Query Data'!$G:$G,"<="&W$3) -> #VALUE!
B64: E4B - US&Can | C64: Eats | D64: =countifs(#REF!,$B64,'Attainment Query Data'!$H:$H,$C64,'Attainment Query Data'!$G:$G,">"&D$2,'Attainment Query Data'!$G:$G,"<="&D$3) -> #VALUE! | E64: =countifs(#REF!,$B64,'Attainment Query Data'!$H:$H,$C64,'Attainment Query Data'!$G:$G,">"&E$2,'Attainment Query Data'!$G:$G,"<="&E$3) -> #VALUE! | F64: =countifs(#REF!,$B64,'Attainment Query Data'!$H:$H,$C64,'Attainment Query Data'!$G:$G,">"&F$2,'Attainment Query Data'!$G:$G,"<="&F$3) -> #VALUE! | G64: =countifs(#REF!,$B64,'Attainment Query Data'!$H:$H,$C64,'Attainment Query Data'!$G:$G,">"&G$2,'Attainment Query Data'!$G:$G,"<="&G$3) -> #VALUE! | H64: =countifs(#REF!,$B64,'Attainment Query Data'!$H:$H,$C64,'Attainment Query Data'!$G:$G,">"&H$2,'Attainment Query Data'!$G:$G,"<="&H$3) -> #VALUE! | I64: =countifs(#REF!,$B64,'Attainment Query Data'!$H:$H,$C64,'Attainment Query Data'!$G:$G,">"&I$2,'Attainment Query Data'!$G:$G,"<="&I$3) -> #VALUE! | J64: =countifs(#REF!,$B64,'Attainment Query Data'!$H:$H,$C64,'Attainment Query Data'!$G:$G,">"&J$2,'Attainment Query Data'!$G:$G,"<="&J$3) -> #VALUE! | K64: =countifs(#REF!,$B64,'Attainment Query Data'!$H:$H,$C64,'Attainment Query Data'!$G:$G,">"&K$2,'Attainment Query Data'!$G:$G,"<="&K$3) -> #VALUE! | ... W64: =countifs(#REF!,$B64,'Attainment Query Data'!$H:$H,$C64,'Attainment Query Data'!$G:$G,">"&W$2,'Attainment Query Data'!$G:$G,"<="&W$3) -> #VALUE!
B65: E4B - US&Can | C65: Gift Card | D65: =countifs(#REF!,$B65,'Attainment Query Data'!$H:$H,$C65,'Attainment Query Data'!$G:$G,">"&D$2,'Attainment Query Data'!$G:$G,"<="&D$3) -> #VALUE! | E65: =countifs(#REF!,$B65,'Attainment Query Data'!$H:$H,$C65,'Attainment Query Data'!$G:$G,">"&E$2,'Attainment Query Data'!$G:$G,"<="&E$3) -> #VALUE! | F65: =countifs(#REF!,$B65,'Attainment Query Data'!$H:$H,$C65,'Attainment Query Data'!$G:$G,">"&F$2,'Attainment Query Data'!$G:$G,"<="&F$3) -> #VALUE! | G65: =countifs(#REF!,$B65,'Attainment Query Data'!$H:$H,$C65,'Attainment Query Data'!$G:$G,">"&G$2,'Attainment Query Data'!$G:$G,"<="&G$3) -> #VALUE! | H65: =countifs(#REF!,$B65,'Attainment Query Data'!$H:$H,$C65,'Attainment Query Data'!$G:$G,">"&H$2,'Attainment Query Data'!$G:$G,"<="&H$3) -> #VALUE! | I65: =countifs(#REF!,$B65,'Attainment Query Data'!$H:$H,$C65,'Attainment Query Data'!$G:$G,">"&I$2,'Attainment Query Data'!$G:$G,"<="&I$3) -> #VALUE! | J65: =countifs(#REF!,$B65,'Attainment Query Data'!$H:$H,$C65,'Attainment Query Data'!$G:$G,">"&J$2,'Attainment Query Data'!$G:$G,"<="&J$3) -> #VALUE! | K65: =countifs(#REF!,$B65,'Attainment Query Data'!$H:$H,$C65,'Attainment Query Data'!$G:$G,">"&K$2,'Attainment Query Data'!$G:$G,"<="&K$3) -> #VALUE! | ... W65: =countifs(#REF!,$B65,'Attainment Query Data'!$H:$H,$C65,'Attainment Query Data'!$G:$G,">"&W$2,'Attainment Query Data'!$G:$G,"<="&W$3) -> #VALUE!
C66: Total | D66: =SUM(D60:D65) -> #VALUE! | E66: =SUM(E60:E65) -> #VALUE! | F66: =SUM(F60:F65) -> #VALUE! | G66: =SUM(G60:G65) -> #VALUE! | H66: =SUM(H60:H65) -> #VALUE! | I66: =SUM(I60:I65) -> #VALUE! | J66: =SUM(J60:J65) -> #VALUE! | K66: =SUM(K60:K65) -> #VALUE! | ... W66: =SUM(W60:W65) -> #VALUE!
B69: Mega Region | C69: Product | D69: 2/18 to 2/25 | E69: 2/25 to 3/3 | F69: 3/3 to 3/10 | G69: 3/10 to 3/17 | H69: 3/17 to 3/24 | I69: 3/24 to 3/31 | J69: 3/31 to 4/7 | K69: 4/7 to 4/14 | L69: 4/14 to 4/21 | M69: 4/21 to 4/28 | N69: 4/28 to 5/5 | O69: 5/5 to 5/12 | P69: 5/12 to 5/19 | Q69: 5/19 to 5/26 | R69: 5/26 to 6/2 | S69: 6/2 to 6/9 | T69: 6/9 to 6/16 | U69: 6/16 to 6/23 | V69: 6/23 to 6/30 | W69: 7/1 to 7/7
B70: E4B - Europe | C70: Travel | D70: =countifs(#REF!,$B70,'Attainment Query Data'!$H:$H,$C70,'Attainment Query Data'!$G:$G,">"&D$2,'Attainment Query Data'!$G:$G,"<="&D$3) -> #VALUE! | E70: =countifs(#REF!,$B70,'Attainment Query Data'!$H:$H,$C70,'Attainment Query Data'!$G:$G,">"&E$2,'Attainment Query Data'!$G:$G,"<="&E$3) -> #VALUE! | F70: =countifs(#REF!,$B70,'Attainment Query Data'!$H:$H,$C70,'Attainment Query Data'!$G:$G,">"&F$2,'Attainment Query Data'!$G:$G,"<="&F$3) -> #VALUE! | G70: =countifs(#REF!,$B70,'Attainment Query Data'!$H:$H,$C70,'Attainment Query Data'!$G:$G,">"&G$2,'Attainment Query Data'!$G:$G,"<="&G$3) -> #VALUE! | H70: =countifs(#REF!,$B70,'Attainment Query Data'!$H:$H,$C70,'Attainment Query Data'!$G:$G,">"&H$2,'Attainment Query Data'!$G:$G,"<="&H$3) -> #VALUE! | I70: =countifs(#REF!,$B70,'Attainment Query Data'!$H:$H,$C70,'Attainment Query Data'!$G:$G,">"&I$2,'Attainment Query Data'!$G:$G,"<="&I$3) -> #VALUE! | J70: =countifs(#REF!,$B70,'Attainment Query Data'!$H:$H,$C70,'Attainment Query Data'!$G:$G,">"&J$2,'Attainment Query Data'!$G:$G,"<="&J$3) -> #VALUE! | K70: =countifs(#REF!,$B70,'Attainment Query Data'!$H:$H,$C70,'Attainment Query Data'!$G:$G,">"&K$2,'Attainment Query Data'!$G:$G,"<="&K$3) -> #VALUE! | ... W70: =countifs(#REF!,$B70,'Attainment Query Data'!$H:$H,$C70,'Attainment Query Data'!$G:$G,">"&W$2,'Attainment Query Data'!$G:$G,"<="&W$3) -> #VALUE!
B71: E4B - Europe | C71: Vouchers | D71: =countifs(#REF!,$B71,'Attainment Query Data'!$H:$H,$C71,'Attainment Query Data'!$G:$G,">"&D$2,'Attainment Query Data'!$G:$G,"<="&D$3) -> #VALUE! | E71: =countifs(#REF!,$B71,'Attainment Query Data'!$H:$H,$C71,'Attainment Query Data'!$G:$G,">"&E$2,'Attainment Query Data'!$G:$G,"<="&E$3) -> #VALUE! | F71: =countifs(#REF!,$B71,'Attainment Query Data'!$H:$H,$C71,'Attainment Query Data'!$G:$G,">"&F$2,'Attainment Query Data'!$G:$G,"<="&F$3) -> #VALUE! | G71: =countifs(#REF!,$B71,'Attainment Query Data'!$H:$H,$C71,'Attainment Query Data'!$G:$G,">"&G$2,'Attainment Query Data'!$G:$G,"<="&G$3) -> #VALUE! | H71: =countifs(#REF!,$B71,'Attainment Query Data'!$H:$H,$C71,'Attainment Query Data'!$G:$G,">"&H$2,'Attainment Query Data'!$G:$G,"<="&H$3) -> #VALUE! | I71: =countifs(#REF!,$B71,'Attainment Query Data'!$H:$H,$C71,'Attainment Query Data'!$G:$G,">"&I$2,'Attainment Query Data'!$G:$G,"<="&I$3) -> #VALUE! | J71: =countifs(#REF!,$B71,'Attainment Query Data'!$H:$H,$C71,'Attainment Query Data'!$G:$G,">"&J$2,'Attainment Query Data'!$G:$G,"<="&J$3) -> #VALUE! | K71: =countifs(#REF!,$B71,'Attainment Query Data'!$H:$H,$C71,'Attainment Query Data'!$G:$G,">"&K$2,'Attainment Query Data'!$G:$G,"<="&K$3) -> #VALUE! | ... W71: =countifs(#REF!,$B71,'Attainment Query Data'!$H:$H,$C71,'Attainment Query Data'!$G:$G,">"&W$2,'Attainment Query Data'!$G:$G,"<="&W$3) -> #VALUE!
B72: E4B - Europe | C72: E4B Vouchers | D72: =countifs(#REF!,$B72,'Attainment Query Data'!$H:$H,$C72,'Attainment Query Data'!$G:$G,">"&D$2,'Attainment Query Data'!$G:$G,"<="&D$3) -> #VALUE! | E72: =countifs(#REF!,$B72,'Attainment Query Data'!$H:$H,$C72,'Attainment Query Data'!$G:$G,">"&E$2,'Attainment Query Data'!$G:$G,"<="&E$3) -> #VALUE! | F72: =countifs(#REF!,$B72,'Attainment Query Data'!$H:$H,$C72,'Attainment Query Data'!$G:$G,">"&F$2,'Attainment Query Data'!$G:$G,"<="&F$3) -> #VALUE! | G72: =countifs(#REF!,$B72,'Attainment Query Data'!$H:$H,$C72,'Attainment Query Data'!$G:$G,">"&G$2,'Attainment Query Data'!$G:$G,"<="&G$3) -> #VALUE! | H72: =countifs(#REF!,$B72,'Attainment Query Data'!$H:$H,$C72,'Attainment Query Data'!$G:$G,">"&H$2,'Attainment Query Data'!$G:$G,"<="&H$3) -> #VALUE! | I72: =countifs(#REF!,$B72,'Attainment Query Data'!$H:$H,$C72,'Attainment Query Data'!$G:$G,">"&I$2,'Attainment Query Data'!$G:$G,"<="&I$3) -> #VALUE! | J72: =countifs(#REF!,$B72,'Attainment Query Data'!$H:$H,$C72,'Attainment Query Data'!$G:$G,">"&J$2,'Attainment Query Data'!$G:$G,"<="&J$3) -> #VALUE! | K72: =countifs(#REF!,$B72,'Attainment Query Data'!$H:$H,$C72,'Attainment Query Data'!$G:$G,">"&K$2,'Attainment Query Data'!$G:$G,"<="&K$3) -> #VALUE! | ... W72: =countifs(#REF!,$B72,'Attainment Query Data'!$H:$H,$C72,'Attainment Query Data'!$G:$G,">"&W$2,'Attainment Query Data'!$G:$G,"<="&W$3) -> #VALUE!
B73: E4B - Europe | C73: Central | D73: =countifs(#REF!,$B73,'Attainment Query Data'!$H:$H,$C73,'Attainment Query Data'!$G:$G,">"&D$2,'Attainment Query Data'!$G:$G,"<="&D$3) -> #VALUE! | E73: =countifs(#REF!,$B73,'Attainment Query Data'!$H:$H,$C73,'Attainment Query Data'!$G:$G,">"&E$2,'Attainment Query Data'!$G:$G,"<="&E$3) -> #VALUE! | F73: =countifs(#REF!,$B73,'Attainment Query Data'!$H:$H,$C73,'Attainment Query Data'!$G:$G,">"&F$2,'Attainment Query Data'!$G:$G,"<="&F$3) -> #VALUE! | G73: =countifs(#REF!,$B73,'Attainment Query Data'!$H:$H,$C73,'Attainment Query Data'!$G:$G,">"&G$2,'Attainment Query Data'!$G:$G,"<="&G$3) -> #VALUE! | H73: =countifs(#REF!,$B73,'Attainment Query Data'!$H:$H,$C73,'Attainment Query Data'!$G:$G,">"&H$2,'Attainment Query Data'!$G:$G,"<="&H$3) -> #VALUE! | I73: =countifs(#REF!,$B73,'Attainment Query Data'!$H:$H,$C73,'Attainment Query Data'!$G:$G,">"&I$2,'Attainment Query Data'!$G:$G,"<="&I$3) -> #VALUE! | J73: =countifs(#REF!,$B73,'Attainment Query Data'!$H:$H,$C73,'Attainment Query Data'!$G:$G,">"&J$2,'Attainment Query Data'!$G:$G,"<="&J$3) -> #VALUE! | K73: =countifs(#REF!,$B73,'Attainment Query Data'!$H:$H,$C73,'Attainment Query Data'!$G:$G,">"&K$2,'Attainment Query Data'!$G:$G,"<="&K$3) -> #VALUE! | ... W73: =countifs(#REF!,$B73,'Attainment Query Data'!$H:$H,$C73,'Attainment Query Data'!$G:$G,">"&W$2,'Attainment Query Data'!$G:$G,"<="&W$3) -> #VALUE!
B74: E4B - Europe | C74: Eats | D74: =countifs(#REF!,$B74,'Attainment Query Data'!$H:$H,$C74,'Attainment Query Data'!$G:$G,">"&D$2,'Attainment Query Data'!$G:$G,"<="&D$3) -> #VALUE! | E74: =countifs(#REF!,$B74,'Attainment Query Data'!$H:$H,$C74,'Attainment Query Data'!$G:$G,">"&E$2,'Attainment Query Data'!$G:$G,"<="&E$3) -> #VALUE! | F74: =countifs(#REF!,$B74,'Attainment Query Data'!$H:$H,$C74,'Attainment Query Data'!$G:$G,">"&F$2,'Attainment Query Data'!$G:$G,"<="&F$3) -> #VALUE! | G74: =countifs(#REF!,$B74,'Attainment Query Data'!$H:$H,$C74,'Attainment Query Data'!$G:$G,">"&G$2,'Attainment Query Data'!$G:$G,"<="&G$3) -> #VALUE! | H74: =countifs(#REF!,$B74,'Attainment Query Data'!$H:$H,$C74,'Attainment Query Data'!$G:$G,">"&H$2,'Attainment Query Data'!$G:$G,"<="&H$3) -> #VALUE! | I74: =countifs(#REF!,$B74,'Attainment Query Data'!$H:$H,$C74,'Attainment Query Data'!$G:$G,">"&I$2,'Attainment Query Data'!$G:$G,"<="&I$3) -> #VALUE! | J74: =countifs(#REF!,$B74,'Attainment Query Data'!$H:$H,$C74,'Attainment Query Data'!$G:$G,">"&J$2,'Attainment Query Data'!$G:$G,"<="&J$3) -> #VALUE! | K74: =countifs(#REF!,$B74,'Attainment Query Data'!$H:$H,$C74,'Attainment Query Data'!$G:$G,">"&K$2,'Attainment Query Data'!$G:$G,"<="&K$3) -> #VALUE! | ... W74: =countifs(#REF!,$B74,'Attainment Query Data'!$H:$H,$C74,'Attainment Query Data'!$G:$G,">"&W$2,'Attainment Query Data'!$G:$G,"<="&W$3) -> #VALUE!
B75: E4B - Europe | C75: Gift Card | D75: =countifs(#REF!,$B75,'Attainment Query Data'!$H:$H,$C75,'Attainment Query Data'!$G:$G,">"&D$2,'Attainment Query Data'!$G:$G,"<="&D$3) -> #VALUE! | E75: =countifs(#REF!,$B75,'Attainment Query Data'!$H:$H,$C75,'Attainment Query Data'!$G:$G,">"&E$2,'Attainment Query Data'!$G:$G,"<="&E$3) -> #VALUE! | F75: =countifs(#REF!,$B75,'Attainment Query Data'!$H:$H,$C75,'Attainment Query Data'!$G:$G,">"&F$2,'Attainment Query Data'!$G:$G,"<="&F$3) -> #VALUE! | G75: =countifs(#REF!,$B75,'Attainment Query Data'!$H:$H,$C75,'Attainment Query Data'!$G:$G,">"&G$2,'Attainment Query Data'!$G:$G,"<="&G$3) -> #VALUE! | H75: =countifs(#REF!,$B75,'Attainment Query Data'!$H:$H,$C75,'Attainment Query Data'!$G:$G,">"&H$2,'Attainment Query Data'!$G:$G,"<="&H$3) -> #VALUE! | I75: =countifs(#REF!,$B75,'Attainment Query Data'!$H:$H,$C75,'Attainment Query Data'!$G:$G,">"&I$2,'Attainment Query Data'!$G:$G,"<="&I$3) -> #VALUE! | J75: =countifs(#REF!,$B75,'Attainment Query Data'!$H:$H,$C75,'Attainment Query Data'!$G:$G,">"&J$2,'Attainment Query Data'!$G:$G,"<="&J$3) -> #VALUE! | K75: =countifs(#REF!,$B75,'Attainment Query Data'!$H:$H,$C75,'Attainment Query Data'!$G:$G,">"&K$2,'Attainment Query Data'!$G:$G,"<="&K$3) -> #VALUE! | ... W75: =countifs(#REF!,$B75,'Attainment Query Data'!$H:$H,$C75,'Attainment Query Data'!$G:$G,">"&W$2,'Attainment Query Data'!$G:$G,"<="&W$3) -> #VALUE!
C76: Total | D76: =SUM(D70:D75) -> #VALUE! | E76: =SUM(E70:E75) -> #VALUE! | F76: =SUM(F70:F75) -> #VALUE! | G76: =SUM(G70:G75) -> #VALUE! | H76: =SUM(H70:H75) -> #VALUE! | I76: =SUM(I70:I75) -> #VALUE! | J76: =SUM(J70:J75) -> #VALUE! | K76: =SUM(K70:K75) -> #VALUE! | ... W76: =SUM(W70:W75) -> #VALUE!
B79: Mega Region | C79: Product | D79: 2/18 to 2/25 | E79: 2/25 to 3/3 | F79: 3/3 to 3/10 | G79: 3/10 to 3/17 | H79: 3/17 to 3/24 | I79: 3/24 to 3/31 | J79: 3/31 to 4/7 | K79: 4/7 to 4/14 | L79: 4/14 to 4/21 | M79: 4/21 to 4/28 | N79: 4/28 to 5/5 | O79: 5/5 to 5/12 | P79: 5/12 to 5/19 | Q79: 5/19 to 5/26 | R79: 5/26 to 6/2 | S79: 6/2 to 6/9 | T79: 6/9 to 6/16 | U79: 6/16 to 6/23 | V79: 6/23 to 6/30 | W79: 7/1 to 7/7
B80: Health - US&Can | C80: Health | D80: =countifs(#REF!,$B80,'Attainment Query Data'!$H:$H,$C80,'Attainment Query Data'!$G:$G,">"&D$2,'Attainment Query Data'!$G:$G,"<="&D$3) -> #VALUE! | E80: =countifs(#REF!,$B80,'Attainment Query Data'!$H:$H,$C80,'Attainment Query Data'!$G:$G,">"&E$2,'Attainment Query Data'!$G:$G,"<="&E$3) -> #VALUE! | F80: =countifs(#REF!,$B80,'Attainment Query Data'!$H:$H,$C80,'Attainment Query Data'!$G:$G,">"&F$2,'Attainment Query Data'!$G:$G,"<="&F$3) -> #VALUE! | G80: =countifs(#REF!,$B80,'Attainment Query Data'!$H:$H,$C80,'Attainment Query Data'!$G:$G,">"&G$2,'Attainment Query Data'!$G:$G,"<="&G$3) -> #VALUE! | H80: =countifs(#REF!,$B80,'Attainment Query Data'!$H:$H,$C80,'Attainment Query Data'!$G:$G,">"&H$2,'Attainment Query Data'!$G:$G,"<="&H$3) -> #VALUE! | I80: =countifs(#REF!,$B80,'Attainment Query Data'!$H:$H,$C80,'Attainment Query Data'!$G:$G,">"&I$2,'Attainment Query Data'!$G:$G,"<="&I$3) -> #VALUE! | J80: =countifs(#REF!,$B80,'Attainment Query Data'!$H:$H,$C80,'Attainment Query Data'!$G:$G,">"&J$2,'Attainment Query Data'!$G:$G,"<="&J$3) -> #VALUE! | K80: =countifs(#REF!,$B80,'Attainment Query Data'!$H:$H,$C80,'Attainment Query Data'!$G:$G,">"&K$2,'Attainment Query Data'!$G:$G,"<="&K$3) -> #VALUE! | ... W80: =countifs(#REF!,$B80,'Attainment Query Data'!$H:$H,$C80,'Attainment Query Data'!$G:$G,">"&W$2,'Attainment Query Data'!$G:$G,"<="&W$3) -> #VALUE!
B81: Health - US&Can | C81: Travel | D81: =countifs(#REF!,$B81,'Attainment Query Data'!$H:$H,$C81,'Attainment Query Data'!$G:$G,">"&D$2,'Attainment Query Data'!$G:$G,"<="&D$3) -> #VALUE! | E81: =countifs(#REF!,$B81,'Attainment Query Data'!$H:$H,$C81,'Attainment Query Data'!$G:$G,">"&E$2,'Attainment Query Data'!$G:$G,"<="&E$3) -> #VALUE! | F81: =countifs(#REF!,$B81,'Attainment Query Data'!$H:$H,$C81,'Attainment Query Data'!$G:$G,">"&F$2,'Attainment Query Data'!$G:$G,"<="&F$3) -> #VALUE! | G81: =countifs(#REF!,$B81,'Attainment Query Data'!$H:$H,$C81,'Attainment Query Data'!$G:$G,">"&G$2,'Attainment Query Data'!$G:$G,"<="&G$3) -> #VALUE! | H81: =countifs(#REF!,$B81,'Attainment Query Data'!$H:$H,$C81,'Attainment Query Data'!$G:$G,">"&H$2,'Attainment Query Data'!$G:$G,"<="&H$3) -> #VALUE! | I81: =countifs(#REF!,$B81,'Attainment Query Data'!$H:$H,$C81,'Attainment Query Data'!$G:$G,">"&I$2,'Attainment Query Data'!$G:$G,"<="&I$3) -> #VALUE! | J81: =countifs(#REF!,$B81,'Attainment Query Data'!$H:$H,$C81,'Attainment Query Data'!$G:$G,">"&J$2,'Attainment Query Data'!$G:$G,"<="&J$3) -> #VALUE! | K81: =countifs(#REF!,$B81,'Attainment Query Data'!$H:$H,$C81,'Attainment Query Data'!$G:$G,">"&K$2,'Attainment Query Data'!$G:$G,"<="&K$3) -> #VALUE! | ... W81: =countifs(#REF!,$B81,'Attainment Query Data'!$H:$H,$C81,'Attainment Query Data'!$G:$G,">"&W$2,'Attainment Query Data'!$G:$G,"<="&W$3) -> #VALUE!
B82: Health - US&Can | C82: Vouchers | D82: =countifs(#REF!,$B82,'Attainment Query Data'!$H:$H,$C82,'Attainment Query Data'!$G:$G,">"&D$2,'Attainment Query Data'!$G:$G,"<="&D$3) -> #VALUE! | E82: =countifs(#REF!,$B82,'Attainment Query Data'!$H:$H,$C82,'Attainment Query Data'!$G:$G,">"&E$2,'Attainment Query Data'!$G:$G,"<="&E$3) -> #VALUE! | F82: =countifs(#REF!,$B82,'Attainment Query Data'!$H:$H,$C82,'Attainment Query Data'!$G:$G,">"&F$2,'Attainment Query Data'!$G:$G,"<="&F$3) -> #VALUE! | G82: =countifs(#REF!,$B82,'Attainment Query Data'!$H:$H,$C82,'Attainment Query Data'!$G:$G,">"&G$2,'Attainment Query Data'!$G:$G,"<="&G$3) -> #VALUE! | H82: =countifs(#REF!,$B82,'Attainment Query Data'!$H:$H,$C82,'Attainment Query Data'!$G:$G,">"&H$2,'Attainment Query Data'!$G:$G,"<="&H$3) -> #VALUE! | I82: =countifs(#REF!,$B82,'Attainment Query Data'!$H:$H,$C82,'Attainment Query Data'!$G:$G,">"&I$2,'Attainment Query Data'!$G:$G,"<="&I$3) -> #VALUE! | J82: =countifs(#REF!,$B82,'Attainment Query Data'!$H:$H,$C82,'Attainment Query Data'!$G:$G,">"&J$2,'Attainment Query Data'!$G:$G,"<="&J$3) -> #VALUE! | K82: =countifs(#REF!,$B82,'Attainment Query Data'!$H:$H,$C82,'Attainment Query Data'!$G:$G,">"&K$2,'Attainment Query Data'!$G:$G,"<="&K$3) -> #VALUE! | ... W82: =countifs(#REF!,$B82,'Attainment Query Data'!$H:$H,$C82,'Attainment Query Data'!$G:$G,">"&W$2,'Attainment Query Data'!$G:$G,"<="&W$3) -> #VALUE!
B83: Health - US&Can | C83: E4B Vouchers | D83: =countifs(#REF!,$B83,'Attainment Query Data'!$H:$H,$C83,'Attainment Query Data'!$G:$G,">"&D$2,'Attainment Query Data'!$G:$G,"<="&D$3) -> #VALUE! | E83: =countifs(#REF!,$B83,'Attainment Query Data'!$H:$H,$C83,'Attainment Query Data'!$G:$G,">"&E$2,'Attainment Query Data'!$G:$G,"<="&E$3) -> #VALUE! | F83: =countifs(#REF!,$B83,'Attainment Query Data'!$H:$H,$C83,'Attainment Query Data'!$G:$G,">"&F$2,'Attainment Query Data'!$G:$G,"<="&F$3) -> #VALUE! | G83: =countifs(#REF!,$B83,'Attainment Query Data'!$H:$H,$C83,'Attainment Query Data'!$G:$G,">"&G$2,'Attainment Query Data'!$G:$G,"<="&G$3) -> #VALUE! | H83: =countifs(#REF!,$B83,'Attainment Query Data'!$H:$H,$C83,'Attainment Query Data'!$G:$G,">"&H$2,'Attainment Query Data'!$G:$G,"<="&H$3) -> #VALUE! | I83: =countifs(#REF!,$B83,'Attainment Query Data'!$H:$H,$C83,'Attainment Query Data'!$G:$G,">"&I$2,'Attainment Query Data'!$G:$G,"<="&I$3) -> #VALUE! | J83: =countifs(#REF!,$B83,'Attainment Query Data'!$H:$H,$C83,'Attainment Query Data'!$G:$G,">"&J$2,'Attainment Query Data'!$G:$G,"<="&J$3) -> #VALUE! | K83: =countifs(#REF!,$B83,'Attainment Query Data'!$H:$H,$C83,'Attainment Query Data'!$G:$G,">"&K$2,'Attainment Query Data'!$G:$G,"<="&K$3) -> #VALUE! | ... W83: =countifs(#REF!,$B83,'Attainment Query Data'!$H:$H,$C83,'Attainment Query Data'!$G:$G,">"&W$2,'Attainment Query Data'!$G:$G,"<="&W$3) -> #VALUE!
B84: Health - US&Can | C84: Central | D84: =countifs(#REF!,$B84,'Attainment Query Data'!$H:$H,$C84,'Attainment Query Data'!$G:$G,">"&D$2,'Attainment Query Data'!$G:$G,"<="&D$3) -> #VALUE! | E84: =countifs(#REF!,$B84,'Attainment Query Data'!$H:$H,$C84,'Attainment Query Data'!$G:$G,">"&E$2,'Attainment Query Data'!$G:$G,"<="&E$3) -> #VALUE! | F84: =countifs(#REF!,$B84,'Attainment Query Data'!$H:$H,$C84,'Attainment Query Data'!$G:$G,">"&F$2,'Attainment Query Data'!$G:$G,"<="&F$3) -> #VALUE! | G84: =countifs(#REF!,$B84,'Attainment Query Data'!$H:$H,$C84,'Attainment Query Data'!$G:$G,">"&G$2,'Attainment Query Data'!$G:$G,"<="&G$3) -> #VALUE! | H84: =countifs(#REF!,$B84,'Attainment Query Data'!$H:$H,$C84,'Attainment Query Data'!$G:$G,">"&H$2,'Attainment Query Data'!$G:$G,"<="&H$3) -> #VALUE! | I84: =countifs(#REF!,$B84,'Attainment Query Data'!$H:$H,$C84,'Attainment Query Data'!$G:$G,">"&I$2,'Attainment Query Data'!$G:$G,"<="&I$3) -> #VALUE! | J84: =countifs(#REF!,$B84,'Attainment Query Data'!$H:$H,$C84,'Attainment Query Data'!$G:$G,">"&J$2,'Attainment Query Data'!$G:$G,"<="&J$3) -> #VALUE! | K84: =countifs(#REF!,$B84,'Attainment Query Data'!$H:$H,$C84,'Attainment Query Data'!$G:$G,">"&K$2,'Attainment Query Data'!$G:$G,"<="&K$3) -> #VALUE! | ... W84: =countifs(#REF!,$B84,'Attainment Query Data'!$H:$H,$C84,'Attainment Query Data'!$G:$G,">"&W$2,'Attainment Query Data'!$G:$G,"<="&W$3) -> #VALUE!
B85: Health - US&Can | C85: Eats | D85: =countifs(#REF!,$B85,'Attainment Query Data'!$H:$H,$C85,'Attainment Query Data'!$G:$G,">"&D$2,'Attainment Query Data'!$G:$G,"<="&D$3) -> #VALUE! | E85: =countifs(#REF!,$B85,'Attainment Query Data'!$H:$H,$C85,'Attainment Query Data'!$G:$G,">"&E$2,'Attainment Query Data'!$G:$G,"<="&E$3) -> #VALUE! | F85: =countifs(#REF!,$B85,'Attainment Query Data'!$H:$H,$C85,'Attainment Query Data'!$G:$G,">"&F$2,'Attainment Query Data'!$G:$G,"<="&F$3) -> #VALUE! | G85: =countifs(#REF!,$B85,'Attainment Query Data'!$H:$H,$C85,'Attainment Query Data'!$G:$G,">"&G$2,'Attainment Query Data'!$G:$G,"<="&G$3) -> #VALUE! | H85: =countifs(#REF!,$B85,'Attainment Query Data'!$H:$H,$C85,'Attainment Query Data'!$G:$G,">"&H$2,'Attainment Query Data'!$G:$G,"<="&H$3) -> #VALUE! | I85: =countifs(#REF!,$B85,'Attainment Query Data'!$H:$H,$C85,'Attainment Query Data'!$G:$G,">"&I$2,'Attainment Query Data'!$G:$G,"<="&I$3) -> #VALUE! | J85: =countifs(#REF!,$B85,'Attainment Query Data'!$H:$H,$C85,'Attainment Query Data'!$G:$G,">"&J$2,'Attainment Query Data'!$G:$G,"<="&J$3) -> #VALUE! | K85: =countifs(#REF!,$B85,'Attainment Query Data'!$H:$H,$C85,'Attainment Query Data'!$G:$G,">"&K$2,'Attainment Query Data'!$G:$G,"<="&K$3) -> #VALUE! | ... W85: =countifs(#REF!,$B85,'Attainment Query Data'!$H:$H,$C85,'Attainment Query Data'!$G:$G,">"&W$2,'Attainment Query Data'!$G:$G,"<="&W$3) -> #VALUE!
B86: Health - US&Can | C86: Gift Card | D86: =countifs(#REF!,$B86,'Attainment Query Data'!$H:$H,$C86,'Attainment Query Data'!$G:$G,">"&D$2,'Attainment Query Data'!$G:$G,"<="&D$3) -> #VALUE! | E86: =countifs(#REF!,$B86,'Attainment Query Data'!$H:$H,$C86,'Attainment Query Data'!$G:$G,">"&E$2,'Attainment Query Data'!$G:$G,"<="&E$3) -> #VALUE! | F86: =countifs(#REF!,$B86,'Attainment Query Data'!$H:$H,$C86,'Attainment Query Data'!$G:$G,">"&F$2,'Attainment Query Data'!$G:$G,"<="&F$3) -> #VALUE! | G86: =countifs(#REF!,$B86,'Attainment Query Data'!$H:$H,$C86,'Attainment Query Data'!$G:$G,">"&G$2,'Attainment Query Data'!$G:$G,"<="&G$3) -> #VALUE! | H86: =countifs(#REF!,$B86,'Attainment Query Data'!$H:$H,$C86,'Attainment Query Data'!$G:$G,">"&H$2,'Attainment Query Data'!$G:$G,"<="&H$3) -> #VALUE! | I86: =countifs(#REF!,$B86,'Attainment Query Data'!$H:$H,$C86,'Attainment Query Data'!$G:$G,">"&I$2,'Attainment Query Data'!$G:$G,"<="&I$3) -> #VALUE! | J86: =countifs(#REF!,$B86,'Attainment Query Data'!$H:$H,$C86,'Attainment Query Data'!$G:$G,">"&J$2,'Attainment Query Data'!$G:$G,"<="&J$3) -> #VALUE! | K86: =countifs(#REF!,$B86,'Attainment Query Data'!$H:$H,$C86,'Attainment Query Data'!$G:$G,">"&K$2,'Attainment Query Data'!$G:$G,"<="&K$3) -> #VALUE! | ... W86: =countifs(#REF!,$B86,'Attainment Query Data'!$H:$H,$C86,'Attainment Query Data'!$G:$G,">"&W$2,'Attainment Query Data'!$G:$G,"<="&W$3) -> #VALUE!
C87: Total | D87: =SUM(D80:D86) -> #VALUE! | E87: =SUM(E80:E86) -> #VALUE! | F87: =SUM(F80:F86) -> #VALUE! | G87: =SUM(G80:G86) -> #VALUE! | H87: =SUM(H80:H86) -> #VALUE! | I87: =SUM(I80:I86) -> #VALUE! | J87: =SUM(J80:J86) -> #VALUE! | K87: =SUM(K80:K86) -> #VALUE! | ... W87: =SUM(W80:W86) -> #VALUE!
B92: Global Summary | J92: 43831
J93: 44012
B94: Mega Region | C94: Travel | D94: Vouchers | E94: E4B Vouchers | F94: Central | G94: Eats | H94: Gift Card | I94: Health | J94: All Products
B95: APACx | C95: =COUNTIFS(#REF!,$B95,'Attainment Query Data'!$H:$H,C$94,'Attainment Query Data'!$G:$G,">"&$J$92,'Attainment Query Data'!$G:$G,"<="&$J$93) -> #VALUE! | D95: =COUNTIFS(#REF!,$B95,'Attainment Query Data'!$H:$H,D$94,'Attainment Query Data'!$G:$G,">"&$J$92,'Attainment Query Data'!$G:$G,"<="&$J$93) -> #VALUE! | E95: =COUNTIFS(#REF!,$B95,'Attainment Query Data'!$H:$H,E$94,'Attainment Query Data'!$G:$G,">"&$J$92,'Attainment Query Data'!$G:$G,"<="&$J$93) -> #VALUE! | F95: =COUNTIFS(#REF!,$B95,'Attainment Query Data'!$H:$H,F$94,'Attainment Query Data'!$G:$G,">"&$J$92,'Attainment Query Data'!$G:$G,"<="&$J$93) -> #VALUE! | G95: =COUNTIFS(#REF!,$B95,'Attainment Query Data'!$H:$H,G$94,'Attainment Query Data'!$G:$G,">"&$J$92,'Attainment Query Data'!$G:$G,"<="&$J$93) -> #VALUE! | H95: =COUNTIFS(#REF!,$B95,'Attainment Query Data'!$H:$H,H$94,'Attainment Query Data'!$G:$G,">"&$J$92,'Attainment Query Data'!$G:$G,"<="&$J$93) -> #VALUE! | I95: =COUNTIFS(#REF!,$B95,'Attainment Query Data'!$H:$H,I$94,'Attainment Query Data'!$G:$G,">"&$J$92,'Attainment Query Data'!$G:$G,"<="&$J$93) -> #VALUE! | J95: =SUM(C95:H95) -> #VALUE!
B96: Europe | C96: =COUNTIFS(#REF!,$B96,'Attainment Query Data'!$H:$H,C$94,'Attainment Query Data'!$G:$G,">"&$J$92,'Attainment Query Data'!$G:$G,"<="&$J$93) -> #VALUE! | D96: =COUNTIFS(#REF!,$B96,'Attainment Query Data'!$H:$H,D$94,'Attainment Query Data'!$G:$G,">"&$J$92,'Attainment Query Data'!$G:$G,"<="&$J$93) -> #VALUE! | E96: =COUNTIFS(#REF!,$B96,'Attainment Query Data'!$H:$H,E$94,'Attainment Query Data'!$G:$G,">"&$J$92,'Attainment Query Data'!$G:$G,"<="&$J$93) -> #VALUE! | F96: =COUNTIFS(#REF!,$B96,'Attainment Query Data'!$H:$H,F$94,'Attainment Query Data'!$G:$G,">"&$J$92,'Attainment Query Data'!$G:$G,"<="&$J$93) -> #VALUE! | G96: =COUNTIFS(#REF!,$B96,'Attainment Query Data'!$H:$H,G$94,'Attainment Query Data'!$G:$G,">"&$J$92,'Attainment Query Data'!$G:$G,"<="&$J$93) -> #VALUE! | H96: =COUNTIFS(#REF!,$B96,'Attainment Query Data'!$H:$H,H$94,'Attainment Query Data'!$G:$G,">"&$J$92,'Attainment Query Data'!$G:$G,"<="&$J$93) -> #VALUE! | I96: =COUNTIFS(#REF!,$B96,'Attainment Query Data'!$H:$H,I$94,'Attainment Query Data'!$G:$G,">"&$J$92,'Attainment Query Data'!$G:$G,"<="&$J$93) -> #VALUE! | J96: =SUM(C96:H96) -> #VALUE!
B97: MEA | C97: =COUNTIFS(#REF!,$B97,'Attainment Query Data'!$H:$H,C$94,'Attainment Query Data'!$G:$G,">"&$J$92,'Attainment Query Data'!$G:$G,"<="&$J$93) -> #VALUE! | D97: =COUNTIFS(#REF!,$B97,'Attainment Query Data'!$H:$H,D$94,'Attainment Query Data'!$G:$G,">"&$J$92,'Attainment Query Data'!$G:$G,"<="&$J$93) -> #VALUE! | E97: =COUNTIFS(#REF!,$B97,'Attainment Query Data'!$H:$H,E$94,'Attainment Query Data'!$G:$G,">"&$J$92,'Attainment Query Data'!$G:$G,"<="&$J$93) -> #VALUE! | F97: =COUNTIFS(#REF!,$B97,'Attainment Query Data'!$H:$H,F$94,'Attainment Query Data'!$G:$G,">"&$J$92,'Attainment Query Data'!$G:$G,"<="&$J$93) -> #VALUE! | G97: =COUNTIFS(#REF!,$B97,'Attainment Query Data'!$H:$H,G$94,'Attainment Query Data'!$G:$G,">"&$J$92,'Attainment Query Data'!$G:$G,"<="&$J$93) -> #VALUE! | H97: =COUNTIFS(#REF!,$B97,'Attainment Query Data'!$H:$H,H$94,'Attainment Query Data'!$G:$G,">"&$J$92,'Attainment Query Data'!$G:$G,"<="&$J$93) -> #VALUE! | I97: =COUNTIFS(#REF!,$B97,'Attainment Query Data'!$H:$H,I$94,'Attainment Query Data'!$G:$G,">"&$J$92,'Attainment Query Data'!$G:$G,"<="&$J$93) -> #VALUE! | J97: =SUM(C97:H97) -> #VALUE!
B98: India | C98: =COUNTIFS(#REF!,$B98,'Attainment Query Data'!$H:$H,C$94,'Attainment Query Data'!$G:$G,">"&$J$92,'Attainment Query Data'!$G:$G,"<="&$J$93) -> #VALUE! | D98: =COUNTIFS(#REF!,$B98,'Attainment Query Data'!$H:$H,D$94,'Attainment Query Data'!$G:$G,">"&$J$92,'Attainment Query Data'!$G:$G,"<="&$J$93) -> #VALUE! | E98: =COUNTIFS(#REF!,$B98,'Attainment Query Data'!$H:$H,E$94,'Attainment Query Data'!$G:$G,">"&$J$92,'Attainment Query Data'!$G:$G,"<="&$J$93) -> #VALUE! | F98: =COUNTIFS(#REF!,$B98,'Attainment Query Data'!$H:$H,F$94,'Attainment Query Data'!$G:$G,">"&$J$92,'Attainment Query Data'!$G:$G,"<="&$J$93) -> #VALUE! | G98: =COUNTIFS(#REF!,$B98,'Attainment Query Data'!$H:$H,G$94,'Attainment Query Data'!$G:$G,">"&$J$92,'Attainment Query Data'!$G:$G,"<="&$J$93) -> #VALUE! | H98: =COUNTIFS(#REF!,$B98,'Attainment Query Data'!$H:$H,H$94,'Attainment Query Data'!$G:$G,">"&$J$92,'Attainment Query Data'!$G:$G,"<="&$J$93) -> #VALUE! | I98: =COUNTIFS(#REF!,$B98,'Attainment Query Data'!$H:$H,I$94,'Attainment Query Data'!$G:$G,">"&$J$92,'Attainment Query Data'!$G:$G,"<="&$J$93) -> #VALUE! | J98: =SUM(C98:H98) -> #VALUE!
B99: LatAm | C99: =COUNTIFS(#REF!,$B99,'Attainment Query Data'!$H:$H,C$94,'Attainment Query Data'!$G:$G,">"&$J$92,'Attainment Query Data'!$G:$G,"<="&$J$93) -> #VALUE! | D99: =COUNTIFS(#REF!,$B99,'Attainment Query Data'!$H:$H,D$94,'Attainment Query Data'!$G:$G,">"&$J$92,'Attainment Query Data'!$G:$G,"<="&$J$93) -> #VALUE! | E99: =COUNTIFS(#REF!,$B99,'Attainment Query Data'!$H:$H,E$94,'Attainment Query Data'!$G:$G,">"&$J$92,'Attainment Query Data'!$G:$G,"<="&$J$93) -> #VALUE! | F99: =COUNTIFS(#REF!,$B99,'Attainment Query Data'!$H:$H,F$94,'Attainment Query Data'!$G:$G,">"&$J$92,'Attainment Query Data'!$G:$G,"<="&$J$93) -> #VALUE! | G99: =COUNTIFS(#REF!,$B99,'Attainment Query Data'!$H:$H,G$94,'Attainment Query Data'!$G:$G,">"&$J$92,'Attainment Query Data'!$G:$G,"<="&$J$93) -> #VALUE! | H99: =COUNTIFS(#REF!,$B99,'Attainment Query Data'!$H:$H,H$94,'Attainment Query Data'!$G:$G,">"&$J$92,'Attainment Query Data'!$G:$G,"<="&$J$93) -> #VALUE! | I99: =COUNTIFS(#REF!,$B99,'Attainment Query Data'!$H:$H,I$94,'Attainment Query Data'!$G:$G,">"&$J$92,'Attainment Query Data'!$G:$G,"<="&$J$93) -> #VALUE! | J99: =SUM(C99:H99) -> #VALUE!
B100: NAMER | C100: =COUNTIFS(#REF!,$B100,'Attainment Query Data'!$H:$H,C$94,'Attainment Query Data'!$G:$G,">"&$J$92,'Attainment Query Data'!$G:$G,"<="&$J$93) -> #VALUE! | D100: =COUNTIFS(#REF!,$B100,'Attainment Query Data'!$H:$H,D$94,'Attainment Query Data'!$G:$G,">"&$J$92,'Attainment Query Data'!$G:$G,"<="&$J$93) -> #VALUE! | E100: =COUNTIFS(#REF!,$B100,'Attainment Query Data'!$H:$H,E$94,'Attainment Query Data'!$G:$G,">"&$J$92,'Attainment Query Data'!$G:$G,"<="&$J$93) -> #VALUE! | F100: =COUNTIFS(#REF!,$B100,'Attainment Query Data'!$H:$H,F$94,'Attainment Query Data'!$G:$G,">"&$J$92,'Attainment Query Data'!$G:$G,"<="&$J$93) -> #VALUE! | G100: =COUNTIFS(#REF!,$B100,'Attainment Query Data'!$H:$H,G$94,'Attainment Query Data'!$G:$G,">"&$J$92,'Attainment Query Data'!$G:$G,"<="&$J$93) -> #VALUE! | H100: =COUNTIFS(#REF!,$B100,'Attainment Query Data'!$H:$H,H$94,'Attainment Query Data'!$G:$G,">"&$J$92,'Attainment Query Data'!$G:$G,"<="&$J$93) -> #VALUE! | I100: =COUNTIFS(#REF!,$B100,'Attainment Query Data'!$H:$H,I$94,'Attainment Query Data'!$G:$G,">"&$J$92,'Attainment Query Data'!$G:$G,"<="&$J$93) -> #VALUE! | J100: =SUM(C100:H100) -> #VALUE!
B101: Total(Platform) | C101: =SUM(C95:C100) -> #VALUE! | D101: =SUM(D95:D100) -> #VALUE! | E101: =SUM(E95:E100) -> #VALUE! | F101: =SUM(F95:F100) -> #VALUE! | G101: =SUM(G95:G100) -> #VALUE! | H101: =SUM(H95:H100) -> #VALUE! | I101: =SUM(I95:I100) -> #VALUE! | J101: =SUM(C101:H101) -> #VALUE!
B103: E4B - NAMER | C103: =COUNTIFS(#REF!,$B103,'Attainment Query Data'!$H:$H,C$94,'Attainment Query Data'!$G:$G,">"&$J$92,'Attainment Query Data'!$G:$G,"<="&$J$93) -> #VALUE! | D103: =COUNTIFS(#REF!,$B103,'Attainment Query Data'!$H:$H,D$94,'Attainment Query Data'!$G:$G,">"&$J$92,'Attainment Query Data'!$G:$G,"<="&$J$93) -> #VALUE! | E103: =COUNTIFS(#REF!,$B103,'Attainment Query Data'!$H:$H,E$94,'Attainment Query Data'!$G:$G,">"&$J$92,'Attainment Query Data'!$G:$G,"<="&$J$93) -> #VALUE! | F103: =COUNTIFS(#REF!,$B103,'Attainment Query Data'!$H:$H,F$94,'Attainment Query Data'!$G:$G,">"&$J$92,'Attainment Query Data'!$G:$G,"<="&$J$93) -> #VALUE! | G103: =COUNTIFS(#REF!,$B103,'Attainment Query Data'!$H:$H,G$94,'Attainment Query Data'!$G:$G,">"&$J$92,'Attainment Query Data'!$G:$G,"<="&$J$93) -> #VALUE! | H103: =COUNTIFS(#REF!,$B103,'Attainment Query Data'!$H:$H,H$94,'Attainment Query Data'!$G:$G,">"&$J$92,'Attainment Query Data'!$G:$G,"<="&$J$93) -> #VALUE! | I103: =COUNTIFS(#REF!,$B103,'Attainment Query Data'!$H:$H,I$94,'Attainment Query Data'!$G:$G,">"&$J$92,'Attainment Query Data'!$G:$G,"<="&$J$93) -> #VALUE! | J103: =SUM(C103:I103) -> #VALUE!
B104: E4B - Europe | C104: =COUNTIFS(#REF!,$B104,'Attainment Query Data'!$H:$H,C$94,'Attainment Query Data'!$G:$G,">"&$J$92,'Attainment Query Data'!$G:$G,"<="&$J$93) -> #VALUE! | D104: =COUNTIFS(#REF!,$B104,'Attainment Query Data'!$H:$H,D$94,'Attainment Query Data'!$G:$G,">"&$J$92,'Attainment Query Data'!$G:$G,"<="&$J$93) -> #VALUE! | E104: =COUNTIFS(#REF!,$B104,'Attainment Query Data'!$H:$H,E$94,'Attainment Query Data'!$G:$G,">"&$J$92,'Attainment Query Data'!$G:$G,"<="&$J$93) -> #VALUE! | F104: =COUNTIFS(#REF!,$B104,'Attainment Query Data'!$H:$H,F$94,'Attainment Query Data'!$G:$G,">"&$J$92,'Attainment Query Data'!$G:$G,"<="&$J$93) -> #VALUE! | G104: =COUNTIFS(#REF!,$B104,'Attainment Query Data'!$H:$H,G$94,'Attainment Query Data'!$G:$G,">"&$J$92,'Attainment Query Data'!$G:$G,"<="&$J$93) -> #VALUE! | H104: =COUNTIFS(#REF!,$B104,'Attainment Query Data'!$H:$H,H$94,'Attainment Query Data'!$G:$G,">"&$J$92,'Attainment Query Data'!$G:$G,"<="&$J$93) -> #VALUE! | I104: =COUNTIFS(#REF!,$B104,'Attainment Query Data'!$H:$H,I$94,'Attainment Query Data'!$G:$G,">"&$J$92,'Attainment Query Data'!$G:$G,"<="&$J$93) -> #VALUE! | J104: =SUM(C104:I104) -> #VALUE!
B105: Guest - UK&I | C105: =COUNTIFS(#REF!,$B105,'Attainment Query Data'!$H:$H,C$94,'Attainment Query Data'!$G:$G,">"&$J$92,'Attainment Query Data'!$G:$G,"<="&$J$93) -> #VALUE! | D105: =COUNTIFS(#REF!,$B105,'Attainment Query Data'!$H:$H,D$94,'Attainment Query Data'!$G:$G,">"&$J$92,'Attainment Query Data'!$G:$G,"<="&$J$93) -> #VALUE! | E105: =COUNTIFS(#REF!,$B105,'Attainment Query Data'!$H:$H,E$94,'Attainment Query Data'!$G:$G,">"&$J$92,'Attainment Query Data'!$G:$G,"<="&$J$93) -> #VALUE! | F105: =COUNTIFS(#REF!,$B105,'Attainment Query Data'!$H:$H,F$94,'Attainment Query Data'!$G:$G,">"&$J$92,'Attainment Query Data'!$G:$G,"<="&$J$93) -> #VALUE! | G105: =COUNTIFS(#REF!,$B105,'Attainment Query Data'!$H:$H,G$94,'Attainment Query Data'!$G:$G,">"&$J$92,'Attainment Query Data'!$G:$G,"<="&$J$93) -> #VALUE! | H105: =COUNTIFS(#REF!,$B105,'Attainment Query Data'!$H:$H,H$94,'Attainment Query Data'!$G:$G,">"&$J$92,'Attainment Query Data'!$G:$G,"<="&$J$93) -> #VALUE! | I105: =COUNTIFS(#REF!,$B105,'Attainment Query Data'!$H:$H,I$94,'Attainment Query Data'!$G:$G,">"&$J$92,'Attainment Query Data'!$G:$G,"<="&$J$93) -> #VALUE! | J105: =SUM(C105:I105) -> #VALUE!
B106: Guest - India | C106: =COUNTIFS(#REF!,$B106,'Attainment Query Data'!$H:$H,C$94,'Attainment Query Data'!$G:$G,">"&$J$92,'Attainment Query Data'!$G:$G,"<="&$J$93) -> #VALUE! | D106: =COUNTIFS(#REF!,$B106,'Attainment Query Data'!$H:$H,D$94,'Attainment Query Data'!$G:$G,">"&$J$92,'Attainment Query Data'!$G:$G,"<="&$J$93) -> #VALUE! | E106: =COUNTIFS(#REF!,$B106,'Attainment Query Data'!$H:$H,E$94,'Attainment Query Data'!$G:$G,">"&$J$92,'Attainment Query Data'!$G:$G,"<="&$J$93) -> #VALUE! | F106: =COUNTIFS(#REF!,$B106,'Attainment Query Data'!$H:$H,F$94,'Attainment Query Data'!$G:$G,">"&$J$92,'Attainment Query Data'!$G:$G,"<="&$J$93) -> #VALUE! | G106: =COUNTIFS(#REF!,$B106,'Attainment Query Data'!$H:$H,G$94,'Attainment Query Data'!$G:$G,">"&$J$92,'Attainment Query Data'!$G:$G,"<="&$J$93) -> #VALUE! | H106: =COUNTIFS(#REF!,$B106,'Attainment Query Data'!$H:$H,H$94,'Attainment Query Data'!$G:$G,">"&$J$92,'Attainment Query Data'!$G:$G,"<="&$J$93) -> #VALUE! | I106: =COUNTIFS(#REF!,$B106,'Attainment Query Data'!$H:$H,I$94,'Attainment Query Data'!$G:$G,">"&$J$92,'Attainment Query Data'!$G:$G,"<="&$J$93) -> #VALUE! | J106: =SUM(C106:I106) -> #VALUE!
B107: Health - NAMER | C107: =COUNTIFS(#REF!,$B107,'Attainment Query Data'!$H:$H,C$94,'Attainment Query Data'!$G:$G,">"&$J$92,'Attainment Query Data'!$G:$G,"<="&$J$93) -> #VALUE! | D107: =COUNTIFS(#REF!,$B107,'Attainment Query Data'!$H:$H,D$94,'Attainment Query Data'!$G:$G,">"&$J$92,'Attainment Query Data'!$G:$G,"<="&$J$93) -> #VALUE! | E107: =COUNTIFS(#REF!,$B107,'Attainment Query Data'!$H:$H,E$94,'Attainment Query Data'!$G:$G,">"&$J$92,'Attainment Query Data'!$G:$G,"<="&$J$93) -> #VALUE! | F107: =COUNTIFS(#REF!,$B107,'Attainment Query Data'!$H:$H,F$94,'Attainment Query Data'!$G:$G,">"&$J$92,'Attainment Query Data'!$G:$G,"<="&$J$93) -> #VALUE! | G107: =COUNTIFS(#REF!,$B107,'Attainment Query Data'!$H:$H,G$94,'Attainment Query Data'!$G:$G,">"&$J$92,'Attainment Query Data'!$G:$G,"<="&$J$93) -> #VALUE! | H107: =COUNTIFS(#REF!,$B107,'Attainment Query Data'!$H:$H,H$94,'Attainment Query Data'!$G:$G,">"&$J$92,'Attainment Query Data'!$G:$G,"<="&$J$93) -> #VALUE! | I107: =COUNTIFS(#REF!,$B107,'Attainment Query Data'!$H:$H,I$94,'Attainment Query Data'!$G:$G,">"&$J$92,'Attainment Query Data'!$G:$G,"<="&$J$93) -> #VALUE! | J107: =SUM(C107:I107) -> #VALUE!
B108: Total(all) | C108: =SUM(C101,C103:C107) -> #VALUE! | D108: =SUM(D101,D103:D107) -> #VALUE! | E108: =SUM(E101,E103:E107) -> #VALUE! | F108: =SUM(F101,F103:F107) -> #VALUE! | G108: =SUM(G101,G103:G107) -> #VALUE! | H108: =SUM(H101,H103:H107) -> #VALUE! | I108: =SUM(I101,I103:I107) -> #VALUE! | J108: =SUM(J101,J103:J107) -> #VALUE!
